Workbook

Sheet Home
A1: DTIA Compliance Knowledge Base
A3: Countries | B3: 9
A4: Acts | B4: 52
A5: Regulators | B5: 70
A6: Topics | B6: 39
A7: Compliance sections | B7: 621
A10: How to use
A11: 1. Open the Query sheet.
A12: 2. Pick a Country, Category, Topic, Data Type, Financial Relevance or Authority — or type a keyword.
A13: 3. Matching sections appear below, each with its Act and page reference for the source document.
A14: 4. The Data Transfer sheet answers cross-border questions: pick two countries and see every relevant act/section from either side of the transfer.
A15: 5. The Compliance Database sheet holds every extracted section; Acts / Regulators / Topics summarise them.

Sheet Query
A1: DTIA Query Engine
A3: Choose filters (leave as 'All' to ignore), then read the results below.
A4: Country | B4: All
A5: Category | B5: All
A6: Topic | B6: All
A7: Data Type | B7: All
A8: Financial Relevance | B8: All
A9: Authority | B9: All
A10: Keyword (free text)
A12: Matching sections (of 621 total): | C12: =Engine!$D$1
A13: Country | B13: Act | C13: Section | D13: Heading | E13: Pages | F13: Category | G13: Financial Relevance | H13: Confidence | I13: Topics | J13: Data Types | K13: Authority | L13: Summary | M13: DTIA Summary | N13: Requirements | O13: Source Quote
A14: =IF(ISNA(MATCH(1,Engine!$C$2:$C$622,0)),"",INDEX('Compliance Database'!$A$2:$A$622,MATCH(1,Engine!$C$2:$C$622,0))) | B14: =IF(ISNA(MATCH(1,Engine!$C$2:$C$622,0)),"",INDEX('Compliance Database'!$B$2:$B$622,MATCH(1,Engine!$C$2:$C$622,0))) | C14: =IF(ISNA(MATCH(1,Engine!$C$2:$C$622,0)),"",INDEX('Compliance Database'!$C$2:$C$622,MATCH(1,Engine!$C$2:$C$622,0))) | D14: =IF(ISNA(MATCH(1,Engine!$C$2:$C$622,0)),"",INDEX('Compliance Database'!$D$2:$D$622,MATCH(1,Engine!$C$2:$C$622,0))) | E14: =IF(ISNA(MATCH(1,Engine!$C$2:$C$622,0)),"",INDEX('Compliance Database'!$E$2:$E$622,MATCH(1,Engine!$C$2:$C$622,0))) | F14: =IF(ISNA(MATCH(1,Engine!$C$2:$C$622,0)),"",INDEX('Compliance Database'!$F$2:$F$622,MATCH(1,Engine!$C$2:$C$622,0))) | G14: =IF(ISNA(MATCH(1,Engine!$C$2:$C$622,0)),"",INDEX('Compliance Database'!$G$2:$G$622,MATCH(1,Engine!$C$2:$C$622,0))) | H14: =IF(ISNA(MATCH(1,Engine!$C$2:$C$622,0)),"",INDEX('Compliance Database'!$H$2:$H$622,MATCH(1,Engine!$C$2:$C$622,0))) | I14: =IF(ISNA(MATCH(1,Engine!$C$2:$C$622,0)),"",INDEX('Compliance Database'!$I$2:$I$622,MATCH(1,Engine!$C$2:$C$622,0))) | J14: =IF(ISNA(MATCH(1,Engine!$C$2:$C$622,0)),"",INDEX('Compliance Database'!$J$2:$J$622,MATCH(1,Engine!$C$2:$C$622,0))) | K14: =IF(ISNA(MATCH(1,Engine!$C$2:$C$622,0)),"",INDEX('Compliance Database'!$K$2:$K$622,MATCH(1,Engine!$C$2:$C$622,0))) | L14: =IF(ISNA(MATCH(1,Engine!$C$2:$C$622,0)),"",INDEX('Compliance Database'!$L$2:$L$622,MATCH(1,Engine!$C$2:$C$622,0))) | M14: =IF(ISNA(MATCH(1,Engine!$C$2:$C$622,0)),"",INDEX('Compliance Database'!$M$2:$M$622,MATCH(1,Engine!$C$2:$C$622,0))) | N14: =IF(ISNA(MATCH(1,Engine!$C$2:$C$622,0)),"",INDEX('Compliance Database'!$N$2:$N$622,MATCH(1,Engine!$C$2:$C$622,0))) | O14: =IF(ISNA(MATCH(1,Engine!$C$2:$C$622,0)),"",INDEX('Compliance Database'!$O$2:$O$622,MATCH(1,Engine!$C$2:$C$622,0)))
A15: =IF(ISNA(MATCH(2,Engine!$C$2:$C$622,0)),"",INDEX('Compliance Database'!$A$2:$A$622,MATCH(2,Engine!$C$2:$C$622,0))) | B15: =IF(ISNA(MATCH(2,Engine!$C$2:$C$622,0)),"",INDEX('Compliance Database'!$B$2:$B$622,MATCH(2,Engine!$C$2:$C$622,0))) | C15: =IF(ISNA(MATCH(2,Engine!$C$2:$C$622,0)),"",INDEX('Compliance Database'!$C$2:$C$622,MATCH(2,Engine!$C$2:$C$622,0))) | D15: =IF(ISNA(MATCH(2,Engine!$C$2:$C$622,0)),"",INDEX('Compliance Database'!$D$2:$D$622,MATCH(2,Engine!$C$2:$C$622,0))) | E15: =IF(ISNA(MATCH(2,Engine!$C$2:$C$622,0)),"",INDEX('Compliance Database'!$E$2:$E$622,MATCH(2,Engine!$C$2:$C$622,0))) | F15: =IF(ISNA(MATCH(2,Engine!$C$2:$C$622,0)),"",INDEX('Compliance Database'!$F$2:$F$622,MATCH(2,Engine!$C$2:$C$622,0))) | G15: =IF(ISNA(MATCH(2,Engine!$C$2:$C$622,0)),"",INDEX('Compliance Database'!$G$2:$G$622,MATCH(2,Engine!$C$2:$C$622,0))) | H15: =IF(ISNA(MATCH(2,Engine!$C$2:$C$622,0)),"",INDEX('Compliance Database'!$H$2:$H$622,MATCH(2,Engine!$C$2:$C$622,0))) | I15: =IF(ISNA(MATCH(2,Engine!$C$2:$C$622,0)),"",INDEX('Compliance Database'!$I$2:$I$622,MATCH(2,Engine!$C$2:$C$622,0))) | J15: =IF(ISNA(MATCH(2,Engine!$C$2:$C$622,0)),"",INDEX('Compliance Database'!$J$2:$J$622,MATCH(2,Engine!$C$2:$C$622,0))) | K15: =IF(ISNA(MATCH(2,Engine!$C$2:$C$622,0)),"",INDEX('Compliance Database'!$K$2:$K$622,MATCH(2,Engine!$C$2:$C$622,0))) | L15: =IF(ISNA(MATCH(2,Engine!$C$2:$C$622,0)),"",INDEX('Compliance Database'!$L$2:$L$622,MATCH(2,Engine!$C$2:$C$622,0))) | M15: =IF(ISNA(MATCH(2,Engine!$C$2:$C$622,0)),"",INDEX('Compliance Database'!$M$2:$M$622,MATCH(2,Engine!$C$2:$C$622,0))) | N15: =IF(ISNA(MATCH(2,Engine!$C$2:$C$622,0)),"",INDEX('Compliance Database'!$N$2:$N$622,MATCH(2,Engine!$C$2:$C$622,0))) | O15: =IF(ISNA(MATCH(2,Engine!$C$2:$C$622,0)),"",INDEX('Compliance Database'!$O$2:$O$622,MATCH(2,Engine!$C$2:$C$622,0)))
A16: =IF(ISNA(MATCH(3,Engine!$C$2:$C$622,0)),"",INDEX('Compliance Database'!$A$2:$A$622,MATCH(3,Engine!$C$2:$C$622,0))) | B16: =IF(ISNA(MATCH(3,Engine!$C$2:$C$622,0)),"",INDEX('Compliance Database'!$B$2:$B$622,MATCH(3,Engine!$C$2:$C$622,0))) | C16: =IF(ISNA(MATCH(3,Engine!$C$2:$C$622,0)),"",INDEX('Compliance Database'!$C$2:$C$622,MATCH(3,Engine!$C$2:$C$622,0))) | D16: =IF(ISNA(MATCH(3,Engine!$C$2:$C$622,0)),"",INDEX('Compliance Database'!$D$2:$D$622,MATCH(3,Engine!$C$2:$C$622,0))) | E16: =IF(ISNA(MATCH(3,Engine!$C$2:$C$622,0)),"",INDEX('Compliance Database'!$E$2:$E$622,MATCH(3,Engine!$C$2:$C$622,0))) | F16: =IF(ISNA(MATCH(3,Engine!$C$2:$C$622,0)),"",INDEX('Compliance Database'!$F$2:$F$622,MATCH(3,Engine!$C$2:$C$622,0))) | G16: =IF(ISNA(MATCH(3,Engine!$C$2:$C$622,0)),"",INDEX('Compliance Database'!$G$2:$G$622,MATCH(3,Engine!$C$2:$C$622,0))) | H16: =IF(ISNA(MATCH(3,Engine!$C$2:$C$622,0)),"",INDEX('Compliance Database'!$H$2:$H$622,MATCH(3,Engine!$C$2:$C$622,0))) | I16: =IF(ISNA(MATCH(3,Engine!$C$2:$C$622,0)),"",INDEX('Compliance Database'!$I$2:$I$622,MATCH(3,Engine!$C$2:$C$622,0))) | J16: =IF(ISNA(MATCH(3,Engine!$C$2:$C$622,0)),"",INDEX('Compliance Database'!$J$2:$J$622,MATCH(3,Engine!$C$2:$C$622,0))) | K16: =IF(ISNA(MATCH(3,Engine!$C$2:$C$622,0)),"",INDEX('Compliance Database'!$K$2:$K$622,MATCH(3,Engine!$C$2:$C$622,0))) | L16: =IF(ISNA(MATCH(3,Engine!$C$2:$C$622,0)),"",INDEX('Compliance Database'!$L$2:$L$622,MATCH(3,Engine!$C$2:$C$622,0))) | M16: =IF(ISNA(MATCH(3,Engine!$C$2:$C$622,0)),"",INDEX('Compliance Database'!$M$2:$M$622,MATCH(3,Engine!$C$2:$C$622,0))) | N16: =IF(ISNA(MATCH(3,Engine!$C$2:$C$622,0)),"",INDEX('Compliance Database'!$N$2:$N$622,MATCH(3,Engine!$C$2:$C$622,0))) | O16: =IF(ISNA(MATCH(3,Engine!$C$2:$C$622,0)),"",INDEX('Compliance Database'!$O$2:$O$622,MATCH(3,Engine!$C$2:$C$622,0)))
A17: =IF(ISNA(MATCH(4,Engine!$C$2:$C$622,0)),"",INDEX('Compliance Database'!$A$2:$A$622,MATCH(4,Engine!$C$2:$C$622,0))) | B17: =IF(ISNA(MATCH(4,Engine!$C$2:$C$622,0)),"",INDEX('Compliance Database'!$B$2:$B$622,MATCH(4,Engine!$C$2:$C$622,0))) | C17: =IF(ISNA(MATCH(4,Engine!$C$2:$C$622,0)),"",INDEX('Compliance Database'!$C$2:$C$622,MATCH(4,Engine!$C$2:$C$622,0))) | D17: =IF(ISNA(MATCH(4,Engine!$C$2:$C$622,0)),"",INDEX('Compliance Database'!$D$2:$D$622,MATCH(4,Engine!$C$2:$C$622,0))) | E17: =IF(ISNA(MATCH(4,Engine!$C$2:$C$622,0)),"",INDEX('Compliance Database'!$E$2:$E$622,MATCH(4,Engine!$C$2:$C$622,0))) | F17: =IF(ISNA(MATCH(4,Engine!$C$2:$C$622,0)),"",INDEX('Compliance Database'!$F$2:$F$622,MATCH(4,Engine!$C$2:$C$622,0))) | G17: =IF(ISNA(MATCH(4,Engine!$C$2:$C$622,0)),"",INDEX('Compliance Database'!$G$2:$G$622,MATCH(4,Engine!$C$2:$C$622,0))) | H17: =IF(ISNA(MATCH(4,Engine!$C$2:$C$622,0)),"",INDEX('Compliance Database'!$H$2:$H$622,MATCH(4,Engine!$C$2:$C$622,0))) | I17: =IF(ISNA(MATCH(4,Engine!$C$2:$C$622,0)),"",INDEX('Compliance Database'!$I$2:$I$622,MATCH(4,Engine!$C$2:$C$622,0))) | J17: =IF(ISNA(MATCH(4,Engine!$C$2:$C$622,0)),"",INDEX('Compliance Database'!$J$2:$J$622,MATCH(4,Engine!$C$2:$C$622,0))) | K17: =IF(ISNA(MATCH(4,Engine!$C$2:$C$622,0)),"",INDEX('Compliance Database'!$K$2:$K$622,MATCH(4,Engine!$C$2:$C$622,0))) | L17: =IF(ISNA(MATCH(4,Engine!$C$2:$C$622,0)),"",INDEX('Compliance Database'!$L$2:$L$622,MATCH(4,Engine!$C$2:$C$622,0))) | M17: =IF(ISNA(MATCH(4,Engine!$C$2:$C$622,0)),"",INDEX('Compliance Database'!$M$2:$M$622,MATCH(4,Engine!$C$2:$C$622,0))) | N17: =IF(ISNA(MATCH(4,Engine!$C$2:$C$622,0)),"",INDEX('Compliance Database'!$N$2:$N$622,MATCH(4,Engine!$C$2:$C$622,0))) | O17: =IF(ISNA(MATCH(4,Engine!$C$2:$C$622,0)),"",INDEX('Compliance Database'!$O$2:$O$622,MATCH(4,Engine!$C$2:$C$622,0)))
A18: =IF(ISNA(MATCH(5,Engine!$C$2:$C$622,0)),"",INDEX('Compliance Database'!$A$2:$A$622,MATCH(5,Engine!$C$2:$C$622,0))) | B18: =IF(ISNA(MATCH(5,Engine!$C$2:$C$622,0)),"",INDEX('Compliance Database'!$B$2:$B$622,MATCH(5,Engine!$C$2:$C$622,0))) | C18: =IF(ISNA(MATCH(5,Engine!$C$2:$C$622,0)),"",INDEX('Compliance Database'!$C$2:$C$622,MATCH(5,Engine!$C$2:$C$622,0))) | D18: =IF(ISNA(MATCH(5,Engine!$C$2:$C$622,0)),"",INDEX('Compliance Database'!$D$2:$D$622,MATCH(5,Engine!$C$2:$C$622,0))) | E18: =IF(ISNA(MATCH(5,Engine!$C$2:$C$622,0)),"",INDEX('Compliance Database'!$E$2:$E$622,MATCH(5,Engine!$C$2:$C$622,0))) | F18: =IF(ISNA(MATCH(5,Engine!$C$2:$C$622,0)),"",INDEX('Compliance Database'!$F$2:$F$622,MATCH(5,Engine!$C$2:$C$622,0))) | G18: =IF(ISNA(MATCH(5,Engine!$C$2:$C$622,0)),"",INDEX('Compliance Database'!$G$2:$G$622,MATCH(5,Engine!$C$2:$C$622,0))) | H18: =IF(ISNA(MATCH(5,Engine!$C$2:$C$622,0)),"",INDEX('Compliance Database'!$H$2:$H$622,MATCH(5,Engine!$C$2:$C$622,0))) | I18: =IF(ISNA(MATCH(5,Engine!$C$2:$C$622,0)),"",INDEX('Compliance Database'!$I$2:$I$622,MATCH(5,Engine!$C$2:$C$622,0))) | J18: =IF(ISNA(MATCH(5,Engine!$C$2:$C$622,0)),"",INDEX('Compliance Database'!$J$2:$J$622,MATCH(5,Engine!$C$2:$C$622,0))) | K18: =IF(ISNA(MATCH(5,Engine!$C$2:$C$622,0)),"",INDEX('Compliance Database'!$K$2:$K$622,MATCH(5,Engine!$C$2:$C$622,0))) | L18: =IF(ISNA(MATCH(5,Engine!$C$2:$C$622,0)),"",INDEX('Compliance Database'!$L$2:$L$622,MATCH(5,Engine!$C$2:$C$622,0))) | M18: =IF(ISNA(MATCH(5,Engine!$C$2:$C$622,0)),"",INDEX('Compliance Database'!$M$2:$M$622,MATCH(5,Engine!$C$2:$C$622,0))) | N18: =IF(ISNA(MATCH(5,Engine!$C$2:$C$622,0)),"",INDEX('Compliance Database'!$N$2:$N$622,MATCH(5,Engine!$C$2:$C$622,0))) | O18: =IF(ISNA(MATCH(5,Engine!$C$2:$C$622,0)),"",INDEX('Compliance Database'!$O$2:$O$622,MATCH(5,Engine!$C$2:$C$622,0)))
A19: =IF(ISNA(MATCH(6,Engine!$C$2:$C$622,0)),"",INDEX('Compliance Database'!$A$2:$A$622,MATCH(6,Engine!$C$2:$C$622,0))) | B19: =IF(ISNA(MATCH(6,Engine!$C$2:$C$622,0)),"",INDEX('Compliance Database'!$B$2:$B$622,MATCH(6,Engine!$C$2:$C$622,0))) | C19: =IF(ISNA(MATCH(6,Engine!$C$2:$C$622,0)),"",INDEX('Compliance Database'!$C$2:$C$622,MATCH(6,Engine!$C$2:$C$622,0))) | D19: =IF(ISNA(MATCH(6,Engine!$C$2:$C$622,0)),"",INDEX('Compliance Database'!$D$2:$D$622,MATCH(6,Engine!$C$2:$C$622,0))) | E19: =IF(ISNA(MATCH(6,Engine!$C$2:$C$622,0)),"",INDEX('Compliance Database'!$E$2:$E$622,MATCH(6,Engine!$C$2:$C$622,0))) | F19: =IF(ISNA(MATCH(6,Engine!$C$2:$C$622,0)),"",INDEX('Compliance Database'!$F$2:$F$622,MATCH(6,Engine!$C$2:$C$622,0))) | G19: =IF(ISNA(MATCH(6,Engine!$C$2:$C$622,0)),"",INDEX('Compliance Database'!$G$2:$G$622,MATCH(6,Engine!$C$2:$C$622,0))) | H19: =IF(ISNA(MATCH(6,Engine!$C$2:$C$622,0)),"",INDEX('Compliance Database'!$H$2:$H$622,MATCH(6,Engine!$C$2:$C$622,0))) | I19: =IF(ISNA(MATCH(6,Engine!$C$2:$C$622,0)),"",INDEX('Compliance Database'!$I$2:$I$622,MATCH(6,Engine!$C$2:$C$622,0))) | J19: =IF(ISNA(MATCH(6,Engine!$C$2:$C$622,0)),"",INDEX('Compliance Database'!$J$2:$J$622,MATCH(6,Engine!$C$2:$C$622,0))) | K19: =IF(ISNA(MATCH(6,Engine!$C$2:$C$622,0)),"",INDEX('Compliance Database'!$K$2:$K$622,MATCH(6,Engine!$C$2:$C$622,0))) | L19: =IF(ISNA(MATCH(6,Engine!$C$2:$C$622,0)),"",INDEX('Compliance Database'!$L$2:$L$622,MATCH(6,Engine!$C$2:$C$622,0))) | M19: =IF(ISNA(MATCH(6,Engine!$C$2:$C$622,0)),"",INDEX('Compliance Database'!$M$2:$M$622,MATCH(6,Engine!$C$2:$C$622,0))) | N19: =IF(ISNA(MATCH(6,Engine!$C$2:$C$622,0)),"",INDEX('Compliance Database'!$N$2:$N$622,MATCH(6,Engine!$C$2:$C$622,0))) | O19: =IF(ISNA(MATCH(6,Engine!$C$2:$C$622,0)),"",INDEX('Compliance Database'!$O$2:$O$622,MATCH(6,Engine!$C$2:$C$622,0)))
A20: =IF(ISNA(MATCH(7,Engine!$C$2:$C$622,0)),"",INDEX('Compliance Database'!$A$2:$A$622,MATCH(7,Engine!$C$2:$C$622,0))) | B20: =IF(ISNA(MATCH(7,Engine!$C$2:$C$622,0)),"",INDEX('Compliance Database'!$B$2:$B$622,MATCH(7,Engine!$C$2:$C$622,0))) | C20: =IF(ISNA(MATCH(7,Engine!$C$2:$C$622,0)),"",INDEX('Compliance Database'!$C$2:$C$622,MATCH(7,Engine!$C$2:$C$622,0))) | D20: =IF(ISNA(MATCH(7,Engine!$C$2:$C$622,0)),"",INDEX('Compliance Database'!$D$2:$D$622,MATCH(7,Engine!$C$2:$C$622,0))) | E20: =IF(ISNA(MATCH(7,Engine!$C$2:$C$622,0)),"",INDEX('Compliance Database'!$E$2:$E$622,MATCH(7,Engine!$C$2:$C$622,0))) | F20: =IF(ISNA(MATCH(7,Engine!$C$2:$C$622,0)),"",INDEX('Compliance Database'!$F$2:$F$622,MATCH(7,Engine!$C$2:$C$622,0))) | G20: =IF(ISNA(MATCH(7,Engine!$C$2:$C$622,0)),"",INDEX('Compliance Database'!$G$2:$G$622,MATCH(7,Engine!$C$2:$C$622,0))) | H20: =IF(ISNA(MATCH(7,Engine!$C$2:$C$622,0)),"",INDEX('Compliance Database'!$H$2:$H$622,MATCH(7,Engine!$C$2:$C$622,0))) | I20: =IF(ISNA(MATCH(7,Engine!$C$2:$C$622,0)),"",INDEX('Compliance Database'!$I$2:$I$622,MATCH(7,Engine!$C$2:$C$622,0))) | J20: =IF(ISNA(MATCH(7,Engine!$C$2:$C$622,0)),"",INDEX('Compliance Database'!$J$2:$J$622,MATCH(7,Engine!$C$2:$C$622,0))) | K20: =IF(ISNA(MATCH(7,Engine!$C$2:$C$622,0)),"",INDEX('Compliance Database'!$K$2:$K$622,MATCH(7,Engine!$C$2:$C$622,0))) | L20: =IF(ISNA(MATCH(7,Engine!$C$2:$C$622,0)),"",INDEX('Compliance Database'!$L$2:$L$622,MATCH(7,Engine!$C$2:$C$622,0))) | M20: =IF(ISNA(MATCH(7,Engine!$C$2:$C$622,0)),"",INDEX('Compliance Database'!$M$2:$M$622,MATCH(7,Engine!$C$2:$C$622,0))) | N20: =IF(ISNA(MATCH(7,Engine!$C$2:$C$622,0)),"",INDEX('Compliance Database'!$N$2:$N$622,MATCH(7,Engine!$C$2:$C$622,0))) | O20: =IF(ISNA(MATCH(7,Engine!$C$2:$C$622,0)),"",INDEX('Compliance Database'!$O$2:$O$622,MATCH(7,Engine!$C$2:$C$622,0)))
A21: =IF(ISNA(MATCH(8,Engine!$C$2:$C$622,0)),"",INDEX('Compliance Database'!$A$2:$A$622,MATCH(8,Engine!$C$2:$C$622,0))) | B21: =IF(ISNA(MATCH(8,Engine!$C$2:$C$622,0)),"",INDEX('Compliance Database'!$B$2:$B$622,MATCH(8,Engine!$C$2:$C$622,0))) | C21: =IF(ISNA(MATCH(8,Engine!$C$2:$C$622,0)),"",INDEX('Compliance Database'!$C$2:$C$622,MATCH(8,Engine!$C$2:$C$622,0))) | D21: =IF(ISNA(MATCH(8,Engine!$C$2:$C$622,0)),"",INDEX('Compliance Database'!$D$2:$D$622,MATCH(8,Engine!$C$2:$C$622,0))) | E21: =IF(ISNA(MATCH(8,Engine!$C$2:$C$622,0)),"",INDEX('Compliance Database'!$E$2:$E$622,MATCH(8,Engine!$C$2:$C$622,0))) | F21: =IF(ISNA(MATCH(8,Engine!$C$2:$C$622,0)),"",INDEX('Compliance Database'!$F$2:$F$622,MATCH(8,Engine!$C$2:$C$622,0))) | G21: =IF(ISNA(MATCH(8,Engine!$C$2:$C$622,0)),"",INDEX('Compliance Database'!$G$2:$G$622,MATCH(8,Engine!$C$2:$C$622,0))) | H21: =IF(ISNA(MATCH(8,Engine!$C$2:$C$622,0)),"",INDEX('Compliance Database'!$H$2:$H$622,MATCH(8,Engine!$C$2:$C$622,0))) | I21: =IF(ISNA(MATCH(8,Engine!$C$2:$C$622,0)),"",INDEX('Compliance Database'!$I$2:$I$622,MATCH(8,Engine!$C$2:$C$622,0))) | J21: =IF(ISNA(MATCH(8,Engine!$C$2:$C$622,0)),"",INDEX('Compliance Database'!$J$2:$J$622,MATCH(8,Engine!$C$2:$C$622,0))) | K21: =IF(ISNA(MATCH(8,Engine!$C$2:$C$622,0)),"",INDEX('Compliance Database'!$K$2:$K$622,MATCH(8,Engine!$C$2:$C$622,0))) | L21: =IF(ISNA(MATCH(8,Engine!$C$2:$C$622,0)),"",INDEX('Compliance Database'!$L$2:$L$622,MATCH(8,Engine!$C$2:$C$622,0))) | M21: =IF(ISNA(MATCH(8,Engine!$C$2:$C$622,0)),"",INDEX('Compliance Database'!$M$2:$M$622,MATCH(8,Engine!$C$2:$C$622,0))) | N21: =IF(ISNA(MATCH(8,Engine!$C$2:$C$622,0)),"",INDEX('Compliance Database'!$N$2:$N$622,MATCH(8,Engine!$C$2:$C$622,0))) | O21: =IF(ISNA(MATCH(8,Engine!$C$2:$C$622,0)),"",INDEX('Compliance Database'!$O$2:$O$622,MATCH(8,Engine!$C$2:$C$622,0)))
A22: =IF(ISNA(MATCH(9,Engine!$C$2:$C$622,0)),"",INDEX('Compliance Database'!$A$2:$A$622,MATCH(9,Engine!$C$2:$C$622,0))) | B22: =IF(ISNA(MATCH(9,Engine!$C$2:$C$622,0)),"",INDEX('Compliance Database'!$B$2:$B$622,MATCH(9,Engine!$C$2:$C$622,0))) | C22: =IF(ISNA(MATCH(9,Engine!$C$2:$C$622,0)),"",INDEX('Compliance Database'!$C$2:$C$622,MATCH(9,Engine!$C$2:$C$622,0))) | D22: =IF(ISNA(MATCH(9,Engine!$C$2:$C$622,0)),"",INDEX('Compliance Database'!$D$2:$D$622,MATCH(9,Engine!$C$2:$C$622,0))) | E22: =IF(ISNA(MATCH(9,Engine!$C$2:$C$622,0)),"",INDEX('Compliance Database'!$E$2:$E$622,MATCH(9,Engine!$C$2:$C$622,0))) | F22: =IF(ISNA(MATCH(9,Engine!$C$2:$C$622,0)),"",INDEX('Compliance Database'!$F$2:$F$622,MATCH(9,Engine!$C$2:$C$622,0))) | G22: =IF(ISNA(MATCH(9,Engine!$C$2:$C$622,0)),"",INDEX('Compliance Database'!$G$2:$G$622,MATCH(9,Engine!$C$2:$C$622,0))) | H22: =IF(ISNA(MATCH(9,Engine!$C$2:$C$622,0)),"",INDEX('Compliance Database'!$H$2:$H$622,MATCH(9,Engine!$C$2:$C$622,0))) | I22: =IF(ISNA(MATCH(9,Engine!$C$2:$C$622,0)),"",INDEX('Compliance Database'!$I$2:$I$622,MATCH(9,Engine!$C$2:$C$622,0))) | J22: =IF(ISNA(MATCH(9,Engine!$C$2:$C$622,0)),"",INDEX('Compliance Database'!$J$2:$J$622,MATCH(9,Engine!$C$2:$C$622,0))) | K22: =IF(ISNA(MATCH(9,Engine!$C$2:$C$622,0)),"",INDEX('Compliance Database'!$K$2:$K$622,MATCH(9,Engine!$C$2:$C$622,0))) | L22: =IF(ISNA(MATCH(9,Engine!$C$2:$C$622,0)),"",INDEX('Compliance Database'!$L$2:$L$622,MATCH(9,Engine!$C$2:$C$622,0))) | M22: =IF(ISNA(MATCH(9,Engine!$C$2:$C$622,0)),"",INDEX('Compliance Database'!$M$2:$M$622,MATCH(9,Engine!$C$2:$C$622,0))) | N22: =IF(ISNA(MATCH(9,Engine!$C$2:$C$622,0)),"",INDEX('Compliance Database'!$N$2:$N$622,MATCH(9,Engine!$C$2:$C$622,0))) | O22: =IF(ISNA(MATCH(9,Engine!$C$2:$C$622,0)),"",INDEX('Compliance Database'!$O$2:$O$622,MATCH(9,Engine!$C$2:$C$622,0)))
A23: =IF(ISNA(MATCH(10,Engine!$C$2:$C$622,0)),"",INDEX('Compliance Database'!$A$2:$A$622,MATCH(10,Engine!$C$2:$C$622,0))) | B23: =IF(ISNA(MATCH(10,Engine!$C$2:$C$622,0)),"",INDEX('Compliance Database'!$B$2:$B$622,MATCH(10,Engine!$C$2:$C$622,0))) | C23: =IF(ISNA(MATCH(10,Engine!$C$2:$C$622,0)),"",INDEX('Compliance Database'!$C$2:$C$622,MATCH(10,Engine!$C$2:$C$622,0))) | D23: =IF(ISNA(MATCH(10,Engine!$C$2:$C$622,0)),"",INDEX('Compliance Database'!$D$2:$D$622,MATCH(10,Engine!$C$2:$C$622,0))) | E23: =IF(ISNA(MATCH(10,Engine!$C$2:$C$622,0)),"",INDEX('Compliance Database'!$E$2:$E$622,MATCH(10,Engine!$C$2:$C$622,0))) | F23: =IF(ISNA(MATCH(10,Engine!$C$2:$C$622,0)),"",INDEX('Compliance Database'!$F$2:$F$622,MATCH(10,Engine!$C$2:$C$622,0))) | G23: =IF(ISNA(MATCH(10,Engine!$C$2:$C$622,0)),"",INDEX('Compliance Database'!$G$2:$G$622,MATCH(10,Engine!$C$2:$C$622,0))) | H23: =IF(ISNA(MATCH(10,Engine!$C$2:$C$622,0)),"",INDEX('Compliance Database'!$H$2:$H$622,MATCH(10,Engine!$C$2:$C$622,0))) | I23: =IF(ISNA(MATCH(10,Engine!$C$2:$C$622,0)),"",INDEX('Compliance Database'!$I$2:$I$622,MATCH(10,Engine!$C$2:$C$622,0))) | J23: =IF(ISNA(MATCH(10,Engine!$C$2:$C$622,0)),"",INDEX('Compliance Database'!$J$2:$J$622,MATCH(10,Engine!$C$2:$C$622,0))) | K23: =IF(ISNA(MATCH(10,Engine!$C$2:$C$622,0)),"",INDEX('Compliance Database'!$K$2:$K$622,MATCH(10,Engine!$C$2:$C$622,0))) | L23: =IF(ISNA(MATCH(10,Engine!$C$2:$C$622,0)),"",INDEX('Compliance Database'!$L$2:$L$622,MATCH(10,Engine!$C$2:$C$622,0))) | M23: =IF(ISNA(MATCH(10,Engine!$C$2:$C$622,0)),"",INDEX('Compliance Database'!$M$2:$M$622,MATCH(10,Engine!$C$2:$C$622,0))) | N23: =IF(ISNA(MATCH(10,Engine!$C$2:$C$622,0)),"",INDEX('Compliance Database'!$N$2:$N$622,MATCH(10,Engine!$C$2:$C$622,0))) | O23: =IF(ISNA(MATCH(10,Engine!$C$2:$C$622,0)),"",INDEX('Compliance Database'!$O$2:$O$622,MATCH(10,Engine!$C$2:$C$622,0)))
A24: =IF(ISNA(MATCH(11,Engine!$C$2:$C$622,0)),"",INDEX('Compliance Database'!$A$2:$A$622,MATCH(11,Engine!$C$2:$C$622,0))) | B24: =IF(ISNA(MATCH(11,Engine!$C$2:$C$622,0)),"",INDEX('Compliance Database'!$B$2:$B$622,MATCH(11,Engine!$C$2:$C$622,0))) | C24: =IF(ISNA(MATCH(11,Engine!$C$2:$C$622,0)),"",INDEX('Compliance Database'!$C$2:$C$622,MATCH(11,Engine!$C$2:$C$622,0))) | D24: =IF(ISNA(MATCH(11,Engine!$C$2:$C$622,0)),"",INDEX('Compliance Database'!$D$2:$D$622,MATCH(11,Engine!$C$2:$C$622,0))) | E24: =IF(ISNA(MATCH(11,Engine!$C$2:$C$622,0)),"",INDEX('Compliance Database'!$E$2:$E$622,MATCH(11,Engine!$C$2:$C$622,0))) | F24: =IF(ISNA(MATCH(11,Engine!$C$2:$C$622,0)),"",INDEX('Compliance Database'!$F$2:$F$622,MATCH(11,Engine!$C$2:$C$622,0))) | G24: =IF(ISNA(MATCH(11,Engine!$C$2:$C$622,0)),"",INDEX('Compliance Database'!$G$2:$G$622,MATCH(11,Engine!$C$2:$C$622,0))) | H24: =IF(ISNA(MATCH(11,Engine!$C$2:$C$622,0)),"",INDEX('Compliance Database'!$H$2:$H$622,MATCH(11,Engine!$C$2:$C$622,0))) | I24: =IF(ISNA(MATCH(11,Engine!$C$2:$C$622,0)),"",INDEX('Compliance Database'!$I$2:$I$622,MATCH(11,Engine!$C$2:$C$622,0))) | J24: =IF(ISNA(MATCH(11,Engine!$C$2:$C$622,0)),"",INDEX('Compliance Database'!$J$2:$J$622,MATCH(11,Engine!$C$2:$C$622,0))) | K24: =IF(ISNA(MATCH(11,Engine!$C$2:$C$622,0)),"",INDEX('Compliance Database'!$K$2:$K$622,MATCH(11,Engine!$C$2:$C$622,0))) | L24: =IF(ISNA(MATCH(11,Engine!$C$2:$C$622,0)),"",INDEX('Compliance Database'!$L$2:$L$622,MATCH(11,Engine!$C$2:$C$622,0))) | M24: =IF(ISNA(MATCH(11,Engine!$C$2:$C$622,0)),"",INDEX('Compliance Database'!$M$2:$M$622,MATCH(11,Engine!$C$2:$C$622,0))) | N24: =IF(ISNA(MATCH(11,Engine!$C$2:$C$622,0)),"",INDEX('Compliance Database'!$N$2:$N$622,MATCH(11,Engine!$C$2:$C$622,0))) | O24: =IF(ISNA(MATCH(11,Engine!$C$2:$C$622,0)),"",INDEX('Compliance Database'!$O$2:$O$622,MATCH(11,Engine!$C$2:$C$622,0)))
A25: =IF(ISNA(MATCH(12,Engine!$C$2:$C$622,0)),"",INDEX('Compliance Database'!$A$2:$A$622,MATCH(12,Engine!$C$2:$C$622,0))) | B25: =IF(ISNA(MATCH(12,Engine!$C$2:$C$622,0)),"",INDEX('Compliance Database'!$B$2:$B$622,MATCH(12,Engine!$C$2:$C$622,0))) | C25: =IF(ISNA(MATCH(12,Engine!$C$2:$C$622,0)),"",INDEX('Compliance Database'!$C$2:$C$622,MATCH(12,Engine!$C$2:$C$622,0))) | D25: =IF(ISNA(MATCH(12,Engine!$C$2:$C$622,0)),"",INDEX('Compliance Database'!$D$2:$D$622,MATCH(12,Engine!$C$2:$C$622,0))) | E25: =IF(ISNA(MATCH(12,Engine!$C$2:$C$622,0)),"",INDEX('Compliance Database'!$E$2:$E$622,MATCH(12,Engine!$C$2:$C$622,0))) | F25: =IF(ISNA(MATCH(12,Engine!$C$2:$C$622,0)),"",INDEX('Compliance Database'!$F$2:$F$622,MATCH(12,Engine!$C$2:$C$622,0))) | G25: =IF(ISNA(MATCH(12,Engine!$C$2:$C$622,0)),"",INDEX('Compliance Database'!$G$2:$G$622,MATCH(12,Engine!$C$2:$C$622,0))) | H25: =IF(ISNA(MATCH(12,Engine!$C$2:$C$622,0)),"",INDEX('Compliance Database'!$H$2:$H$622,MATCH(12,Engine!$C$2:$C$622,0))) | I25: =IF(ISNA(MATCH(12,Engine!$C$2:$C$622,0)),"",INDEX('Compliance Database'!$I$2:$I$622,MATCH(12,Engine!$C$2:$C$622,0))) | J25: =IF(ISNA(MATCH(12,Engine!$C$2:$C$622,0)),"",INDEX('Compliance Database'!$J$2:$J$622,MATCH(12,Engine!$C$2:$C$622,0))) | K25: =IF(ISNA(MATCH(12,Engine!$C$2:$C$622,0)),"",INDEX('Compliance Database'!$K$2:$K$622,MATCH(12,Engine!$C$2:$C$622,0))) | L25: =IF(ISNA(MATCH(12,Engine!$C$2:$C$622,0)),"",INDEX('Compliance Database'!$L$2:$L$622,MATCH(12,Engine!$C$2:$C$622,0))) | M25: =IF(ISNA(MATCH(12,Engine!$C$2:$C$622,0)),"",INDEX('Compliance Database'!$M$2:$M$622,MATCH(12,Engine!$C$2:$C$622,0))) | N25: =IF(ISNA(MATCH(12,Engine!$C$2:$C$622,0)),"",INDEX('Compliance Database'!$N$2:$N$622,MATCH(12,Engine!$C$2:$C$622,0))) | O25: =IF(ISNA(MATCH(12,Engine!$C$2:$C$622,0)),"",INDEX('Compliance Database'!$O$2:$O$622,MATCH(12,Engine!$C$2:$C$622,0)))
A26: =IF(ISNA(MATCH(13,Engine!$C$2:$C$622,0)),"",INDEX('Compliance Database'!$A$2:$A$622,MATCH(13,Engine!$C$2:$C$622,0))) | B26: =IF(ISNA(MATCH(13,Engine!$C$2:$C$622,0)),"",INDEX('Compliance Database'!$B$2:$B$622,MATCH(13,Engine!$C$2:$C$622,0))) | C26: =IF(ISNA(MATCH(13,Engine!$C$2:$C$622,0)),"",INDEX('Compliance Database'!$C$2:$C$622,MATCH(13,Engine!$C$2:$C$622,0))) | D26: =IF(ISNA(MATCH(13,Engine!$C$2:$C$622,0)),"",INDEX('Compliance Database'!$D$2:$D$622,MATCH(13,Engine!$C$2:$C$622,0))) | E26: =IF(ISNA(MATCH(13,Engine!$C$2:$C$622,0)),"",INDEX('Compliance Database'!$E$2:$E$622,MATCH(13,Engine!$C$2:$C$622,0))) | F26: =IF(ISNA(MATCH(13,Engine!$C$2:$C$622,0)),"",INDEX('Compliance Database'!$F$2:$F$622,MATCH(13,Engine!$C$2:$C$622,0))) | G26: =IF(ISNA(MATCH(13,Engine!$C$2:$C$622,0)),"",INDEX('Compliance Database'!$G$2:$G$622,MATCH(13,Engine!$C$2:$C$622,0))) | H26: =IF(ISNA(MATCH(13,Engine!$C$2:$C$622,0)),"",INDEX('Compliance Database'!$H$2:$H$622,MATCH(13,Engine!$C$2:$C$622,0))) | I26: =IF(ISNA(MATCH(13,Engine!$C$2:$C$622,0)),"",INDEX('Compliance Database'!$I$2:$I$622,MATCH(13,Engine!$C$2:$C$622,0))) | J26: =IF(ISNA(MATCH(13,Engine!$C$2:$C$622,0)),"",INDEX('Compliance Database'!$J$2:$J$622,MATCH(13,Engine!$C$2:$C$622,0))) | K26: =IF(ISNA(MATCH(13,Engine!$C$2:$C$622,0)),"",INDEX('Compliance Database'!$K$2:$K$622,MATCH(13,Engine!$C$2:$C$622,0))) | L26: =IF(ISNA(MATCH(13,Engine!$C$2:$C$622,0)),"",INDEX('Compliance Database'!$L$2:$L$622,MATCH(13,Engine!$C$2:$C$622,0))) | M26: =IF(ISNA(MATCH(13,Engine!$C$2:$C$622,0)),"",INDEX('Compliance Database'!$M$2:$M$622,MATCH(13,Engine!$C$2:$C$622,0))) | N26: =IF(ISNA(MATCH(13,Engine!$C$2:$C$622,0)),"",INDEX('Compliance Database'!$N$2:$N$622,MATCH(13,Engine!$C$2:$C$622,0))) | O26: =IF(ISNA(MATCH(13,Engine!$C$2:$C$622,0)),"",INDEX('Compliance Database'!$O$2:$O$622,MATCH(13,Engine!$C$2:$C$622,0)))
A27: =IF(ISNA(MATCH(14,Engine!$C$2:$C$622,0)),"",INDEX('Compliance Database'!$A$2:$A$622,MATCH(14,Engine!$C$2:$C$622,0))) | B27: =IF(ISNA(MATCH(14,Engine!$C$2:$C$622,0)),"",INDEX('Compliance Database'!$B$2:$B$622,MATCH(14,Engine!$C$2:$C$622,0))) | C27: =IF(ISNA(MATCH(14,Engine!$C$2:$C$622,0)),"",INDEX('Compliance Database'!$C$2:$C$622,MATCH(14,Engine!$C$2:$C$622,0))) | D27: =IF(ISNA(MATCH(14,Engine!$C$2:$C$622,0)),"",INDEX('Compliance Database'!$D$2:$D$622,MATCH(14,Engine!$C$2:$C$622,0))) | E27: =IF(ISNA(MATCH(14,Engine!$C$2:$C$622,0)),"",INDEX('Compliance Database'!$E$2:$E$622,MATCH(14,Engine!$C$2:$C$622,0))) | F27: =IF(ISNA(MATCH(14,Engine!$C$2:$C$622,0)),"",INDEX('Compliance Database'!$F$2:$F$622,MATCH(14,Engine!$C$2:$C$622,0))) | G27: =IF(ISNA(MATCH(14,Engine!$C$2:$C$622,0)),"",INDEX('Compliance Database'!$G$2:$G$622,MATCH(14,Engine!$C$2:$C$622,0))) | H27: =IF(ISNA(MATCH(14,Engine!$C$2:$C$622,0)),"",INDEX('Compliance Database'!$H$2:$H$622,MATCH(14,Engine!$C$2:$C$622,0))) | I27: =IF(ISNA(MATCH(14,Engine!$C$2:$C$622,0)),"",INDEX('Compliance Database'!$I$2:$I$622,MATCH(14,Engine!$C$2:$C$622,0))) | J27: =IF(ISNA(MATCH(14,Engine!$C$2:$C$622,0)),"",INDEX('Compliance Database'!$J$2:$J$622,MATCH(14,Engine!$C$2:$C$622,0))) | K27: =IF(ISNA(MATCH(14,Engine!$C$2:$C$622,0)),"",INDEX('Compliance Database'!$K$2:$K$622,MATCH(14,Engine!$C$2:$C$622,0))) | L27: =IF(ISNA(MATCH(14,Engine!$C$2:$C$622,0)),"",INDEX('Compliance Database'!$L$2:$L$622,MATCH(14,Engine!$C$2:$C$622,0))) | M27: =IF(ISNA(MATCH(14,Engine!$C$2:$C$622,0)),"",INDEX('Compliance Database'!$M$2:$M$622,MATCH(14,Engine!$C$2:$C$622,0))) | N27: =IF(ISNA(MATCH(14,Engine!$C$2:$C$622,0)),"",INDEX('Compliance Database'!$N$2:$N$622,MATCH(14,Engine!$C$2:$C$622,0))) | O27: =IF(ISNA(MATCH(14,Engine!$C$2:$C$622,0)),"",INDEX('Compliance Database'!$O$2:$O$622,MATCH(14,Engine!$C$2:$C$622,0)))
A28: =IF(ISNA(MATCH(15,Engine!$C$2:$C$622,0)),"",INDEX('Compliance Database'!$A$2:$A$622,MATCH(15,Engine!$C$2:$C$622,0))) | B28: =IF(ISNA(MATCH(15,Engine!$C$2:$C$622,0)),"",INDEX('Compliance Database'!$B$2:$B$622,MATCH(15,Engine!$C$2:$C$622,0))) | C28: =IF(ISNA(MATCH(15,Engine!$C$2:$C$622,0)),"",INDEX('Compliance Database'!$C$2:$C$622,MATCH(15,Engine!$C$2:$C$622,0))) | D28: =IF(ISNA(MATCH(15,Engine!$C$2:$C$622,0)),"",INDEX('Compliance Database'!$D$2:$D$622,MATCH(15,Engine!$C$2:$C$622,0))) | E28: =IF(ISNA(MATCH(15,Engine!$C$2:$C$622,0)),"",INDEX('Compliance Database'!$E$2:$E$622,MATCH(15,Engine!$C$2:$C$622,0))) | F28: =IF(ISNA(MATCH(15,Engine!$C$2:$C$622,0)),"",INDEX('Compliance Database'!$F$2:$F$622,MATCH(15,Engine!$C$2:$C$622,0))) | G28: =IF(ISNA(MATCH(15,Engine!$C$2:$C$622,0)),"",INDEX('Compliance Database'!$G$2:$G$622,MATCH(15,Engine!$C$2:$C$622,0))) | H28: =IF(ISNA(MATCH(15,Engine!$C$2:$C$622,0)),"",INDEX('Compliance Database'!$H$2:$H$622,MATCH(15,Engine!$C$2:$C$622,0))) | I28: =IF(ISNA(MATCH(15,Engine!$C$2:$C$622,0)),"",INDEX('Compliance Database'!$I$2:$I$622,MATCH(15,Engine!$C$2:$C$622,0))) | J28: =IF(ISNA(MATCH(15,Engine!$C$2:$C$622,0)),"",INDEX('Compliance Database'!$J$2:$J$622,MATCH(15,Engine!$C$2:$C$622,0))) | K28: =IF(ISNA(MATCH(15,Engine!$C$2:$C$622,0)),"",INDEX('Compliance Database'!$K$2:$K$622,MATCH(15,Engine!$C$2:$C$622,0))) | L28: =IF(ISNA(MATCH(15,Engine!$C$2:$C$622,0)),"",INDEX('Compliance Database'!$L$2:$L$622,MATCH(15,Engine!$C$2:$C$622,0))) | M28: =IF(ISNA(MATCH(15,Engine!$C$2:$C$622,0)),"",INDEX('Compliance Database'!$M$2:$M$622,MATCH(15,Engine!$C$2:$C$622,0))) | N28: =IF(ISNA(MATCH(15,Engine!$C$2:$C$622,0)),"",INDEX('Compliance Database'!$N$2:$N$622,MATCH(15,Engine!$C$2:$C$622,0))) | O28: =IF(ISNA(MATCH(15,Engine!$C$2:$C$622,0)),"",INDEX('Compliance Database'!$O$2:$O$622,MATCH(15,Engine!$C$2:$C$622,0)))
A29: =IF(ISNA(MATCH(16,Engine!$C$2:$C$622,0)),"",INDEX('Compliance Database'!$A$2:$A$622,MATCH(16,Engine!$C$2:$C$622,0))) | B29: =IF(ISNA(MATCH(16,Engine!$C$2:$C$622,0)),"",INDEX('Compliance Database'!$B$2:$B$622,MATCH(16,Engine!$C$2:$C$622,0))) | C29: =IF(ISNA(MATCH(16,Engine!$C$2:$C$622,0)),"",INDEX('Compliance Database'!$C$2:$C$622,MATCH(16,Engine!$C$2:$C$622,0))) | D29: =IF(ISNA(MATCH(16,Engine!$C$2:$C$622,0)),"",INDEX('Compliance Database'!$D$2:$D$622,MATCH(16,Engine!$C$2:$C$622,0))) | E29: =IF(ISNA(MATCH(16,Engine!$C$2:$C$622,0)),"",INDEX('Compliance Database'!$E$2:$E$622,MATCH(16,Engine!$C$2:$C$622,0))) | F29: =IF(ISNA(MATCH(16,Engine!$C$2:$C$622,0)),"",INDEX('Compliance Database'!$F$2:$F$622,MATCH(16,Engine!$C$2:$C$622,0))) | G29: =IF(ISNA(MATCH(16,Engine!$C$2:$C$622,0)),"",INDEX('Compliance Database'!$G$2:$G$622,MATCH(16,Engine!$C$2:$C$622,0))) | H29: =IF(ISNA(MATCH(16,Engine!$C$2:$C$622,0)),"",INDEX('Compliance Database'!$H$2:$H$622,MATCH(16,Engine!$C$2:$C$622,0))) | I29: =IF(ISNA(MATCH(16,Engine!$C$2:$C$622,0)),"",INDEX('Compliance Database'!$I$2:$I$622,MATCH(16,Engine!$C$2:$C$622,0))) | J29: =IF(ISNA(MATCH(16,Engine!$C$2:$C$622,0)),"",INDEX('Compliance Database'!$J$2:$J$622,MATCH(16,Engine!$C$2:$C$622,0))) | K29: =IF(ISNA(MATCH(16,Engine!$C$2:$C$622,0)),"",INDEX('Compliance Database'!$K$2:$K$622,MATCH(16,Engine!$C$2:$C$622,0))) | L29: =IF(ISNA(MATCH(16,Engine!$C$2:$C$622,0)),"",INDEX('Compliance Database'!$L$2:$L$622,MATCH(16,Engine!$C$2:$C$622,0))) | M29: =IF(ISNA(MATCH(16,Engine!$C$2:$C$622,0)),"",INDEX('Compliance Database'!$M$2:$M$622,MATCH(16,Engine!$C$2:$C$622,0))) | N29: =IF(ISNA(MATCH(16,Engine!$C$2:$C$622,0)),"",INDEX('Compliance Database'!$N$2:$N$622,MATCH(16,Engine!$C$2:$C$622,0))) | O29: =IF(ISNA(MATCH(16,Engine!$C$2:$C$622,0)),"",INDEX('Compliance Database'!$O$2:$O$622,MATCH(16,Engine!$C$2:$C$622,0)))
A30: =IF(ISNA(MATCH(17,Engine!$C$2:$C$622,0)),"",INDEX('Compliance Database'!$A$2:$A$622,MATCH(17,Engine!$C$2:$C$622,0))) | B30: =IF(ISNA(MATCH(17,Engine!$C$2:$C$622,0)),"",INDEX('Compliance Database'!$B$2:$B$622,MATCH(17,Engine!$C$2:$C$622,0))) | C30: =IF(ISNA(MATCH(17,Engine!$C$2:$C$622,0)),"",INDEX('Compliance Database'!$C$2:$C$622,MATCH(17,Engine!$C$2:$C$622,0))) | D30: =IF(ISNA(MATCH(17,Engine!$C$2:$C$622,0)),"",INDEX('Compliance Database'!$D$2:$D$622,MATCH(17,Engine!$C$2:$C$622,0))) | E30: =IF(ISNA(MATCH(17,Engine!$C$2:$C$622,0)),"",INDEX('Compliance Database'!$E$2:$E$622,MATCH(17,Engine!$C$2:$C$622,0))) | F30: =IF(ISNA(MATCH(17,Engine!$C$2:$C$622,0)),"",INDEX('Compliance Database'!$F$2:$F$622,MATCH(17,Engine!$C$2:$C$622,0))) | G30: =IF(ISNA(MATCH(17,Engine!$C$2:$C$622,0)),"",INDEX('Compliance Database'!$G$2:$G$622,MATCH(17,Engine!$C$2:$C$622,0))) | H30: =IF(ISNA(MATCH(17,Engine!$C$2:$C$622,0)),"",INDEX('Compliance Database'!$H$2:$H$622,MATCH(17,Engine!$C$2:$C$622,0))) | I30: =IF(ISNA(MATCH(17,Engine!$C$2:$C$622,0)),"",INDEX('Compliance Database'!$I$2:$I$622,MATCH(17,Engine!$C$2:$C$622,0))) | J30: =IF(ISNA(MATCH(17,Engine!$C$2:$C$622,0)),"",INDEX('Compliance Database'!$J$2:$J$622,MATCH(17,Engine!$C$2:$C$622,0))) | K30: =IF(ISNA(MATCH(17,Engine!$C$2:$C$622,0)),"",INDEX('Compliance Database'!$K$2:$K$622,MATCH(17,Engine!$C$2:$C$622,0))) | L30: =IF(ISNA(MATCH(17,Engine!$C$2:$C$622,0)),"",INDEX('Compliance Database'!$L$2:$L$622,MATCH(17,Engine!$C$2:$C$622,0))) | M30: =IF(ISNA(MATCH(17,Engine!$C$2:$C$622,0)),"",INDEX('Compliance Database'!$M$2:$M$622,MATCH(17,Engine!$C$2:$C$622,0))) | N30: =IF(ISNA(MATCH(17,Engine!$C$2:$C$622,0)),"",INDEX('Compliance Database'!$N$2:$N$622,MATCH(17,Engine!$C$2:$C$622,0))) | O30: =IF(ISNA(MATCH(17,Engine!$C$2:$C$622,0)),"",INDEX('Compliance Database'!$O$2:$O$622,MATCH(17,Engine!$C$2:$C$622,0)))
A31: =IF(ISNA(MATCH(18,Engine!$C$2:$C$622,0)),"",INDEX('Compliance Database'!$A$2:$A$622,MATCH(18,Engine!$C$2:$C$622,0))) | B31: =IF(ISNA(MATCH(18,Engine!$C$2:$C$622,0)),"",INDEX('Compliance Database'!$B$2:$B$622,MATCH(18,Engine!$C$2:$C$622,0))) | C31: =IF(ISNA(MATCH(18,Engine!$C$2:$C$622,0)),"",INDEX('Compliance Database'!$C$2:$C$622,MATCH(18,Engine!$C$2:$C$622,0))) | D31: =IF(ISNA(MATCH(18,Engine!$C$2:$C$622,0)),"",INDEX('Compliance Database'!$D$2:$D$622,MATCH(18,Engine!$C$2:$C$622,0))) | E31: =IF(ISNA(MATCH(18,Engine!$C$2:$C$622,0)),"",INDEX('Compliance Database'!$E$2:$E$622,MATCH(18,Engine!$C$2:$C$622,0))) | F31: =IF(ISNA(MATCH(18,Engine!$C$2:$C$622,0)),"",INDEX('Compliance Database'!$F$2:$F$622,MATCH(18,Engine!$C$2:$C$622,0))) | G31: =IF(ISNA(MATCH(18,Engine!$C$2:$C$622,0)),"",INDEX('Compliance Database'!$G$2:$G$622,MATCH(18,Engine!$C$2:$C$622,0))) | H31: =IF(ISNA(MATCH(18,Engine!$C$2:$C$622,0)),"",INDEX('Compliance Database'!$H$2:$H$622,MATCH(18,Engine!$C$2:$C$622,0))) | I31: =IF(ISNA(MATCH(18,Engine!$C$2:$C$622,0)),"",INDEX('Compliance Database'!$I$2:$I$622,MATCH(18,Engine!$C$2:$C$622,0))) | J31: =IF(ISNA(MATCH(18,Engine!$C$2:$C$622,0)),"",INDEX('Compliance Database'!$J$2:$J$622,MATCH(18,Engine!$C$2:$C$622,0))) | K31: =IF(ISNA(MATCH(18,Engine!$C$2:$C$622,0)),"",INDEX('Compliance Database'!$K$2:$K$622,MATCH(18,Engine!$C$2:$C$622,0))) | L31: =IF(ISNA(MATCH(18,Engine!$C$2:$C$622,0)),"",INDEX('Compliance Database'!$L$2:$L$622,MATCH(18,Engine!$C$2:$C$622,0))) | M31: =IF(ISNA(MATCH(18,Engine!$C$2:$C$622,0)),"",INDEX('Compliance Database'!$M$2:$M$622,MATCH(18,Engine!$C$2:$C$622,0))) | N31: =IF(ISNA(MATCH(18,Engine!$C$2:$C$622,0)),"",INDEX('Compliance Database'!$N$2:$N$622,MATCH(18,Engine!$C$2:$C$622,0))) | O31: =IF(ISNA(MATCH(18,Engine!$C$2:$C$622,0)),"",INDEX('Compliance Database'!$O$2:$O$622,MATCH(18,Engine!$C$2:$C$622,0)))
A32: =IF(ISNA(MATCH(19,Engine!$C$2:$C$622,0)),"",INDEX('Compliance Database'!$A$2:$A$622,MATCH(19,Engine!$C$2:$C$622,0))) | B32: =IF(ISNA(MATCH(19,Engine!$C$2:$C$622,0)),"",INDEX('Compliance Database'!$B$2:$B$622,MATCH(19,Engine!$C$2:$C$622,0))) | C32: =IF(ISNA(MATCH(19,Engine!$C$2:$C$622,0)),"",INDEX('Compliance Database'!$C$2:$C$622,MATCH(19,Engine!$C$2:$C$622,0))) | D32: =IF(ISNA(MATCH(19,Engine!$C$2:$C$622,0)),"",INDEX('Compliance Database'!$D$2:$D$622,MATCH(19,Engine!$C$2:$C$622,0))) | E32: =IF(ISNA(MATCH(19,Engine!$C$2:$C$622,0)),"",INDEX('Compliance Database'!$E$2:$E$622,MATCH(19,Engine!$C$2:$C$622,0))) | F32: =IF(ISNA(MATCH(19,Engine!$C$2:$C$622,0)),"",INDEX('Compliance Database'!$F$2:$F$622,MATCH(19,Engine!$C$2:$C$622,0))) | G32: =IF(ISNA(MATCH(19,Engine!$C$2:$C$622,0)),"",INDEX('Compliance Database'!$G$2:$G$622,MATCH(19,Engine!$C$2:$C$622,0))) | H32: =IF(ISNA(MATCH(19,Engine!$C$2:$C$622,0)),"",INDEX('Compliance Database'!$H$2:$H$622,MATCH(19,Engine!$C$2:$C$622,0))) | I32: =IF(ISNA(MATCH(19,Engine!$C$2:$C$622,0)),"",INDEX('Compliance Database'!$I$2:$I$622,MATCH(19,Engine!$C$2:$C$622,0))) | J32: =IF(ISNA(MATCH(19,Engine!$C$2:$C$622,0)),"",INDEX('Compliance Database'!$J$2:$J$622,MATCH(19,Engine!$C$2:$C$622,0))) | K32: =IF(ISNA(MATCH(19,Engine!$C$2:$C$622,0)),"",INDEX('Compliance Database'!$K$2:$K$622,MATCH(19,Engine!$C$2:$C$622,0))) | L32: =IF(ISNA(MATCH(19,Engine!$C$2:$C$622,0)),"",INDEX('Compliance Database'!$L$2:$L$622,MATCH(19,Engine!$C$2:$C$622,0))) | M32: =IF(ISNA(MATCH(19,Engine!$C$2:$C$622,0)),"",INDEX('Compliance Database'!$M$2:$M$622,MATCH(19,Engine!$C$2:$C$622,0))) | N32: =IF(ISNA(MATCH(19,Engine!$C$2:$C$622,0)),"",INDEX('Compliance Database'!$N$2:$N$622,MATCH(19,Engine!$C$2:$C$622,0))) | O32: =IF(ISNA(MATCH(19,Engine!$C$2:$C$622,0)),"",INDEX('Compliance Database'!$O$2:$O$622,MATCH(19,Engine!$C$2:$C$622,0)))
A33: =IF(ISNA(MATCH(20,Engine!$C$2:$C$622,0)),"",INDEX('Compliance Database'!$A$2:$A$622,MATCH(20,Engine!$C$2:$C$622,0))) | B33: =IF(ISNA(MATCH(20,Engine!$C$2:$C$622,0)),"",INDEX('Compliance Database'!$B$2:$B$622,MATCH(20,Engine!$C$2:$C$622,0))) | C33: =IF(ISNA(MATCH(20,Engine!$C$2:$C$622,0)),"",INDEX('Compliance Database'!$C$2:$C$622,MATCH(20,Engine!$C$2:$C$622,0))) | D33: =IF(ISNA(MATCH(20,Engine!$C$2:$C$622,0)),"",INDEX('Compliance Database'!$D$2:$D$622,MATCH(20,Engine!$C$2:$C$622,0))) | E33: =IF(ISNA(MATCH(20,Engine!$C$2:$C$622,0)),"",INDEX('Compliance Database'!$E$2:$E$622,MATCH(20,Engine!$C$2:$C$622,0))) | F33: =IF(ISNA(MATCH(20,Engine!$C$2:$C$622,0)),"",INDEX('Compliance Database'!$F$2:$F$622,MATCH(20,Engine!$C$2:$C$622,0))) | G33: =IF(ISNA(MATCH(20,Engine!$C$2:$C$622,0)),"",INDEX('Compliance Database'!$G$2:$G$622,MATCH(20,Engine!$C$2:$C$622,0))) | H33: =IF(ISNA(MATCH(20,Engine!$C$2:$C$622,0)),"",INDEX('Compliance Database'!$H$2:$H$622,MATCH(20,Engine!$C$2:$C$622,0))) | I33: =IF(ISNA(MATCH(20,Engine!$C$2:$C$622,0)),"",INDEX('Compliance Database'!$I$2:$I$622,MATCH(20,Engine!$C$2:$C$622,0))) | J33: =IF(ISNA(MATCH(20,Engine!$C$2:$C$622,0)),"",INDEX('Compliance Database'!$J$2:$J$622,MATCH(20,Engine!$C$2:$C$622,0))) | K33: =IF(ISNA(MATCH(20,Engine!$C$2:$C$622,0)),"",INDEX('Compliance Database'!$K$2:$K$622,MATCH(20,Engine!$C$2:$C$622,0))) | L33: =IF(ISNA(MATCH(20,Engine!$C$2:$C$622,0)),"",INDEX('Compliance Database'!$L$2:$L$622,MATCH(20,Engine!$C$2:$C$622,0))) | M33: =IF(ISNA(MATCH(20,Engine!$C$2:$C$622,0)),"",INDEX('Compliance Database'!$M$2:$M$622,MATCH(20,Engine!$C$2:$C$622,0))) | N33: =IF(ISNA(MATCH(20,Engine!$C$2:$C$622,0)),"",INDEX('Compliance Database'!$N$2:$N$622,MATCH(20,Engine!$C$2:$C$622,0))) | O33: =IF(ISNA(MATCH(20,Engine!$C$2:$C$622,0)),"",INDEX('Compliance Database'!$O$2:$O$622,MATCH(20,Engine!$C$2:$C$622,0)))
A34: =IF(ISNA(MATCH(21,Engine!$C$2:$C$622,0)),"",INDEX('Compliance Database'!$A$2:$A$622,MATCH(21,Engine!$C$2:$C$622,0))) | B34: =IF(ISNA(MATCH(21,Engine!$C$2:$C$622,0)),"",INDEX('Compliance Database'!$B$2:$B$622,MATCH(21,Engine!$C$2:$C$622,0))) | C34: =IF(ISNA(MATCH(21,Engine!$C$2:$C$622,0)),"",INDEX('Compliance Database'!$C$2:$C$622,MATCH(21,Engine!$C$2:$C$622,0))) | D34: =IF(ISNA(MATCH(21,Engine!$C$2:$C$622,0)),"",INDEX('Compliance Database'!$D$2:$D$622,MATCH(21,Engine!$C$2:$C$622,0))) | E34: =IF(ISNA(MATCH(21,Engine!$C$2:$C$622,0)),"",INDEX('Compliance Database'!$E$2:$E$622,MATCH(21,Engine!$C$2:$C$622,0))) | F34: =IF(ISNA(MATCH(21,Engine!$C$2:$C$622,0)),"",INDEX('Compliance Database'!$F$2:$F$622,MATCH(21,Engine!$C$2:$C$622,0))) | G34: =IF(ISNA(MATCH(21,Engine!$C$2:$C$622,0)),"",INDEX('Compliance Database'!$G$2:$G$622,MATCH(21,Engine!$C$2:$C$622,0))) | H34: =IF(ISNA(MATCH(21,Engine!$C$2:$C$622,0)),"",INDEX('Compliance Database'!$H$2:$H$622,MATCH(21,Engine!$C$2:$C$622,0))) | I34: =IF(ISNA(MATCH(21,Engine!$C$2:$C$622,0)),"",INDEX('Compliance Database'!$I$2:$I$622,MATCH(21,Engine!$C$2:$C$622,0))) | J34: =IF(ISNA(MATCH(21,Engine!$C$2:$C$622,0)),"",INDEX('Compliance Database'!$J$2:$J$622,MATCH(21,Engine!$C$2:$C$622,0))) | K34: =IF(ISNA(MATCH(21,Engine!$C$2:$C$622,0)),"",INDEX('Compliance Database'!$K$2:$K$622,MATCH(21,Engine!$C$2:$C$622,0))) | L34: =IF(ISNA(MATCH(21,Engine!$C$2:$C$622,0)),"",INDEX('Compliance Database'!$L$2:$L$622,MATCH(21,Engine!$C$2:$C$622,0))) | M34: =IF(ISNA(MATCH(21,Engine!$C$2:$C$622,0)),"",INDEX('Compliance Database'!$M$2:$M$622,MATCH(21,Engine!$C$2:$C$622,0))) | N34: =IF(ISNA(MATCH(21,Engine!$C$2:$C$622,0)),"",INDEX('Compliance Database'!$N$2:$N$622,MATCH(21,Engine!$C$2:$C$622,0))) | O34: =IF(ISNA(MATCH(21,Engine!$C$2:$C$622,0)),"",INDEX('Compliance Database'!$O$2:$O$622,MATCH(21,Engine!$C$2:$C$622,0)))
A35: =IF(ISNA(MATCH(22,Engine!$C$2:$C$622,0)),"",INDEX('Compliance Database'!$A$2:$A$622,MATCH(22,Engine!$C$2:$C$622,0))) | B35: =IF(ISNA(MATCH(22,Engine!$C$2:$C$622,0)),"",INDEX('Compliance Database'!$B$2:$B$622,MATCH(22,Engine!$C$2:$C$622,0))) | C35: =IF(ISNA(MATCH(22,Engine!$C$2:$C$622,0)),"",INDEX('Compliance Database'!$C$2:$C$622,MATCH(22,Engine!$C$2:$C$622,0))) | D35: =IF(ISNA(MATCH(22,Engine!$C$2:$C$622,0)),"",INDEX('Compliance Database'!$D$2:$D$622,MATCH(22,Engine!$C$2:$C$622,0))) | E35: =IF(ISNA(MATCH(22,Engine!$C$2:$C$622,0)),"",INDEX('Compliance Database'!$E$2:$E$622,MATCH(22,Engine!$C$2:$C$622,0))) | F35: =IF(ISNA(MATCH(22,Engine!$C$2:$C$622,0)),"",INDEX('Compliance Database'!$F$2:$F$622,MATCH(22,Engine!$C$2:$C$622,0))) | G35: =IF(ISNA(MATCH(22,Engine!$C$2:$C$622,0)),"",INDEX('Compliance Database'!$G$2:$G$622,MATCH(22,Engine!$C$2:$C$622,0))) | H35: =IF(ISNA(MATCH(22,Engine!$C$2:$C$622,0)),"",INDEX('Compliance Database'!$H$2:$H$622,MATCH(22,Engine!$C$2:$C$622,0))) | I35: =IF(ISNA(MATCH(22,Engine!$C$2:$C$622,0)),"",INDEX('Compliance Database'!$I$2:$I$622,MATCH(22,Engine!$C$2:$C$622,0))) | J35: =IF(ISNA(MATCH(22,Engine!$C$2:$C$622,0)),"",INDEX('Compliance Database'!$J$2:$J$622,MATCH(22,Engine!$C$2:$C$622,0))) | K35: =IF(ISNA(MATCH(22,Engine!$C$2:$C$622,0)),"",INDEX('Compliance Database'!$K$2:$K$622,MATCH(22,Engine!$C$2:$C$622,0))) | L35: =IF(ISNA(MATCH(22,Engine!$C$2:$C$622,0)),"",INDEX('Compliance Database'!$L$2:$L$622,MATCH(22,Engine!$C$2:$C$622,0))) | M35: =IF(ISNA(MATCH(22,Engine!$C$2:$C$622,0)),"",INDEX('Compliance Database'!$M$2:$M$622,MATCH(22,Engine!$C$2:$C$622,0))) | N35: =IF(ISNA(MATCH(22,Engine!$C$2:$C$622,0)),"",INDEX('Compliance Database'!$N$2:$N$622,MATCH(22,Engine!$C$2:$C$622,0))) | O35: =IF(ISNA(MATCH(22,Engine!$C$2:$C$622,0)),"",INDEX('Compliance Database'!$O$2:$O$622,MATCH(22,Engine!$C$2:$C$622,0)))
A36: =IF(ISNA(MATCH(23,Engine!$C$2:$C$622,0)),"",INDEX('Compliance Database'!$A$2:$A$622,MATCH(23,Engine!$C$2:$C$622,0))) | B36: =IF(ISNA(MATCH(23,Engine!$C$2:$C$622,0)),"",INDEX('Compliance Database'!$B$2:$B$622,MATCH(23,Engine!$C$2:$C$622,0))) | C36: =IF(ISNA(MATCH(23,Engine!$C$2:$C$622,0)),"",INDEX('Compliance Database'!$C$2:$C$622,MATCH(23,Engine!$C$2:$C$622,0))) | D36: =IF(ISNA(MATCH(23,Engine!$C$2:$C$622,0)),"",INDEX('Compliance Database'!$D$2:$D$622,MATCH(23,Engine!$C$2:$C$622,0))) | E36: =IF(ISNA(MATCH(23,Engine!$C$2:$C$622,0)),"",INDEX('Compliance Database'!$E$2:$E$622,MATCH(23,Engine!$C$2:$C$622,0))) | F36: =IF(ISNA(MATCH(23,Engine!$C$2:$C$622,0)),"",INDEX('Compliance Database'!$F$2:$F$622,MATCH(23,Engine!$C$2:$C$622,0))) | G36: =IF(ISNA(MATCH(23,Engine!$C$2:$C$622,0)),"",INDEX('Compliance Database'!$G$2:$G$622,MATCH(23,Engine!$C$2:$C$622,0))) | H36: =IF(ISNA(MATCH(23,Engine!$C$2:$C$622,0)),"",INDEX('Compliance Database'!$H$2:$H$622,MATCH(23,Engine!$C$2:$C$622,0))) | I36: =IF(ISNA(MATCH(23,Engine!$C$2:$C$622,0)),"",INDEX('Compliance Database'!$I$2:$I$622,MATCH(23,Engine!$C$2:$C$622,0))) | J36: =IF(ISNA(MATCH(23,Engine!$C$2:$C$622,0)),"",INDEX('Compliance Database'!$J$2:$J$622,MATCH(23,Engine!$C$2:$C$622,0))) | K36: =IF(ISNA(MATCH(23,Engine!$C$2:$C$622,0)),"",INDEX('Compliance Database'!$K$2:$K$622,MATCH(23,Engine!$C$2:$C$622,0))) | L36: =IF(ISNA(MATCH(23,Engine!$C$2:$C$622,0)),"",INDEX('Compliance Database'!$L$2:$L$622,MATCH(23,Engine!$C$2:$C$622,0))) | M36: =IF(ISNA(MATCH(23,Engine!$C$2:$C$622,0)),"",INDEX('Compliance Database'!$M$2:$M$622,MATCH(23,Engine!$C$2:$C$622,0))) | N36: =IF(ISNA(MATCH(23,Engine!$C$2:$C$622,0)),"",INDEX('Compliance Database'!$N$2:$N$622,MATCH(23,Engine!$C$2:$C$622,0))) | O36: =IF(ISNA(MATCH(23,Engine!$C$2:$C$622,0)),"",INDEX('Compliance Database'!$O$2:$O$622,MATCH(23,Engine!$C$2:$C$622,0)))
A37: =IF(ISNA(MATCH(24,Engine!$C$2:$C$622,0)),"",INDEX('Compliance Database'!$A$2:$A$622,MATCH(24,Engine!$C$2:$C$622,0))) | B37: =IF(ISNA(MATCH(24,Engine!$C$2:$C$622,0)),"",INDEX('Compliance Database'!$B$2:$B$622,MATCH(24,Engine!$C$2:$C$622,0))) | C37: =IF(ISNA(MATCH(24,Engine!$C$2:$C$622,0)),"",INDEX('Compliance Database'!$C$2:$C$622,MATCH(24,Engine!$C$2:$C$622,0))) | D37: =IF(ISNA(MATCH(24,Engine!$C$2:$C$622,0)),"",INDEX('Compliance Database'!$D$2:$D$622,MATCH(24,Engine!$C$2:$C$622,0))) | E37: =IF(ISNA(MATCH(24,Engine!$C$2:$C$622,0)),"",INDEX('Compliance Database'!$E$2:$E$622,MATCH(24,Engine!$C$2:$C$622,0))) | F37: =IF(ISNA(MATCH(24,Engine!$C$2:$C$622,0)),"",INDEX('Compliance Database'!$F$2:$F$622,MATCH(24,Engine!$C$2:$C$622,0))) | G37: =IF(ISNA(MATCH(24,Engine!$C$2:$C$622,0)),"",INDEX('Compliance Database'!$G$2:$G$622,MATCH(24,Engine!$C$2:$C$622,0))) | H37: =IF(ISNA(MATCH(24,Engine!$C$2:$C$622,0)),"",INDEX('Compliance Database'!$H$2:$H$622,MATCH(24,Engine!$C$2:$C$622,0))) | I37: =IF(ISNA(MATCH(24,Engine!$C$2:$C$622,0)),"",INDEX('Compliance Database'!$I$2:$I$622,MATCH(24,Engine!$C$2:$C$622,0))) | J37: =IF(ISNA(MATCH(24,Engine!$C$2:$C$622,0)),"",INDEX('Compliance Database'!$J$2:$J$622,MATCH(24,Engine!$C$2:$C$622,0))) | K37: =IF(ISNA(MATCH(24,Engine!$C$2:$C$622,0)),"",INDEX('Compliance Database'!$K$2:$K$622,MATCH(24,Engine!$C$2:$C$622,0))) | L37: =IF(ISNA(MATCH(24,Engine!$C$2:$C$622,0)),"",INDEX('Compliance Database'!$L$2:$L$622,MATCH(24,Engine!$C$2:$C$622,0))) | M37: =IF(ISNA(MATCH(24,Engine!$C$2:$C$622,0)),"",INDEX('Compliance Database'!$M$2:$M$622,MATCH(24,Engine!$C$2:$C$622,0))) | N37: =IF(ISNA(MATCH(24,Engine!$C$2:$C$622,0)),"",INDEX('Compliance Database'!$N$2:$N$622,MATCH(24,Engine!$C$2:$C$622,0))) | O37: =IF(ISNA(MATCH(24,Engine!$C$2:$C$622,0)),"",INDEX('Compliance Database'!$O$2:$O$622,MATCH(24,Engine!$C$2:$C$622,0)))
A38: =IF(ISNA(MATCH(25,Engine!$C$2:$C$622,0)),"",INDEX('Compliance Database'!$A$2:$A$622,MATCH(25,Engine!$C$2:$C$622,0))) | B38: =IF(ISNA(MATCH(25,Engine!$C$2:$C$622,0)),"",INDEX('Compliance Database'!$B$2:$B$622,MATCH(25,Engine!$C$2:$C$622,0))) | C38: =IF(ISNA(MATCH(25,Engine!$C$2:$C$622,0)),"",INDEX('Compliance Database'!$C$2:$C$622,MATCH(25,Engine!$C$2:$C$622,0))) | D38: =IF(ISNA(MATCH(25,Engine!$C$2:$C$622,0)),"",INDEX('Compliance Database'!$D$2:$D$622,MATCH(25,Engine!$C$2:$C$622,0))) | E38: =IF(ISNA(MATCH(25,Engine!$C$2:$C$622,0)),"",INDEX('Compliance Database'!$E$2:$E$622,MATCH(25,Engine!$C$2:$C$622,0))) | F38: =IF(ISNA(MATCH(25,Engine!$C$2:$C$622,0)),"",INDEX('Compliance Database'!$F$2:$F$622,MATCH(25,Engine!$C$2:$C$622,0))) | G38: =IF(ISNA(MATCH(25,Engine!$C$2:$C$622,0)),"",INDEX('Compliance Database'!$G$2:$G$622,MATCH(25,Engine!$C$2:$C$622,0))) | H38: =IF(ISNA(MATCH(25,Engine!$C$2:$C$622,0)),"",INDEX('Compliance Database'!$H$2:$H$622,MATCH(25,Engine!$C$2:$C$622,0))) | I38: =IF(ISNA(MATCH(25,Engine!$C$2:$C$622,0)),"",INDEX('Compliance Database'!$I$2:$I$622,MATCH(25,Engine!$C$2:$C$622,0))) | J38: =IF(ISNA(MATCH(25,Engine!$C$2:$C$622,0)),"",INDEX('Compliance Database'!$J$2:$J$622,MATCH(25,Engine!$C$2:$C$622,0))) | K38: =IF(ISNA(MATCH(25,Engine!$C$2:$C$622,0)),"",INDEX('Compliance Database'!$K$2:$K$622,MATCH(25,Engine!$C$2:$C$622,0))) | L38: =IF(ISNA(MATCH(25,Engine!$C$2:$C$622,0)),"",INDEX('Compliance Database'!$L$2:$L$622,MATCH(25,Engine!$C$2:$C$622,0))) | M38: =IF(ISNA(MATCH(25,Engine!$C$2:$C$622,0)),"",INDEX('Compliance Database'!$M$2:$M$622,MATCH(25,Engine!$C$2:$C$622,0))) | N38: =IF(ISNA(MATCH(25,Engine!$C$2:$C$622,0)),"",INDEX('Compliance Database'!$N$2:$N$622,MATCH(25,Engine!$C$2:$C$622,0))) | O38: =IF(ISNA(MATCH(25,Engine!$C$2:$C$622,0)),"",INDEX('Compliance Database'!$O$2:$O$622,MATCH(25,Engine!$C$2:$C$622,0)))
A39: =IF(ISNA(MATCH(26,Engine!$C$2:$C$622,0)),"",INDEX('Compliance Database'!$A$2:$A$622,MATCH(26,Engine!$C$2:$C$622,0))) | B39: =IF(ISNA(MATCH(26,Engine!$C$2:$C$622,0)),"",INDEX('Compliance Database'!$B$2:$B$622,MATCH(26,Engine!$C$2:$C$622,0))) | C39: =IF(ISNA(MATCH(26,Engine!$C$2:$C$622,0)),"",INDEX('Compliance Database'!$C$2:$C$622,MATCH(26,Engine!$C$2:$C$622,0))) | D39: =IF(ISNA(MATCH(26,Engine!$C$2:$C$622,0)),"",INDEX('Compliance Database'!$D$2:$D$622,MATCH(26,Engine!$C$2:$C$622,0))) | E39: =IF(ISNA(MATCH(26,Engine!$C$2:$C$622,0)),"",INDEX('Compliance Database'!$E$2:$E$622,MATCH(26,Engine!$C$2:$C$622,0))) | F39: =IF(ISNA(MATCH(26,Engine!$C$2:$C$622,0)),"",INDEX('Compliance Database'!$F$2:$F$622,MATCH(26,Engine!$C$2:$C$622,0))) | G39: =IF(ISNA(MATCH(26,Engine!$C$2:$C$622,0)),"",INDEX('Compliance Database'!$G$2:$G$622,MATCH(26,Engine!$C$2:$C$622,0))) | H39: =IF(ISNA(MATCH(26,Engine!$C$2:$C$622,0)),"",INDEX('Compliance Database'!$H$2:$H$622,MATCH(26,Engine!$C$2:$C$622,0))) | I39: =IF(ISNA(MATCH(26,Engine!$C$2:$C$622,0)),"",INDEX('Compliance Database'!$I$2:$I$622,MATCH(26,Engine!$C$2:$C$622,0))) | J39: =IF(ISNA(MATCH(26,Engine!$C$2:$C$622,0)),"",INDEX('Compliance Database'!$J$2:$J$622,MATCH(26,Engine!$C$2:$C$622,0))) | K39: =IF(ISNA(MATCH(26,Engine!$C$2:$C$622,0)),"",INDEX('Compliance Database'!$K$2:$K$622,MATCH(26,Engine!$C$2:$C$622,0))) | L39: =IF(ISNA(MATCH(26,Engine!$C$2:$C$622,0)),"",INDEX('Compliance Database'!$L$2:$L$622,MATCH(26,Engine!$C$2:$C$622,0))) | M39: =IF(ISNA(MATCH(26,Engine!$C$2:$C$622,0)),"",INDEX('Compliance Database'!$M$2:$M$622,MATCH(26,Engine!$C$2:$C$622,0))) | N39: =IF(ISNA(MATCH(26,Engine!$C$2:$C$622,0)),"",INDEX('Compliance Database'!$N$2:$N$622,MATCH(26,Engine!$C$2:$C$622,0))) | O39: =IF(ISNA(MATCH(26,Engine!$C$2:$C$622,0)),"",INDEX('Compliance Database'!$O$2:$O$622,MATCH(26,Engine!$C$2:$C$622,0)))
A40: =IF(ISNA(MATCH(27,Engine!$C$2:$C$622,0)),"",INDEX('Compliance Database'!$A$2:$A$622,MATCH(27,Engine!$C$2:$C$622,0))) | B40: =IF(ISNA(MATCH(27,Engine!$C$2:$C$622,0)),"",INDEX('Compliance Database'!$B$2:$B$622,MATCH(27,Engine!$C$2:$C$622,0))) | C40: =IF(ISNA(MATCH(27,Engine!$C$2:$C$622,0)),"",INDEX('Compliance Database'!$C$2:$C$622,MATCH(27,Engine!$C$2:$C$622,0))) | D40: =IF(ISNA(MATCH(27,Engine!$C$2:$C$622,0)),"",INDEX('Compliance Database'!$D$2:$D$622,MATCH(27,Engine!$C$2:$C$622,0))) | E40: =IF(ISNA(MATCH(27,Engine!$C$2:$C$622,0)),"",INDEX('Compliance Database'!$E$2:$E$622,MATCH(27,Engine!$C$2:$C$622,0))) | F40: =IF(ISNA(MATCH(27,Engine!$C$2:$C$622,0)),"",INDEX('Compliance Database'!$F$2:$F$622,MATCH(27,Engine!$C$2:$C$622,0))) | G40: =IF(ISNA(MATCH(27,Engine!$C$2:$C$622,0)),"",INDEX('Compliance Database'!$G$2:$G$622,MATCH(27,Engine!$C$2:$C$622,0))) | H40: =IF(ISNA(MATCH(27,Engine!$C$2:$C$622,0)),"",INDEX('Compliance Database'!$H$2:$H$622,MATCH(27,Engine!$C$2:$C$622,0))) | I40: =IF(ISNA(MATCH(27,Engine!$C$2:$C$622,0)),"",INDEX('Compliance Database'!$I$2:$I$622,MATCH(27,Engine!$C$2:$C$622,0))) | J40: =IF(ISNA(MATCH(27,Engine!$C$2:$C$622,0)),"",INDEX('Compliance Database'!$J$2:$J$622,MATCH(27,Engine!$C$2:$C$622,0))) | K40: =IF(ISNA(MATCH(27,Engine!$C$2:$C$622,0)),"",INDEX('Compliance Database'!$K$2:$K$622,MATCH(27,Engine!$C$2:$C$622,0))) | L40: =IF(ISNA(MATCH(27,Engine!$C$2:$C$622,0)),"",INDEX('Compliance Database'!$L$2:$L$622,MATCH(27,Engine!$C$2:$C$622,0))) | M40: =IF(ISNA(MATCH(27,Engine!$C$2:$C$622,0)),"",INDEX('Compliance Database'!$M$2:$M$622,MATCH(27,Engine!$C$2:$C$622,0))) | N40: =IF(ISNA(MATCH(27,Engine!$C$2:$C$622,0)),"",INDEX('Compliance Database'!$N$2:$N$622,MATCH(27,Engine!$C$2:$C$622,0))) | O40: =IF(ISNA(MATCH(27,Engine!$C$2:$C$622,0)),"",INDEX('Compliance Database'!$O$2:$O$622,MATCH(27,Engine!$C$2:$C$622,0)))
A41: =IF(ISNA(MATCH(28,Engine!$C$2:$C$622,0)),"",INDEX('Compliance Database'!$A$2:$A$622,MATCH(28,Engine!$C$2:$C$622,0))) | B41: =IF(ISNA(MATCH(28,Engine!$C$2:$C$622,0)),"",INDEX('Compliance Database'!$B$2:$B$622,MATCH(28,Engine!$C$2:$C$622,0))) | C41: =IF(ISNA(MATCH(28,Engine!$C$2:$C$622,0)),"",INDEX('Compliance Database'!$C$2:$C$622,MATCH(28,Engine!$C$2:$C$622,0))) | D41: =IF(ISNA(MATCH(28,Engine!$C$2:$C$622,0)),"",INDEX('Compliance Database'!$D$2:$D$622,MATCH(28,Engine!$C$2:$C$622,0))) | E41: =IF(ISNA(MATCH(28,Engine!$C$2:$C$622,0)),"",INDEX('Compliance Database'!$E$2:$E$622,MATCH(28,Engine!$C$2:$C$622,0))) | F41: =IF(ISNA(MATCH(28,Engine!$C$2:$C$622,0)),"",INDEX('Compliance Database'!$F$2:$F$622,MATCH(28,Engine!$C$2:$C$622,0))) | G41: =IF(ISNA(MATCH(28,Engine!$C$2:$C$622,0)),"",INDEX('Compliance Database'!$G$2:$G$622,MATCH(28,Engine!$C$2:$C$622,0))) | H41: =IF(ISNA(MATCH(28,Engine!$C$2:$C$622,0)),"",INDEX('Compliance Database'!$H$2:$H$622,MATCH(28,Engine!$C$2:$C$622,0))) | I41: =IF(ISNA(MATCH(28,Engine!$C$2:$C$622,0)),"",INDEX('Compliance Database'!$I$2:$I$622,MATCH(28,Engine!$C$2:$C$622,0))) | J41: =IF(ISNA(MATCH(28,Engine!$C$2:$C$622,0)),"",INDEX('Compliance Database'!$J$2:$J$622,MATCH(28,Engine!$C$2:$C$622,0))) | K41: =IF(ISNA(MATCH(28,Engine!$C$2:$C$622,0)),"",INDEX('Compliance Database'!$K$2:$K$622,MATCH(28,Engine!$C$2:$C$622,0))) | L41: =IF(ISNA(MATCH(28,Engine!$C$2:$C$622,0)),"",INDEX('Compliance Database'!$L$2:$L$622,MATCH(28,Engine!$C$2:$C$622,0))) | M41: =IF(ISNA(MATCH(28,Engine!$C$2:$C$622,0)),"",INDEX('Compliance Database'!$M$2:$M$622,MATCH(28,Engine!$C$2:$C$622,0))) | N41: =IF(ISNA(MATCH(28,Engine!$C$2:$C$622,0)),"",INDEX('Compliance Database'!$N$2:$N$622,MATCH(28,Engine!$C$2:$C$622,0))) | O41: =IF(ISNA(MATCH(28,Engine!$C$2:$C$622,0)),"",INDEX('Compliance Database'!$O$2:$O$622,MATCH(28,Engine!$C$2:$C$622,0)))
A42: =IF(ISNA(MATCH(29,Engine!$C$2:$C$622,0)),"",INDEX('Compliance Database'!$A$2:$A$622,MATCH(29,Engine!$C$2:$C$622,0))) | B42: =IF(ISNA(MATCH(29,Engine!$C$2:$C$622,0)),"",INDEX('Compliance Database'!$B$2:$B$622,MATCH(29,Engine!$C$2:$C$622,0))) | C42: =IF(ISNA(MATCH(29,Engine!$C$2:$C$622,0)),"",INDEX('Compliance Database'!$C$2:$C$622,MATCH(29,Engine!$C$2:$C$622,0))) | D42: =IF(ISNA(MATCH(29,Engine!$C$2:$C$622,0)),"",INDEX('Compliance Database'!$D$2:$D$622,MATCH(29,Engine!$C$2:$C$622,0))) | E42: =IF(ISNA(MATCH(29,Engine!$C$2:$C$622,0)),"",INDEX('Compliance Database'!$E$2:$E$622,MATCH(29,Engine!$C$2:$C$622,0))) | F42: =IF(ISNA(MATCH(29,Engine!$C$2:$C$622,0)),"",INDEX('Compliance Database'!$F$2:$F$622,MATCH(29,Engine!$C$2:$C$622,0))) | G42: =IF(ISNA(MATCH(29,Engine!$C$2:$C$622,0)),"",INDEX('Compliance Database'!$G$2:$G$622,MATCH(29,Engine!$C$2:$C$622,0))) | H42: =IF(ISNA(MATCH(29,Engine!$C$2:$C$622,0)),"",INDEX('Compliance Database'!$H$2:$H$622,MATCH(29,Engine!$C$2:$C$622,0))) | I42: =IF(ISNA(MATCH(29,Engine!$C$2:$C$622,0)),"",INDEX('Compliance Database'!$I$2:$I$622,MATCH(29,Engine!$C$2:$C$622,0))) | J42: =IF(ISNA(MATCH(29,Engine!$C$2:$C$622,0)),"",INDEX('Compliance Database'!$J$2:$J$622,MATCH(29,Engine!$C$2:$C$622,0))) | K42: =IF(ISNA(MATCH(29,Engine!$C$2:$C$622,0)),"",INDEX('Compliance Database'!$K$2:$K$622,MATCH(29,Engine!$C$2:$C$622,0))) | L42: =IF(ISNA(MATCH(29,Engine!$C$2:$C$622,0)),"",INDEX('Compliance Database'!$L$2:$L$622,MATCH(29,Engine!$C$2:$C$622,0))) | M42: =IF(ISNA(MATCH(29,Engine!$C$2:$C$622,0)),"",INDEX('Compliance Database'!$M$2:$M$622,MATCH(29,Engine!$C$2:$C$622,0))) | N42: =IF(ISNA(MATCH(29,Engine!$C$2:$C$622,0)),"",INDEX('Compliance Database'!$N$2:$N$622,MATCH(29,Engine!$C$2:$C$622,0))) | O42: =IF(ISNA(MATCH(29,Engine!$C$2:$C$622,0)),"",INDEX('Compliance Database'!$O$2:$O$622,MATCH(29,Engine!$C$2:$C$622,0)))
A43: =IF(ISNA(MATCH(30,Engine!$C$2:$C$622,0)),"",INDEX('Compliance Database'!$A$2:$A$622,MATCH(30,Engine!$C$2:$C$622,0))) | B43: =IF(ISNA(MATCH(30,Engine!$C$2:$C$622,0)),"",INDEX('Compliance Database'!$B$2:$B$622,MATCH(30,Engine!$C$2:$C$622,0))) | C43: =IF(ISNA(MATCH(30,Engine!$C$2:$C$622,0)),"",INDEX('Compliance Database'!$C$2:$C$622,MATCH(30,Engine!$C$2:$C$622,0))) | D43: =IF(ISNA(MATCH(30,Engine!$C$2:$C$622,0)),"",INDEX('Compliance Database'!$D$2:$D$622,MATCH(30,Engine!$C$2:$C$622,0))) | E43: =IF(ISNA(MATCH(30,Engine!$C$2:$C$622,0)),"",INDEX('Compliance Database'!$E$2:$E$622,MATCH(30,Engine!$C$2:$C$622,0))) | F43: =IF(ISNA(MATCH(30,Engine!$C$2:$C$622,0)),"",INDEX('Compliance Database'!$F$2:$F$622,MATCH(30,Engine!$C$2:$C$622,0))) | G43: =IF(ISNA(MATCH(30,Engine!$C$2:$C$622,0)),"",INDEX('Compliance Database'!$G$2:$G$622,MATCH(30,Engine!$C$2:$C$622,0))) | H43: =IF(ISNA(MATCH(30,Engine!$C$2:$C$622,0)),"",INDEX('Compliance Database'!$H$2:$H$622,MATCH(30,Engine!$C$2:$C$622,0))) | I43: =IF(ISNA(MATCH(30,Engine!$C$2:$C$622,0)),"",INDEX('Compliance Database'!$I$2:$I$622,MATCH(30,Engine!$C$2:$C$622,0))) | J43: =IF(ISNA(MATCH(30,Engine!$C$2:$C$622,0)),"",INDEX('Compliance Database'!$J$2:$J$622,MATCH(30,Engine!$C$2:$C$622,0))) | K43: =IF(ISNA(MATCH(30,Engine!$C$2:$C$622,0)),"",INDEX('Compliance Database'!$K$2:$K$622,MATCH(30,Engine!$C$2:$C$622,0))) | L43: =IF(ISNA(MATCH(30,Engine!$C$2:$C$622,0)),"",INDEX('Compliance Database'!$L$2:$L$622,MATCH(30,Engine!$C$2:$C$622,0))) | M43: =IF(ISNA(MATCH(30,Engine!$C$2:$C$622,0)),"",INDEX('Compliance Database'!$M$2:$M$622,MATCH(30,Engine!$C$2:$C$622,0))) | N43: =IF(ISNA(MATCH(30,Engine!$C$2:$C$622,0)),"",INDEX('Compliance Database'!$N$2:$N$622,MATCH(30,Engine!$C$2:$C$622,0))) | O43: =IF(ISNA(MATCH(30,Engine!$C$2:$C$622,0)),"",INDEX('Compliance Database'!$O$2:$O$622,MATCH(30,Engine!$C$2:$C$622,0)))
A44: =IF(ISNA(MATCH(31,Engine!$C$2:$C$622,0)),"",INDEX('Compliance Database'!$A$2:$A$622,MATCH(31,Engine!$C$2:$C$622,0))) | B44: =IF(ISNA(MATCH(31,Engine!$C$2:$C$622,0)),"",INDEX('Compliance Database'!$B$2:$B$622,MATCH(31,Engine!$C$2:$C$622,0))) | C44: =IF(ISNA(MATCH(31,Engine!$C$2:$C$622,0)),"",INDEX('Compliance Database'!$C$2:$C$622,MATCH(31,Engine!$C$2:$C$622,0))) | D44: =IF(ISNA(MATCH(31,Engine!$C$2:$C$622,0)),"",INDEX('Compliance Database'!$D$2:$D$622,MATCH(31,Engine!$C$2:$C$622,0))) | E44: =IF(ISNA(MATCH(31,Engine!$C$2:$C$622,0)),"",INDEX('Compliance Database'!$E$2:$E$622,MATCH(31,Engine!$C$2:$C$622,0))) | F44: =IF(ISNA(MATCH(31,Engine!$C$2:$C$622,0)),"",INDEX('Compliance Database'!$F$2:$F$622,MATCH(31,Engine!$C$2:$C$622,0))) | G44: =IF(ISNA(MATCH(31,Engine!$C$2:$C$622,0)),"",INDEX('Compliance Database'!$G$2:$G$622,MATCH(31,Engine!$C$2:$C$622,0))) | H44: =IF(ISNA(MATCH(31,Engine!$C$2:$C$622,0)),"",INDEX('Compliance Database'!$H$2:$H$622,MATCH(31,Engine!$C$2:$C$622,0))) | I44: =IF(ISNA(MATCH(31,Engine!$C$2:$C$622,0)),"",INDEX('Compliance Database'!$I$2:$I$622,MATCH(31,Engine!$C$2:$C$622,0))) | J44: =IF(ISNA(MATCH(31,Engine!$C$2:$C$622,0)),"",INDEX('Compliance Database'!$J$2:$J$622,MATCH(31,Engine!$C$2:$C$622,0))) | K44: =IF(ISNA(MATCH(31,Engine!$C$2:$C$622,0)),"",INDEX('Compliance Database'!$K$2:$K$622,MATCH(31,Engine!$C$2:$C$622,0))) | L44: =IF(ISNA(MATCH(31,Engine!$C$2:$C$622,0)),"",INDEX('Compliance Database'!$L$2:$L$622,MATCH(31,Engine!$C$2:$C$622,0))) | M44: =IF(ISNA(MATCH(31,Engine!$C$2:$C$622,0)),"",INDEX('Compliance Database'!$M$2:$M$622,MATCH(31,Engine!$C$2:$C$622,0))) | N44: =IF(ISNA(MATCH(31,Engine!$C$2:$C$622,0)),"",INDEX('Compliance Database'!$N$2:$N$622,MATCH(31,Engine!$C$2:$C$622,0))) | O44: =IF(ISNA(MATCH(31,Engine!$C$2:$C$622,0)),"",INDEX('Compliance Database'!$O$2:$O$622,MATCH(31,Engine!$C$2:$C$622,0)))
A45: =IF(ISNA(MATCH(32,Engine!$C$2:$C$622,0)),"",INDEX('Compliance Database'!$A$2:$A$622,MATCH(32,Engine!$C$2:$C$622,0))) | B45: =IF(ISNA(MATCH(32,Engine!$C$2:$C$622,0)),"",INDEX('Compliance Database'!$B$2:$B$622,MATCH(32,Engine!$C$2:$C$622,0))) | C45: =IF(ISNA(MATCH(32,Engine!$C$2:$C$622,0)),"",INDEX('Compliance Database'!$C$2:$C$622,MATCH(32,Engine!$C$2:$C$622,0))) | D45: =IF(ISNA(MATCH(32,Engine!$C$2:$C$622,0)),"",INDEX('Compliance Database'!$D$2:$D$622,MATCH(32,Engine!$C$2:$C$622,0))) | E45: =IF(ISNA(MATCH(32,Engine!$C$2:$C$622,0)),"",INDEX('Compliance Database'!$E$2:$E$622,MATCH(32,Engine!$C$2:$C$622,0))) | F45: =IF(ISNA(MATCH(32,Engine!$C$2:$C$622,0)),"",INDEX('Compliance Database'!$F$2:$F$622,MATCH(32,Engine!$C$2:$C$622,0))) | G45: =IF(ISNA(MATCH(32,Engine!$C$2:$C$622,0)),"",INDEX('Compliance Database'!$G$2:$G$622,MATCH(32,Engine!$C$2:$C$622,0))) | H45: =IF(ISNA(MATCH(32,Engine!$C$2:$C$622,0)),"",INDEX('Compliance Database'!$H$2:$H$622,MATCH(32,Engine!$C$2:$C$622,0))) | I45: =IF(ISNA(MATCH(32,Engine!$C$2:$C$622,0)),"",INDEX('Compliance Database'!$I$2:$I$622,MATCH(32,Engine!$C$2:$C$622,0))) | J45: =IF(ISNA(MATCH(32,Engine!$C$2:$C$622,0)),"",INDEX('Compliance Database'!$J$2:$J$622,MATCH(32,Engine!$C$2:$C$622,0))) | K45: =IF(ISNA(MATCH(32,Engine!$C$2:$C$622,0)),"",INDEX('Compliance Database'!$K$2:$K$622,MATCH(32,Engine!$C$2:$C$622,0))) | L45: =IF(ISNA(MATCH(32,Engine!$C$2:$C$622,0)),"",INDEX('Compliance Database'!$L$2:$L$622,MATCH(32,Engine!$C$2:$C$622,0))) | M45: =IF(ISNA(MATCH(32,Engine!$C$2:$C$622,0)),"",INDEX('Compliance Database'!$M$2:$M$622,MATCH(32,Engine!$C$2:$C$622,0))) | N45: =IF(ISNA(MATCH(32,Engine!$C$2:$C$622,0)),"",INDEX('Compliance Database'!$N$2:$N$622,MATCH(32,Engine!$C$2:$C$622,0))) | O45: =IF(ISNA(MATCH(32,Engine!$C$2:$C$622,0)),"",INDEX('Compliance Database'!$O$2:$O$622,MATCH(32,Engine!$C$2:$C$622,0)))
A46: =IF(ISNA(MATCH(33,Engine!$C$2:$C$622,0)),"",INDEX('Compliance Database'!$A$2:$A$622,MATCH(33,Engine!$C$2:$C$622,0))) | B46: =IF(ISNA(MATCH(33,Engine!$C$2:$C$622,0)),"",INDEX('Compliance Database'!$B$2:$B$622,MATCH(33,Engine!$C$2:$C$622,0))) | C46: =IF(ISNA(MATCH(33,Engine!$C$2:$C$622,0)),"",INDEX('Compliance Database'!$C$2:$C$622,MATCH(33,Engine!$C$2:$C$622,0))) | D46: =IF(ISNA(MATCH(33,Engine!$C$2:$C$622,0)),"",INDEX('Compliance Database'!$D$2:$D$622,MATCH(33,Engine!$C$2:$C$622,0))) | E46: =IF(ISNA(MATCH(33,Engine!$C$2:$C$622,0)),"",INDEX('Compliance Database'!$E$2:$E$622,MATCH(33,Engine!$C$2:$C$622,0))) | F46: =IF(ISNA(MATCH(33,Engine!$C$2:$C$622,0)),"",INDEX('Compliance Database'!$F$2:$F$622,MATCH(33,Engine!$C$2:$C$622,0))) | G46: =IF(ISNA(MATCH(33,Engine!$C$2:$C$622,0)),"",INDEX('Compliance Database'!$G$2:$G$622,MATCH(33,Engine!$C$2:$C$622,0))) | H46: =IF(ISNA(MATCH(33,Engine!$C$2:$C$622,0)),"",INDEX('Compliance Database'!$H$2:$H$622,MATCH(33,Engine!$C$2:$C$622,0))) | I46: =IF(ISNA(MATCH(33,Engine!$C$2:$C$622,0)),"",INDEX('Compliance Database'!$I$2:$I$622,MATCH(33,Engine!$C$2:$C$622,0))) | J46: =IF(ISNA(MATCH(33,Engine!$C$2:$C$622,0)),"",INDEX('Compliance Database'!$J$2:$J$622,MATCH(33,Engine!$C$2:$C$622,0))) | K46: =IF(ISNA(MATCH(33,Engine!$C$2:$C$622,0)),"",INDEX('Compliance Database'!$K$2:$K$622,MATCH(33,Engine!$C$2:$C$622,0))) | L46: =IF(ISNA(MATCH(33,Engine!$C$2:$C$622,0)),"",INDEX('Compliance Database'!$L$2:$L$622,MATCH(33,Engine!$C$2:$C$622,0))) | M46: =IF(ISNA(MATCH(33,Engine!$C$2:$C$622,0)),"",INDEX('Compliance Database'!$M$2:$M$622,MATCH(33,Engine!$C$2:$C$622,0))) | N46: =IF(ISNA(MATCH(33,Engine!$C$2:$C$622,0)),"",INDEX('Compliance Database'!$N$2:$N$622,MATCH(33,Engine!$C$2:$C$622,0))) | O46: =IF(ISNA(MATCH(33,Engine!$C$2:$C$622,0)),"",INDEX('Compliance Database'!$O$2:$O$622,MATCH(33,Engine!$C$2:$C$622,0)))
A47: =IF(ISNA(MATCH(34,Engine!$C$2:$C$622,0)),"",INDEX('Compliance Database'!$A$2:$A$622,MATCH(34,Engine!$C$2:$C$622,0))) | B47: =IF(ISNA(MATCH(34,Engine!$C$2:$C$622,0)),"",INDEX('Compliance Database'!$B$2:$B$622,MATCH(34,Engine!$C$2:$C$622,0))) | C47: =IF(ISNA(MATCH(34,Engine!$C$2:$C$622,0)),"",INDEX('Compliance Database'!$C$2:$C$622,MATCH(34,Engine!$C$2:$C$622,0))) | D47: =IF(ISNA(MATCH(34,Engine!$C$2:$C$622,0)),"",INDEX('Compliance Database'!$D$2:$D$622,MATCH(34,Engine!$C$2:$C$622,0))) | E47: =IF(ISNA(MATCH(34,Engine!$C$2:$C$622,0)),"",INDEX('Compliance Database'!$E$2:$E$622,MATCH(34,Engine!$C$2:$C$622,0))) | F47: =IF(ISNA(MATCH(34,Engine!$C$2:$C$622,0)),"",INDEX('Compliance Database'!$F$2:$F$622,MATCH(34,Engine!$C$2:$C$622,0))) | G47: =IF(ISNA(MATCH(34,Engine!$C$2:$C$622,0)),"",INDEX('Compliance Database'!$G$2:$G$622,MATCH(34,Engine!$C$2:$C$622,0))) | H47: =IF(ISNA(MATCH(34,Engine!$C$2:$C$622,0)),"",INDEX('Compliance Database'!$H$2:$H$622,MATCH(34,Engine!$C$2:$C$622,0))) | I47: =IF(ISNA(MATCH(34,Engine!$C$2:$C$622,0)),"",INDEX('Compliance Database'!$I$2:$I$622,MATCH(34,Engine!$C$2:$C$622,0))) | J47: =IF(ISNA(MATCH(34,Engine!$C$2:$C$622,0)),"",INDEX('Compliance Database'!$J$2:$J$622,MATCH(34,Engine!$C$2:$C$622,0))) | K47: =IF(ISNA(MATCH(34,Engine!$C$2:$C$622,0)),"",INDEX('Compliance Database'!$K$2:$K$622,MATCH(34,Engine!$C$2:$C$622,0))) | L47: =IF(ISNA(MATCH(34,Engine!$C$2:$C$622,0)),"",INDEX('Compliance Database'!$L$2:$L$622,MATCH(34,Engine!$C$2:$C$622,0))) | M47: =IF(ISNA(MATCH(34,Engine!$C$2:$C$622,0)),"",INDEX('Compliance Database'!$M$2:$M$622,MATCH(34,Engine!$C$2:$C$622,0))) | N47: =IF(ISNA(MATCH(34,Engine!$C$2:$C$622,0)),"",INDEX('Compliance Database'!$N$2:$N$622,MATCH(34,Engine!$C$2:$C$622,0))) | O47: =IF(ISNA(MATCH(34,Engine!$C$2:$C$622,0)),"",INDEX('Compliance Database'!$O$2:$O$622,MATCH(34,Engine!$C$2:$C$622,0)))
A48: =IF(ISNA(MATCH(35,Engine!$C$2:$C$622,0)),"",INDEX('Compliance Database'!$A$2:$A$622,MATCH(35,Engine!$C$2:$C$622,0))) | B48: =IF(ISNA(MATCH(35,Engine!$C$2:$C$622,0)),"",INDEX('Compliance Database'!$B$2:$B$622,MATCH(35,Engine!$C$2:$C$622,0))) | C48: =IF(ISNA(MATCH(35,Engine!$C$2:$C$622,0)),"",INDEX('Compliance Database'!$C$2:$C$622,MATCH(35,Engine!$C$2:$C$622,0))) | D48: =IF(ISNA(MATCH(35,Engine!$C$2:$C$622,0)),"",INDEX('Compliance Database'!$D$2:$D$622,MATCH(35,Engine!$C$2:$C$622,0))) | E48: =IF(ISNA(MATCH(35,Engine!$C$2:$C$622,0)),"",INDEX('Compliance Database'!$E$2:$E$622,MATCH(35,Engine!$C$2:$C$622,0))) | F48: =IF(ISNA(MATCH(35,Engine!$C$2:$C$622,0)),"",INDEX('Compliance Database'!$F$2:$F$622,MATCH(35,Engine!$C$2:$C$622,0))) | G48: =IF(ISNA(MATCH(35,Engine!$C$2:$C$622,0)),"",INDEX('Compliance Database'!$G$2:$G$622,MATCH(35,Engine!$C$2:$C$622,0))) | H48: =IF(ISNA(MATCH(35,Engine!$C$2:$C$622,0)),"",INDEX('Compliance Database'!$H$2:$H$622,MATCH(35,Engine!$C$2:$C$622,0))) | I48: =IF(ISNA(MATCH(35,Engine!$C$2:$C$622,0)),"",INDEX('Compliance Database'!$I$2:$I$622,MATCH(35,Engine!$C$2:$C$622,0))) | J48: =IF(ISNA(MATCH(35,Engine!$C$2:$C$622,0)),"",INDEX('Compliance Database'!$J$2:$J$622,MATCH(35,Engine!$C$2:$C$622,0))) | K48: =IF(ISNA(MATCH(35,Engine!$C$2:$C$622,0)),"",INDEX('Compliance Database'!$K$2:$K$622,MATCH(35,Engine!$C$2:$C$622,0))) | L48: =IF(ISNA(MATCH(35,Engine!$C$2:$C$622,0)),"",INDEX('Compliance Database'!$L$2:$L$622,MATCH(35,Engine!$C$2:$C$622,0))) | M48: =IF(ISNA(MATCH(35,Engine!$C$2:$C$622,0)),"",INDEX('Compliance Database'!$M$2:$M$622,MATCH(35,Engine!$C$2:$C$622,0))) | N48: =IF(ISNA(MATCH(35,Engine!$C$2:$C$622,0)),"",INDEX('Compliance Database'!$N$2:$N$622,MATCH(35,Engine!$C$2:$C$622,0))) | O48: =IF(ISNA(MATCH(35,Engine!$C$2:$C$622,0)),"",INDEX('Compliance Database'!$O$2:$O$622,MATCH(35,Engine!$C$2:$C$622,0)))
A49: =IF(ISNA(MATCH(36,Engine!$C$2:$C$622,0)),"",INDEX('Compliance Database'!$A$2:$A$622,MATCH(36,Engine!$C$2:$C$622,0))) | B49: =IF(ISNA(MATCH(36,Engine!$C$2:$C$622,0)),"",INDEX('Compliance Database'!$B$2:$B$622,MATCH(36,Engine!$C$2:$C$622,0))) | C49: =IF(ISNA(MATCH(36,Engine!$C$2:$C$622,0)),"",INDEX('Compliance Database'!$C$2:$C$622,MATCH(36,Engine!$C$2:$C$622,0))) | D49: =IF(ISNA(MATCH(36,Engine!$C$2:$C$622,0)),"",INDEX('Compliance Database'!$D$2:$D$622,MATCH(36,Engine!$C$2:$C$622,0))) | E49: =IF(ISNA(MATCH(36,Engine!$C$2:$C$622,0)),"",INDEX('Compliance Database'!$E$2:$E$622,MATCH(36,Engine!$C$2:$C$622,0))) | F49: =IF(ISNA(MATCH(36,Engine!$C$2:$C$622,0)),"",INDEX('Compliance Database'!$F$2:$F$622,MATCH(36,Engine!$C$2:$C$622,0))) | G49: =IF(ISNA(MATCH(36,Engine!$C$2:$C$622,0)),"",INDEX('Compliance Database'!$G$2:$G$622,MATCH(36,Engine!$C$2:$C$622,0))) | H49: =IF(ISNA(MATCH(36,Engine!$C$2:$C$622,0)),"",INDEX('Compliance Database'!$H$2:$H$622,MATCH(36,Engine!$C$2:$C$622,0))) | I49: =IF(ISNA(MATCH(36,Engine!$C$2:$C$622,0)),"",INDEX('Compliance Database'!$I$2:$I$622,MATCH(36,Engine!$C$2:$C$622,0))) | J49: =IF(ISNA(MATCH(36,Engine!$C$2:$C$622,0)),"",INDEX('Compliance Database'!$J$2:$J$622,MATCH(36,Engine!$C$2:$C$622,0))) | K49: =IF(ISNA(MATCH(36,Engine!$C$2:$C$622,0)),"",INDEX('Compliance Database'!$K$2:$K$622,MATCH(36,Engine!$C$2:$C$622,0))) | L49: =IF(ISNA(MATCH(36,Engine!$C$2:$C$622,0)),"",INDEX('Compliance Database'!$L$2:$L$622,MATCH(36,Engine!$C$2:$C$622,0))) | M49: =IF(ISNA(MATCH(36,Engine!$C$2:$C$622,0)),"",INDEX('Compliance Database'!$M$2:$M$622,MATCH(36,Engine!$C$2:$C$622,0))) | N49: =IF(ISNA(MATCH(36,Engine!$C$2:$C$622,0)),"",INDEX('Compliance Database'!$N$2:$N$622,MATCH(36,Engine!$C$2:$C$622,0))) | O49: =IF(ISNA(MATCH(36,Engine!$C$2:$C$622,0)),"",INDEX('Compliance Database'!$O$2:$O$622,MATCH(36,Engine!$C$2:$C$622,0)))
A50: =IF(ISNA(MATCH(37,Engine!$C$2:$C$622,0)),"",INDEX('Compliance Database'!$A$2:$A$622,MATCH(37,Engine!$C$2:$C$622,0))) | B50: =IF(ISNA(MATCH(37,Engine!$C$2:$C$622,0)),"",INDEX('Compliance Database'!$B$2:$B$622,MATCH(37,Engine!$C$2:$C$622,0))) | C50: =IF(ISNA(MATCH(37,Engine!$C$2:$C$622,0)),"",INDEX('Compliance Database'!$C$2:$C$622,MATCH(37,Engine!$C$2:$C$622,0))) | D50: =IF(ISNA(MATCH(37,Engine!$C$2:$C$622,0)),"",INDEX('Compliance Database'!$D$2:$D$622,MATCH(37,Engine!$C$2:$C$622,0))) | E50: =IF(ISNA(MATCH(37,Engine!$C$2:$C$622,0)),"",INDEX('Compliance Database'!$E$2:$E$622,MATCH(37,Engine!$C$2:$C$622,0))) | F50: =IF(ISNA(MATCH(37,Engine!$C$2:$C$622,0)),"",INDEX('Compliance Database'!$F$2:$F$622,MATCH(37,Engine!$C$2:$C$622,0))) | G50: =IF(ISNA(MATCH(37,Engine!$C$2:$C$622,0)),"",INDEX('Compliance Database'!$G$2:$G$622,MATCH(37,Engine!$C$2:$C$622,0))) | H50: =IF(ISNA(MATCH(37,Engine!$C$2:$C$622,0)),"",INDEX('Compliance Database'!$H$2:$H$622,MATCH(37,Engine!$C$2:$C$622,0))) | I50: =IF(ISNA(MATCH(37,Engine!$C$2:$C$622,0)),"",INDEX('Compliance Database'!$I$2:$I$622,MATCH(37,Engine!$C$2:$C$622,0))) | J50: =IF(ISNA(MATCH(37,Engine!$C$2:$C$622,0)),"",INDEX('Compliance Database'!$J$2:$J$622,MATCH(37,Engine!$C$2:$C$622,0))) | K50: =IF(ISNA(MATCH(37,Engine!$C$2:$C$622,0)),"",INDEX('Compliance Database'!$K$2:$K$622,MATCH(37,Engine!$C$2:$C$622,0))) | L50: =IF(ISNA(MATCH(37,Engine!$C$2:$C$622,0)),"",INDEX('Compliance Database'!$L$2:$L$622,MATCH(37,Engine!$C$2:$C$622,0))) | M50: =IF(ISNA(MATCH(37,Engine!$C$2:$C$622,0)),"",INDEX('Compliance Database'!$M$2:$M$622,MATCH(37,Engine!$C$2:$C$622,0))) | N50: =IF(ISNA(MATCH(37,Engine!$C$2:$C$622,0)),"",INDEX('Compliance Database'!$N$2:$N$622,MATCH(37,Engine!$C$2:$C$622,0))) | O50: =IF(ISNA(MATCH(37,Engine!$C$2:$C$622,0)),"",INDEX('Compliance Database'!$O$2:$O$622,MATCH(37,Engine!$C$2:$C$622,0)))
A51: =IF(ISNA(MATCH(38,Engine!$C$2:$C$622,0)),"",INDEX('Compliance Database'!$A$2:$A$622,MATCH(38,Engine!$C$2:$C$622,0))) | B51: =IF(ISNA(MATCH(38,Engine!$C$2:$C$622,0)),"",INDEX('Compliance Database'!$B$2:$B$622,MATCH(38,Engine!$C$2:$C$622,0))) | C51: =IF(ISNA(MATCH(38,Engine!$C$2:$C$622,0)),"",INDEX('Compliance Database'!$C$2:$C$622,MATCH(38,Engine!$C$2:$C$622,0))) | D51: =IF(ISNA(MATCH(38,Engine!$C$2:$C$622,0)),"",INDEX('Compliance Database'!$D$2:$D$622,MATCH(38,Engine!$C$2:$C$622,0))) | E51: =IF(ISNA(MATCH(38,Engine!$C$2:$C$622,0)),"",INDEX('Compliance Database'!$E$2:$E$622,MATCH(38,Engine!$C$2:$C$622,0))) | F51: =IF(ISNA(MATCH(38,Engine!$C$2:$C$622,0)),"",INDEX('Compliance Database'!$F$2:$F$622,MATCH(38,Engine!$C$2:$C$622,0))) | G51: =IF(ISNA(MATCH(38,Engine!$C$2:$C$622,0)),"",INDEX('Compliance Database'!$G$2:$G$622,MATCH(38,Engine!$C$2:$C$622,0))) | H51: =IF(ISNA(MATCH(38,Engine!$C$2:$C$622,0)),"",INDEX('Compliance Database'!$H$2:$H$622,MATCH(38,Engine!$C$2:$C$622,0))) | I51: =IF(ISNA(MATCH(38,Engine!$C$2:$C$622,0)),"",INDEX('Compliance Database'!$I$2:$I$622,MATCH(38,Engine!$C$2:$C$622,0))) | J51: =IF(ISNA(MATCH(38,Engine!$C$2:$C$622,0)),"",INDEX('Compliance Database'!$J$2:$J$622,MATCH(38,Engine!$C$2:$C$622,0))) | K51: =IF(ISNA(MATCH(38,Engine!$C$2:$C$622,0)),"",INDEX('Compliance Database'!$K$2:$K$622,MATCH(38,Engine!$C$2:$C$622,0))) | L51: =IF(ISNA(MATCH(38,Engine!$C$2:$C$622,0)),"",INDEX('Compliance Database'!$L$2:$L$622,MATCH(38,Engine!$C$2:$C$622,0))) | M51: =IF(ISNA(MATCH(38,Engine!$C$2:$C$622,0)),"",INDEX('Compliance Database'!$M$2:$M$622,MATCH(38,Engine!$C$2:$C$622,0))) | N51: =IF(ISNA(MATCH(38,Engine!$C$2:$C$622,0)),"",INDEX('Compliance Database'!$N$2:$N$622,MATCH(38,Engine!$C$2:$C$622,0))) | O51: =IF(ISNA(MATCH(38,Engine!$C$2:$C$622,0)),"",INDEX('Compliance Database'!$O$2:$O$622,MATCH(38,Engine!$C$2:$C$622,0)))
A52: =IF(ISNA(MATCH(39,Engine!$C$2:$C$622,0)),"",INDEX('Compliance Database'!$A$2:$A$622,MATCH(39,Engine!$C$2:$C$622,0))) | B52: =IF(ISNA(MATCH(39,Engine!$C$2:$C$622,0)),"",INDEX('Compliance Database'!$B$2:$B$622,MATCH(39,Engine!$C$2:$C$622,0))) | C52: =IF(ISNA(MATCH(39,Engine!$C$2:$C$622,0)),"",INDEX('Compliance Database'!$C$2:$C$622,MATCH(39,Engine!$C$2:$C$622,0))) | D52: =IF(ISNA(MATCH(39,Engine!$C$2:$C$622,0)),"",INDEX('Compliance Database'!$D$2:$D$622,MATCH(39,Engine!$C$2:$C$622,0))) | E52: =IF(ISNA(MATCH(39,Engine!$C$2:$C$622,0)),"",INDEX('Compliance Database'!$E$2:$E$622,MATCH(39,Engine!$C$2:$C$622,0))) | F52: =IF(ISNA(MATCH(39,Engine!$C$2:$C$622,0)),"",INDEX('Compliance Database'!$F$2:$F$622,MATCH(39,Engine!$C$2:$C$622,0))) | G52: =IF(ISNA(MATCH(39,Engine!$C$2:$C$622,0)),"",INDEX('Compliance Database'!$G$2:$G$622,MATCH(39,Engine!$C$2:$C$622,0))) | H52: =IF(ISNA(MATCH(39,Engine!$C$2:$C$622,0)),"",INDEX('Compliance Database'!$H$2:$H$622,MATCH(39,Engine!$C$2:$C$622,0))) | I52: =IF(ISNA(MATCH(39,Engine!$C$2:$C$622,0)),"",INDEX('Compliance Database'!$I$2:$I$622,MATCH(39,Engine!$C$2:$C$622,0))) | J52: =IF(ISNA(MATCH(39,Engine!$C$2:$C$622,0)),"",INDEX('Compliance Database'!$J$2:$J$622,MATCH(39,Engine!$C$2:$C$622,0))) | K52: =IF(ISNA(MATCH(39,Engine!$C$2:$C$622,0)),"",INDEX('Compliance Database'!$K$2:$K$622,MATCH(39,Engine!$C$2:$C$622,0))) | L52: =IF(ISNA(MATCH(39,Engine!$C$2:$C$622,0)),"",INDEX('Compliance Database'!$L$2:$L$622,MATCH(39,Engine!$C$2:$C$622,0))) | M52: =IF(ISNA(MATCH(39,Engine!$C$2:$C$622,0)),"",INDEX('Compliance Database'!$M$2:$M$622,MATCH(39,Engine!$C$2:$C$622,0))) | N52: =IF(ISNA(MATCH(39,Engine!$C$2:$C$622,0)),"",INDEX('Compliance Database'!$N$2:$N$622,MATCH(39,Engine!$C$2:$C$622,0))) | O52: =IF(ISNA(MATCH(39,Engine!$C$2:$C$622,0)),"",INDEX('Compliance Database'!$O$2:$O$622,MATCH(39,Engine!$C$2:$C$622,0)))
A53: =IF(ISNA(MATCH(40,Engine!$C$2:$C$622,0)),"",INDEX('Compliance Database'!$A$2:$A$622,MATCH(40,Engine!$C$2:$C$622,0))) | B53: =IF(ISNA(MATCH(40,Engine!$C$2:$C$622,0)),"",INDEX('Compliance Database'!$B$2:$B$622,MATCH(40,Engine!$C$2:$C$622,0))) | C53: =IF(ISNA(MATCH(40,Engine!$C$2:$C$622,0)),"",INDEX('Compliance Database'!$C$2:$C$622,MATCH(40,Engine!$C$2:$C$622,0))) | D53: =IF(ISNA(MATCH(40,Engine!$C$2:$C$622,0)),"",INDEX('Compliance Database'!$D$2:$D$622,MATCH(40,Engine!$C$2:$C$622,0))) | E53: =IF(ISNA(MATCH(40,Engine!$C$2:$C$622,0)),"",INDEX('Compliance Database'!$E$2:$E$622,MATCH(40,Engine!$C$2:$C$622,0))) | F53: =IF(ISNA(MATCH(40,Engine!$C$2:$C$622,0)),"",INDEX('Compliance Database'!$F$2:$F$622,MATCH(40,Engine!$C$2:$C$622,0))) | G53: =IF(ISNA(MATCH(40,Engine!$C$2:$C$622,0)),"",INDEX('Compliance Database'!$G$2:$G$622,MATCH(40,Engine!$C$2:$C$622,0))) | H53: =IF(ISNA(MATCH(40,Engine!$C$2:$C$622,0)),"",INDEX('Compliance Database'!$H$2:$H$622,MATCH(40,Engine!$C$2:$C$622,0))) | I53: =IF(ISNA(MATCH(40,Engine!$C$2:$C$622,0)),"",INDEX('Compliance Database'!$I$2:$I$622,MATCH(40,Engine!$C$2:$C$622,0))) | J53: =IF(ISNA(MATCH(40,Engine!$C$2:$C$622,0)),"",INDEX('Compliance Database'!$J$2:$J$622,MATCH(40,Engine!$C$2:$C$622,0))) | K53: =IF(ISNA(MATCH(40,Engine!$C$2:$C$622,0)),"",INDEX('Compliance Database'!$K$2:$K$622,MATCH(40,Engine!$C$2:$C$622,0))) | L53: =IF(ISNA(MATCH(40,Engine!$C$2:$C$622,0)),"",INDEX('Compliance Database'!$L$2:$L$622,MATCH(40,Engine!$C$2:$C$622,0))) | M53: =IF(ISNA(MATCH(40,Engine!$C$2:$C$622,0)),"",INDEX('Compliance Database'!$M$2:$M$622,MATCH(40,Engine!$C$2:$C$622,0))) | N53: =IF(ISNA(MATCH(40,Engine!$C$2:$C$622,0)),"",INDEX('Compliance Database'!$N$2:$N$622,MATCH(40,Engine!$C$2:$C$622,0))) | O53: =IF(ISNA(MATCH(40,Engine!$C$2:$C$622,0)),"",INDEX('Compliance Database'!$O$2:$O$622,MATCH(40,Engine!$C$2:$C$622,0)))
A54: =IF(ISNA(MATCH(41,Engine!$C$2:$C$622,0)),"",INDEX('Compliance Database'!$A$2:$A$622,MATCH(41,Engine!$C$2:$C$622,0))) | B54: =IF(ISNA(MATCH(41,Engine!$C$2:$C$622,0)),"",INDEX('Compliance Database'!$B$2:$B$622,MATCH(41,Engine!$C$2:$C$622,0))) | C54: =IF(ISNA(MATCH(41,Engine!$C$2:$C$622,0)),"",INDEX('Compliance Database'!$C$2:$C$622,MATCH(41,Engine!$C$2:$C$622,0))) | D54: =IF(ISNA(MATCH(41,Engine!$C$2:$C$622,0)),"",INDEX('Compliance Database'!$D$2:$D$622,MATCH(41,Engine!$C$2:$C$622,0))) | E54: =IF(ISNA(MATCH(41,Engine!$C$2:$C$622,0)),"",INDEX('Compliance Database'!$E$2:$E$622,MATCH(41,Engine!$C$2:$C$622,0))) | F54: =IF(ISNA(MATCH(41,Engine!$C$2:$C$622,0)),"",INDEX('Compliance Database'!$F$2:$F$622,MATCH(41,Engine!$C$2:$C$622,0))) | G54: =IF(ISNA(MATCH(41,Engine!$C$2:$C$622,0)),"",INDEX('Compliance Database'!$G$2:$G$622,MATCH(41,Engine!$C$2:$C$622,0))) | H54: =IF(ISNA(MATCH(41,Engine!$C$2:$C$622,0)),"",INDEX('Compliance Database'!$H$2:$H$622,MATCH(41,Engine!$C$2:$C$622,0))) | I54: =IF(ISNA(MATCH(41,Engine!$C$2:$C$622,0)),"",INDEX('Compliance Database'!$I$2:$I$622,MATCH(41,Engine!$C$2:$C$622,0))) | J54: =IF(ISNA(MATCH(41,Engine!$C$2:$C$622,0)),"",INDEX('Compliance Database'!$J$2:$J$622,MATCH(41,Engine!$C$2:$C$622,0))) | K54: =IF(ISNA(MATCH(41,Engine!$C$2:$C$622,0)),"",INDEX('Compliance Database'!$K$2:$K$622,MATCH(41,Engine!$C$2:$C$622,0))) | L54: =IF(ISNA(MATCH(41,Engine!$C$2:$C$622,0)),"",INDEX('Compliance Database'!$L$2:$L$622,MATCH(41,Engine!$C$2:$C$622,0))) | M54: =IF(ISNA(MATCH(41,Engine!$C$2:$C$622,0)),"",INDEX('Compliance Database'!$M$2:$M$622,MATCH(41,Engine!$C$2:$C$622,0))) | N54: =IF(ISNA(MATCH(41,Engine!$C$2:$C$622,0)),"",INDEX('Compliance Database'!$N$2:$N$622,MATCH(41,Engine!$C$2:$C$622,0))) | O54: =IF(ISNA(MATCH(41,Engine!$C$2:$C$622,0)),"",INDEX('Compliance Database'!$O$2:$O$622,MATCH(41,Engine!$C$2:$C$622,0)))
A55: =IF(ISNA(MATCH(42,Engine!$C$2:$C$622,0)),"",INDEX('Compliance Database'!$A$2:$A$622,MATCH(42,Engine!$C$2:$C$622,0))) | B55: =IF(ISNA(MATCH(42,Engine!$C$2:$C$622,0)),"",INDEX('Compliance Database'!$B$2:$B$622,MATCH(42,Engine!$C$2:$C$622,0))) | C55: =IF(ISNA(MATCH(42,Engine!$C$2:$C$622,0)),"",INDEX('Compliance Database'!$C$2:$C$622,MATCH(42,Engine!$C$2:$C$622,0))) | D55: =IF(ISNA(MATCH(42,Engine!$C$2:$C$622,0)),"",INDEX('Compliance Database'!$D$2:$D$622,MATCH(42,Engine!$C$2:$C$622,0))) | E55: =IF(ISNA(MATCH(42,Engine!$C$2:$C$622,0)),"",INDEX('Compliance Database'!$E$2:$E$622,MATCH(42,Engine!$C$2:$C$622,0))) | F55: =IF(ISNA(MATCH(42,Engine!$C$2:$C$622,0)),"",INDEX('Compliance Database'!$F$2:$F$622,MATCH(42,Engine!$C$2:$C$622,0))) | G55: =IF(ISNA(MATCH(42,Engine!$C$2:$C$622,0)),"",INDEX('Compliance Database'!$G$2:$G$622,MATCH(42,Engine!$C$2:$C$622,0))) | H55: =IF(ISNA(MATCH(42,Engine!$C$2:$C$622,0)),"",INDEX('Compliance Database'!$H$2:$H$622,MATCH(42,Engine!$C$2:$C$622,0))) | I55: =IF(ISNA(MATCH(42,Engine!$C$2:$C$622,0)),"",INDEX('Compliance Database'!$I$2:$I$622,MATCH(42,Engine!$C$2:$C$622,0))) | J55: =IF(ISNA(MATCH(42,Engine!$C$2:$C$622,0)),"",INDEX('Compliance Database'!$J$2:$J$622,MATCH(42,Engine!$C$2:$C$622,0))) | K55: =IF(ISNA(MATCH(42,Engine!$C$2:$C$622,0)),"",INDEX('Compliance Database'!$K$2:$K$622,MATCH(42,Engine!$C$2:$C$622,0))) | L55: =IF(ISNA(MATCH(42,Engine!$C$2:$C$622,0)),"",INDEX('Compliance Database'!$L$2:$L$622,MATCH(42,Engine!$C$2:$C$622,0))) | M55: =IF(ISNA(MATCH(42,Engine!$C$2:$C$622,0)),"",INDEX('Compliance Database'!$M$2:$M$622,MATCH(42,Engine!$C$2:$C$622,0))) | N55: =IF(ISNA(MATCH(42,Engine!$C$2:$C$622,0)),"",INDEX('Compliance Database'!$N$2:$N$622,MATCH(42,Engine!$C$2:$C$622,0))) | O55: =IF(ISNA(MATCH(42,Engine!$C$2:$C$622,0)),"",INDEX('Compliance Database'!$O$2:$O$622,MATCH(42,Engine!$C$2:$C$622,0)))
A56: =IF(ISNA(MATCH(43,Engine!$C$2:$C$622,0)),"",INDEX('Compliance Database'!$A$2:$A$622,MATCH(43,Engine!$C$2:$C$622,0))) | B56: =IF(ISNA(MATCH(43,Engine!$C$2:$C$622,0)),"",INDEX('Compliance Database'!$B$2:$B$622,MATCH(43,Engine!$C$2:$C$622,0))) | C56: =IF(ISNA(MATCH(43,Engine!$C$2:$C$622,0)),"",INDEX('Compliance Database'!$C$2:$C$622,MATCH(43,Engine!$C$2:$C$622,0))) | D56: =IF(ISNA(MATCH(43,Engine!$C$2:$C$622,0)),"",INDEX('Compliance Database'!$D$2:$D$622,MATCH(43,Engine!$C$2:$C$622,0))) | E56: =IF(ISNA(MATCH(43,Engine!$C$2:$C$622,0)),"",INDEX('Compliance Database'!$E$2:$E$622,MATCH(43,Engine!$C$2:$C$622,0))) | F56: =IF(ISNA(MATCH(43,Engine!$C$2:$C$622,0)),"",INDEX('Compliance Database'!$F$2:$F$622,MATCH(43,Engine!$C$2:$C$622,0))) | G56: =IF(ISNA(MATCH(43,Engine!$C$2:$C$622,0)),"",INDEX('Compliance Database'!$G$2:$G$622,MATCH(43,Engine!$C$2:$C$622,0))) | H56: =IF(ISNA(MATCH(43,Engine!$C$2:$C$622,0)),"",INDEX('Compliance Database'!$H$2:$H$622,MATCH(43,Engine!$C$2:$C$622,0))) | I56: =IF(ISNA(MATCH(43,Engine!$C$2:$C$622,0)),"",INDEX('Compliance Database'!$I$2:$I$622,MATCH(43,Engine!$C$2:$C$622,0))) | J56: =IF(ISNA(MATCH(43,Engine!$C$2:$C$622,0)),"",INDEX('Compliance Database'!$J$2:$J$622,MATCH(43,Engine!$C$2:$C$622,0))) | K56: =IF(ISNA(MATCH(43,Engine!$C$2:$C$622,0)),"",INDEX('Compliance Database'!$K$2:$K$622,MATCH(43,Engine!$C$2:$C$622,0))) | L56: =IF(ISNA(MATCH(43,Engine!$C$2:$C$622,0)),"",INDEX('Compliance Database'!$L$2:$L$622,MATCH(43,Engine!$C$2:$C$622,0))) | M56: =IF(ISNA(MATCH(43,Engine!$C$2:$C$622,0)),"",INDEX('Compliance Database'!$M$2:$M$622,MATCH(43,Engine!$C$2:$C$622,0))) | N56: =IF(ISNA(MATCH(43,Engine!$C$2:$C$622,0)),"",INDEX('Compliance Database'!$N$2:$N$622,MATCH(43,Engine!$C$2:$C$622,0))) | O56: =IF(ISNA(MATCH(43,Engine!$C$2:$C$622,0)),"",INDEX('Compliance Database'!$O$2:$O$622,MATCH(43,Engine!$C$2:$C$622,0)))
A57: =IF(ISNA(MATCH(44,Engine!$C$2:$C$622,0)),"",INDEX('Compliance Database'!$A$2:$A$622,MATCH(44,Engine!$C$2:$C$622,0))) | B57: =IF(ISNA(MATCH(44,Engine!$C$2:$C$622,0)),"",INDEX('Compliance Database'!$B$2:$B$622,MATCH(44,Engine!$C$2:$C$622,0))) | C57: =IF(ISNA(MATCH(44,Engine!$C$2:$C$622,0)),"",INDEX('Compliance Database'!$C$2:$C$622,MATCH(44,Engine!$C$2:$C$622,0))) | D57: =IF(ISNA(MATCH(44,Engine!$C$2:$C$622,0)),"",INDEX('Compliance Database'!$D$2:$D$622,MATCH(44,Engine!$C$2:$C$622,0))) | E57: =IF(ISNA(MATCH(44,Engine!$C$2:$C$622,0)),"",INDEX('Compliance Database'!$E$2:$E$622,MATCH(44,Engine!$C$2:$C$622,0))) | F57: =IF(ISNA(MATCH(44,Engine!$C$2:$C$622,0)),"",INDEX('Compliance Database'!$F$2:$F$622,MATCH(44,Engine!$C$2:$C$622,0))) | G57: =IF(ISNA(MATCH(44,Engine!$C$2:$C$622,0)),"",INDEX('Compliance Database'!$G$2:$G$622,MATCH(44,Engine!$C$2:$C$622,0))) | H57: =IF(ISNA(MATCH(44,Engine!$C$2:$C$622,0)),"",INDEX('Compliance Database'!$H$2:$H$622,MATCH(44,Engine!$C$2:$C$622,0))) | I57: =IF(ISNA(MATCH(44,Engine!$C$2:$C$622,0)),"",INDEX('Compliance Database'!$I$2:$I$622,MATCH(44,Engine!$C$2:$C$622,0))) | J57: =IF(ISNA(MATCH(44,Engine!$C$2:$C$622,0)),"",INDEX('Compliance Database'!$J$2:$J$622,MATCH(44,Engine!$C$2:$C$622,0))) | K57: =IF(ISNA(MATCH(44,Engine!$C$2:$C$622,0)),"",INDEX('Compliance Database'!$K$2:$K$622,MATCH(44,Engine!$C$2:$C$622,0))) | L57: =IF(ISNA(MATCH(44,Engine!$C$2:$C$622,0)),"",INDEX('Compliance Database'!$L$2:$L$622,MATCH(44,Engine!$C$2:$C$622,0))) | M57: =IF(ISNA(MATCH(44,Engine!$C$2:$C$622,0)),"",INDEX('Compliance Database'!$M$2:$M$622,MATCH(44,Engine!$C$2:$C$622,0))) | N57: =IF(ISNA(MATCH(44,Engine!$C$2:$C$622,0)),"",INDEX('Compliance Database'!$N$2:$N$622,MATCH(44,Engine!$C$2:$C$622,0))) | O57: =IF(ISNA(MATCH(44,Engine!$C$2:$C$622,0)),"",INDEX('Compliance Database'!$O$2:$O$622,MATCH(44,Engine!$C$2:$C$622,0)))
A58: =IF(ISNA(MATCH(45,Engine!$C$2:$C$622,0)),"",INDEX('Compliance Database'!$A$2:$A$622,MATCH(45,Engine!$C$2:$C$622,0))) | B58: =IF(ISNA(MATCH(45,Engine!$C$2:$C$622,0)),"",INDEX('Compliance Database'!$B$2:$B$622,MATCH(45,Engine!$C$2:$C$622,0))) | C58: =IF(ISNA(MATCH(45,Engine!$C$2:$C$622,0)),"",INDEX('Compliance Database'!$C$2:$C$622,MATCH(45,Engine!$C$2:$C$622,0))) | D58: =IF(ISNA(MATCH(45,Engine!$C$2:$C$622,0)),"",INDEX('Compliance Database'!$D$2:$D$622,MATCH(45,Engine!$C$2:$C$622,0))) | E58: =IF(ISNA(MATCH(45,Engine!$C$2:$C$622,0)),"",INDEX('Compliance Database'!$E$2:$E$622,MATCH(45,Engine!$C$2:$C$622,0))) | F58: =IF(ISNA(MATCH(45,Engine!$C$2:$C$622,0)),"",INDEX('Compliance Database'!$F$2:$F$622,MATCH(45,Engine!$C$2:$C$622,0))) | G58: =IF(ISNA(MATCH(45,Engine!$C$2:$C$622,0)),"",INDEX('Compliance Database'!$G$2:$G$622,MATCH(45,Engine!$C$2:$C$622,0))) | H58: =IF(ISNA(MATCH(45,Engine!$C$2:$C$622,0)),"",INDEX('Compliance Database'!$H$2:$H$622,MATCH(45,Engine!$C$2:$C$622,0))) | I58: =IF(ISNA(MATCH(45,Engine!$C$2:$C$622,0)),"",INDEX('Compliance Database'!$I$2:$I$622,MATCH(45,Engine!$C$2:$C$622,0))) | J58: =IF(ISNA(MATCH(45,Engine!$C$2:$C$622,0)),"",INDEX('Compliance Database'!$J$2:$J$622,MATCH(45,Engine!$C$2:$C$622,0))) | K58: =IF(ISNA(MATCH(45,Engine!$C$2:$C$622,0)),"",INDEX('Compliance Database'!$K$2:$K$622,MATCH(45,Engine!$C$2:$C$622,0))) | L58: =IF(ISNA(MATCH(45,Engine!$C$2:$C$622,0)),"",INDEX('Compliance Database'!$L$2:$L$622,MATCH(45,Engine!$C$2:$C$622,0))) | M58: =IF(ISNA(MATCH(45,Engine!$C$2:$C$622,0)),"",INDEX('Compliance Database'!$M$2:$M$622,MATCH(45,Engine!$C$2:$C$622,0))) | N58: =IF(ISNA(MATCH(45,Engine!$C$2:$C$622,0)),"",INDEX('Compliance Database'!$N$2:$N$622,MATCH(45,Engine!$C$2:$C$622,0))) | O58: =IF(ISNA(MATCH(45,Engine!$C$2:$C$622,0)),"",INDEX('Compliance Database'!$O$2:$O$622,MATCH(45,Engine!$C$2:$C$622,0)))
A59: =IF(ISNA(MATCH(46,Engine!$C$2:$C$622,0)),"",INDEX('Compliance Database'!$A$2:$A$622,MATCH(46,Engine!$C$2:$C$622,0))) | B59: =IF(ISNA(MATCH(46,Engine!$C$2:$C$622,0)),"",INDEX('Compliance Database'!$B$2:$B$622,MATCH(46,Engine!$C$2:$C$622,0))) | C59: =IF(ISNA(MATCH(46,Engine!$C$2:$C$622,0)),"",INDEX('Compliance Database'!$C$2:$C$622,MATCH(46,Engine!$C$2:$C$622,0))) | D59: =IF(ISNA(MATCH(46,Engine!$C$2:$C$622,0)),"",INDEX('Compliance Database'!$D$2:$D$622,MATCH(46,Engine!$C$2:$C$622,0))) | E59: =IF(ISNA(MATCH(46,Engine!$C$2:$C$622,0)),"",INDEX('Compliance Database'!$E$2:$E$622,MATCH(46,Engine!$C$2:$C$622,0))) | F59: =IF(ISNA(MATCH(46,Engine!$C$2:$C$622,0)),"",INDEX('Compliance Database'!$F$2:$F$622,MATCH(46,Engine!$C$2:$C$622,0))) | G59: =IF(ISNA(MATCH(46,Engine!$C$2:$C$622,0)),"",INDEX('Compliance Database'!$G$2:$G$622,MATCH(46,Engine!$C$2:$C$622,0))) | H59: =IF(ISNA(MATCH(46,Engine!$C$2:$C$622,0)),"",INDEX('Compliance Database'!$H$2:$H$622,MATCH(46,Engine!$C$2:$C$622,0))) | I59: =IF(ISNA(MATCH(46,Engine!$C$2:$C$622,0)),"",INDEX('Compliance Database'!$I$2:$I$622,MATCH(46,Engine!$C$2:$C$622,0))) | J59: =IF(ISNA(MATCH(46,Engine!$C$2:$C$622,0)),"",INDEX('Compliance Database'!$J$2:$J$622,MATCH(46,Engine!$C$2:$C$622,0))) | K59: =IF(ISNA(MATCH(46,Engine!$C$2:$C$622,0)),"",INDEX('Compliance Database'!$K$2:$K$622,MATCH(46,Engine!$C$2:$C$622,0))) | L59: =IF(ISNA(MATCH(46,Engine!$C$2:$C$622,0)),"",INDEX('Compliance Database'!$L$2:$L$622,MATCH(46,Engine!$C$2:$C$622,0))) | M59: =IF(ISNA(MATCH(46,Engine!$C$2:$C$622,0)),"",INDEX('Compliance Database'!$M$2:$M$622,MATCH(46,Engine!$C$2:$C$622,0))) | N59: =IF(ISNA(MATCH(46,Engine!$C$2:$C$622,0)),"",INDEX('Compliance Database'!$N$2:$N$622,MATCH(46,Engine!$C$2:$C$622,0))) | O59: =IF(ISNA(MATCH(46,Engine!$C$2:$C$622,0)),"",INDEX('Compliance Database'!$O$2:$O$622,MATCH(46,Engine!$C$2:$C$622,0)))
A60: =IF(ISNA(MATCH(47,Engine!$C$2:$C$622,0)),"",INDEX('Compliance Database'!$A$2:$A$622,MATCH(47,Engine!$C$2:$C$622,0))) | B60: =IF(ISNA(MATCH(47,Engine!$C$2:$C$622,0)),"",INDEX('Compliance Database'!$B$2:$B$622,MATCH(47,Engine!$C$2:$C$622,0))) | C60: =IF(ISNA(MATCH(47,Engine!$C$2:$C$622,0)),"",INDEX('Compliance Database'!$C$2:$C$622,MATCH(47,Engine!$C$2:$C$622,0))) | D60: =IF(ISNA(MATCH(47,Engine!$C$2:$C$622,0)),"",INDEX('Compliance Database'!$D$2:$D$622,MATCH(47,Engine!$C$2:$C$622,0))) | E60: =IF(ISNA(MATCH(47,Engine!$C$2:$C$622,0)),"",INDEX('Compliance Database'!$E$2:$E$622,MATCH(47,Engine!$C$2:$C$622,0))) | F60: =IF(ISNA(MATCH(47,Engine!$C$2:$C$622,0)),"",INDEX('Compliance Database'!$F$2:$F$622,MATCH(47,Engine!$C$2:$C$622,0))) | G60: =IF(ISNA(MATCH(47,Engine!$C$2:$C$622,0)),"",INDEX('Compliance Database'!$G$2:$G$622,MATCH(47,Engine!$C$2:$C$622,0))) | H60: =IF(ISNA(MATCH(47,Engine!$C$2:$C$622,0)),"",INDEX('Compliance Database'!$H$2:$H$622,MATCH(47,Engine!$C$2:$C$622,0))) | I60: =IF(ISNA(MATCH(47,Engine!$C$2:$C$622,0)),"",INDEX('Compliance Database'!$I$2:$I$622,MATCH(47,Engine!$C$2:$C$622,0))) | J60: =IF(ISNA(MATCH(47,Engine!$C$2:$C$622,0)),"",INDEX('Compliance Database'!$J$2:$J$622,MATCH(47,Engine!$C$2:$C$622,0))) | K60: =IF(ISNA(MATCH(47,Engine!$C$2:$C$622,0)),"",INDEX('Compliance Database'!$K$2:$K$622,MATCH(47,Engine!$C$2:$C$622,0))) | L60: =IF(ISNA(MATCH(47,Engine!$C$2:$C$622,0)),"",INDEX('Compliance Database'!$L$2:$L$622,MATCH(47,Engine!$C$2:$C$622,0))) | M60: =IF(ISNA(MATCH(47,Engine!$C$2:$C$622,0)),"",INDEX('Compliance Database'!$M$2:$M$622,MATCH(47,Engine!$C$2:$C$622,0))) | N60: =IF(ISNA(MATCH(47,Engine!$C$2:$C$622,0)),"",INDEX('Compliance Database'!$N$2:$N$622,MATCH(47,Engine!$C$2:$C$622,0))) | O60: =IF(ISNA(MATCH(47,Engine!$C$2:$C$622,0)),"",INDEX('Compliance Database'!$O$2:$O$622,MATCH(47,Engine!$C$2:$C$622,0)))
A61: =IF(ISNA(MATCH(48,Engine!$C$2:$C$622,0)),"",INDEX('Compliance Database'!$A$2:$A$622,MATCH(48,Engine!$C$2:$C$622,0))) | B61: =IF(ISNA(MATCH(48,Engine!$C$2:$C$622,0)),"",INDEX('Compliance Database'!$B$2:$B$622,MATCH(48,Engine!$C$2:$C$622,0))) | C61: =IF(ISNA(MATCH(48,Engine!$C$2:$C$622,0)),"",INDEX('Compliance Database'!$C$2:$C$622,MATCH(48,Engine!$C$2:$C$622,0))) | D61: =IF(ISNA(MATCH(48,Engine!$C$2:$C$622,0)),"",INDEX('Compliance Database'!$D$2:$D$622,MATCH(48,Engine!$C$2:$C$622,0))) | E61: =IF(ISNA(MATCH(48,Engine!$C$2:$C$622,0)),"",INDEX('Compliance Database'!$E$2:$E$622,MATCH(48,Engine!$C$2:$C$622,0))) | F61: =IF(ISNA(MATCH(48,Engine!$C$2:$C$622,0)),"",INDEX('Compliance Database'!$F$2:$F$622,MATCH(48,Engine!$C$2:$C$622,0))) | G61: =IF(ISNA(MATCH(48,Engine!$C$2:$C$622,0)),"",INDEX('Compliance Database'!$G$2:$G$622,MATCH(48,Engine!$C$2:$C$622,0))) | H61: =IF(ISNA(MATCH(48,Engine!$C$2:$C$622,0)),"",INDEX('Compliance Database'!$H$2:$H$622,MATCH(48,Engine!$C$2:$C$622,0))) | I61: =IF(ISNA(MATCH(48,Engine!$C$2:$C$622,0)),"",INDEX('Compliance Database'!$I$2:$I$622,MATCH(48,Engine!$C$2:$C$622,0))) | J61: =IF(ISNA(MATCH(48,Engine!$C$2:$C$622,0)),"",INDEX('Compliance Database'!$J$2:$J$622,MATCH(48,Engine!$C$2:$C$622,0))) | K61: =IF(ISNA(MATCH(48,Engine!$C$2:$C$622,0)),"",INDEX('Compliance Database'!$K$2:$K$622,MATCH(48,Engine!$C$2:$C$622,0))) | L61: =IF(ISNA(MATCH(48,Engine!$C$2:$C$622,0)),"",INDEX('Compliance Database'!$L$2:$L$622,MATCH(48,Engine!$C$2:$C$622,0))) | M61: =IF(ISNA(MATCH(48,Engine!$C$2:$C$622,0)),"",INDEX('Compliance Database'!$M$2:$M$622,MATCH(48,Engine!$C$2:$C$622,0))) | N61: =IF(ISNA(MATCH(48,Engine!$C$2:$C$622,0)),"",INDEX('Compliance Database'!$N$2:$N$622,MATCH(48,Engine!$C$2:$C$622,0))) | O61: =IF(ISNA(MATCH(48,Engine!$C$2:$C$622,0)),"",INDEX('Compliance Database'!$O$2:$O$622,MATCH(48,Engine!$C$2:$C$622,0)))
A62: =IF(ISNA(MATCH(49,Engine!$C$2:$C$622,0)),"",INDEX('Compliance Database'!$A$2:$A$622,MATCH(49,Engine!$C$2:$C$622,0))) | B62: =IF(ISNA(MATCH(49,Engine!$C$2:$C$622,0)),"",INDEX('Compliance Database'!$B$2:$B$622,MATCH(49,Engine!$C$2:$C$622,0))) | C62: =IF(ISNA(MATCH(49,Engine!$C$2:$C$622,0)),"",INDEX('Compliance Database'!$C$2:$C$622,MATCH(49,Engine!$C$2:$C$622,0))) | D62: =IF(ISNA(MATCH(49,Engine!$C$2:$C$622,0)),"",INDEX('Compliance Database'!$D$2:$D$622,MATCH(49,Engine!$C$2:$C$622,0))) | E62: =IF(ISNA(MATCH(49,Engine!$C$2:$C$622,0)),"",INDEX('Compliance Database'!$E$2:$E$622,MATCH(49,Engine!$C$2:$C$622,0))) | F62: =IF(ISNA(MATCH(49,Engine!$C$2:$C$622,0)),"",INDEX('Compliance Database'!$F$2:$F$622,MATCH(49,Engine!$C$2:$C$622,0))) | G62: =IF(ISNA(MATCH(49,Engine!$C$2:$C$622,0)),"",INDEX('Compliance Database'!$G$2:$G$622,MATCH(49,Engine!$C$2:$C$622,0))) | H62: =IF(ISNA(MATCH(49,Engine!$C$2:$C$622,0)),"",INDEX('Compliance Database'!$H$2:$H$622,MATCH(49,Engine!$C$2:$C$622,0))) | I62: =IF(ISNA(MATCH(49,Engine!$C$2:$C$622,0)),"",INDEX('Compliance Database'!$I$2:$I$622,MATCH(49,Engine!$C$2:$C$622,0))) | J62: =IF(ISNA(MATCH(49,Engine!$C$2:$C$622,0)),"",INDEX('Compliance Database'!$J$2:$J$622,MATCH(49,Engine!$C$2:$C$622,0))) | K62: =IF(ISNA(MATCH(49,Engine!$C$2:$C$622,0)),"",INDEX('Compliance Database'!$K$2:$K$622,MATCH(49,Engine!$C$2:$C$622,0))) | L62: =IF(ISNA(MATCH(49,Engine!$C$2:$C$622,0)),"",INDEX('Compliance Database'!$L$2:$L$622,MATCH(49,Engine!$C$2:$C$622,0))) | M62: =IF(ISNA(MATCH(49,Engine!$C$2:$C$622,0)),"",INDEX('Compliance Database'!$M$2:$M$622,MATCH(49,Engine!$C$2:$C$622,0))) | N62: =IF(ISNA(MATCH(49,Engine!$C$2:$C$622,0)),"",INDEX('Compliance Database'!$N$2:$N$622,MATCH(49,Engine!$C$2:$C$622,0))) | O62: =IF(ISNA(MATCH(49,Engine!$C$2:$C$622,0)),"",INDEX('Compliance Database'!$O$2:$O$622,MATCH(49,Engine!$C$2:$C$622,0)))
A63: =IF(ISNA(MATCH(50,Engine!$C$2:$C$622,0)),"",INDEX('Compliance Database'!$A$2:$A$622,MATCH(50,Engine!$C$2:$C$622,0))) | B63: =IF(ISNA(MATCH(50,Engine!$C$2:$C$622,0)),"",INDEX('Compliance Database'!$B$2:$B$622,MATCH(50,Engine!$C$2:$C$622,0))) | C63: =IF(ISNA(MATCH(50,Engine!$C$2:$C$622,0)),"",INDEX('Compliance Database'!$C$2:$C$622,MATCH(50,Engine!$C$2:$C$622,0))) | D63: =IF(ISNA(MATCH(50,Engine!$C$2:$C$622,0)),"",INDEX('Compliance Database'!$D$2:$D$622,MATCH(50,Engine!$C$2:$C$622,0))) | E63: =IF(ISNA(MATCH(50,Engine!$C$2:$C$622,0)),"",INDEX('Compliance Database'!$E$2:$E$622,MATCH(50,Engine!$C$2:$C$622,0))) | F63: =IF(ISNA(MATCH(50,Engine!$C$2:$C$622,0)),"",INDEX('Compliance Database'!$F$2:$F$622,MATCH(50,Engine!$C$2:$C$622,0))) | G63: =IF(ISNA(MATCH(50,Engine!$C$2:$C$622,0)),"",INDEX('Compliance Database'!$G$2:$G$622,MATCH(50,Engine!$C$2:$C$622,0))) | H63: =IF(ISNA(MATCH(50,Engine!$C$2:$C$622,0)),"",INDEX('Compliance Database'!$H$2:$H$622,MATCH(50,Engine!$C$2:$C$622,0))) | I63: =IF(ISNA(MATCH(50,Engine!$C$2:$C$622,0)),"",INDEX('Compliance Database'!$I$2:$I$622,MATCH(50,Engine!$C$2:$C$622,0))) | J63: =IF(ISNA(MATCH(50,Engine!$C$2:$C$622,0)),"",INDEX('Compliance Database'!$J$2:$J$622,MATCH(50,Engine!$C$2:$C$622,0))) | K63: =IF(ISNA(MATCH(50,Engine!$C$2:$C$622,0)),"",INDEX('Compliance Database'!$K$2:$K$622,MATCH(50,Engine!$C$2:$C$622,0))) | L63: =IF(ISNA(MATCH(50,Engine!$C$2:$C$622,0)),"",INDEX('Compliance Database'!$L$2:$L$622,MATCH(50,Engine!$C$2:$C$622,0))) | M63: =IF(ISNA(MATCH(50,Engine!$C$2:$C$622,0)),"",INDEX('Compliance Database'!$M$2:$M$622,MATCH(50,Engine!$C$2:$C$622,0))) | N63: =IF(ISNA(MATCH(50,Engine!$C$2:$C$622,0)),"",INDEX('Compliance Database'!$N$2:$N$622,MATCH(50,Engine!$C$2:$C$622,0))) | O63: =IF(ISNA(MATCH(50,Engine!$C$2:$C$622,0)),"",INDEX('Compliance Database'!$O$2:$O$622,MATCH(50,Engine!$C$2:$C$622,0)))
A64: =IF(ISNA(MATCH(51,Engine!$C$2:$C$622,0)),"",INDEX('Compliance Database'!$A$2:$A$622,MATCH(51,Engine!$C$2:$C$622,0))) | B64: =IF(ISNA(MATCH(51,Engine!$C$2:$C$622,0)),"",INDEX('Compliance Database'!$B$2:$B$622,MATCH(51,Engine!$C$2:$C$622,0))) | C64: =IF(ISNA(MATCH(51,Engine!$C$2:$C$622,0)),"",INDEX('Compliance Database'!$C$2:$C$622,MATCH(51,Engine!$C$2:$C$622,0))) | D64: =IF(ISNA(MATCH(51,Engine!$C$2:$C$622,0)),"",INDEX('Compliance Database'!$D$2:$D$622,MATCH(51,Engine!$C$2:$C$622,0))) | E64: =IF(ISNA(MATCH(51,Engine!$C$2:$C$622,0)),"",INDEX('Compliance Database'!$E$2:$E$622,MATCH(51,Engine!$C$2:$C$622,0))) | F64: =IF(ISNA(MATCH(51,Engine!$C$2:$C$622,0)),"",INDEX('Compliance Database'!$F$2:$F$622,MATCH(51,Engine!$C$2:$C$622,0))) | G64: =IF(ISNA(MATCH(51,Engine!$C$2:$C$622,0)),"",INDEX('Compliance Database'!$G$2:$G$622,MATCH(51,Engine!$C$2:$C$622,0))) | H64: =IF(ISNA(MATCH(51,Engine!$C$2:$C$622,0)),"",INDEX('Compliance Database'!$H$2:$H$622,MATCH(51,Engine!$C$2:$C$622,0))) | I64: =IF(ISNA(MATCH(51,Engine!$C$2:$C$622,0)),"",INDEX('Compliance Database'!$I$2:$I$622,MATCH(51,Engine!$C$2:$C$622,0))) | J64: =IF(ISNA(MATCH(51,Engine!$C$2:$C$622,0)),"",INDEX('Compliance Database'!$J$2:$J$622,MATCH(51,Engine!$C$2:$C$622,0))) | K64: =IF(ISNA(MATCH(51,Engine!$C$2:$C$622,0)),"",INDEX('Compliance Database'!$K$2:$K$622,MATCH(51,Engine!$C$2:$C$622,0))) | L64: =IF(ISNA(MATCH(51,Engine!$C$2:$C$622,0)),"",INDEX('Compliance Database'!$L$2:$L$622,MATCH(51,Engine!$C$2:$C$622,0))) | M64: =IF(ISNA(MATCH(51,Engine!$C$2:$C$622,0)),"",INDEX('Compliance Database'!$M$2:$M$622,MATCH(51,Engine!$C$2:$C$622,0))) | N64: =IF(ISNA(MATCH(51,Engine!$C$2:$C$622,0)),"",INDEX('Compliance Database'!$N$2:$N$622,MATCH(51,Engine!$C$2:$C$622,0))) | O64: =IF(ISNA(MATCH(51,Engine!$C$2:$C$622,0)),"",INDEX('Compliance Database'!$O$2:$O$622,MATCH(51,Engine!$C$2:$C$622,0)))
A65: =IF(ISNA(MATCH(52,Engine!$C$2:$C$622,0)),"",INDEX('Compliance Database'!$A$2:$A$622,MATCH(52,Engine!$C$2:$C$622,0))) | B65: =IF(ISNA(MATCH(52,Engine!$C$2:$C$622,0)),"",INDEX('Compliance Database'!$B$2:$B$622,MATCH(52,Engine!$C$2:$C$622,0))) | C65: =IF(ISNA(MATCH(52,Engine!$C$2:$C$622,0)),"",INDEX('Compliance Database'!$C$2:$C$622,MATCH(52,Engine!$C$2:$C$622,0))) | D65: =IF(ISNA(MATCH(52,Engine!$C$2:$C$622,0)),"",INDEX('Compliance Database'!$D$2:$D$622,MATCH(52,Engine!$C$2:$C$622,0))) | E65: =IF(ISNA(MATCH(52,Engine!$C$2:$C$622,0)),"",INDEX('Compliance Database'!$E$2:$E$622,MATCH(52,Engine!$C$2:$C$622,0))) | F65: =IF(ISNA(MATCH(52,Engine!$C$2:$C$622,0)),"",INDEX('Compliance Database'!$F$2:$F$622,MATCH(52,Engine!$C$2:$C$622,0))) | G65: =IF(ISNA(MATCH(52,Engine!$C$2:$C$622,0)),"",INDEX('Compliance Database'!$G$2:$G$622,MATCH(52,Engine!$C$2:$C$622,0))) | H65: =IF(ISNA(MATCH(52,Engine!$C$2:$C$622,0)),"",INDEX('Compliance Database'!$H$2:$H$622,MATCH(52,Engine!$C$2:$C$622,0))) | I65: =IF(ISNA(MATCH(52,Engine!$C$2:$C$622,0)),"",INDEX('Compliance Database'!$I$2:$I$622,MATCH(52,Engine!$C$2:$C$622,0))) | J65: =IF(ISNA(MATCH(52,Engine!$C$2:$C$622,0)),"",INDEX('Compliance Database'!$J$2:$J$622,MATCH(52,Engine!$C$2:$C$622,0))) | K65: =IF(ISNA(MATCH(52,Engine!$C$2:$C$622,0)),"",INDEX('Compliance Database'!$K$2:$K$622,MATCH(52,Engine!$C$2:$C$622,0))) | L65: =IF(ISNA(MATCH(52,Engine!$C$2:$C$622,0)),"",INDEX('Compliance Database'!$L$2:$L$622,MATCH(52,Engine!$C$2:$C$622,0))) | M65: =IF(ISNA(MATCH(52,Engine!$C$2:$C$622,0)),"",INDEX('Compliance Database'!$M$2:$M$622,MATCH(52,Engine!$C$2:$C$622,0))) | N65: =IF(ISNA(MATCH(52,Engine!$C$2:$C$622,0)),"",INDEX('Compliance Database'!$N$2:$N$622,MATCH(52,Engine!$C$2:$C$622,0))) | O65: =IF(ISNA(MATCH(52,Engine!$C$2:$C$622,0)),"",INDEX('Compliance Database'!$O$2:$O$622,MATCH(52,Engine!$C$2:$C$622,0)))
A66: =IF(ISNA(MATCH(53,Engine!$C$2:$C$622,0)),"",INDEX('Compliance Database'!$A$2:$A$622,MATCH(53,Engine!$C$2:$C$622,0))) | B66: =IF(ISNA(MATCH(53,Engine!$C$2:$C$622,0)),"",INDEX('Compliance Database'!$B$2:$B$622,MATCH(53,Engine!$C$2:$C$622,0))) | C66: =IF(ISNA(MATCH(53,Engine!$C$2:$C$622,0)),"",INDEX('Compliance Database'!$C$2:$C$622,MATCH(53,Engine!$C$2:$C$622,0))) | D66: =IF(ISNA(MATCH(53,Engine!$C$2:$C$622,0)),"",INDEX('Compliance Database'!$D$2:$D$622,MATCH(53,Engine!$C$2:$C$622,0))) | E66: =IF(ISNA(MATCH(53,Engine!$C$2:$C$622,0)),"",INDEX('Compliance Database'!$E$2:$E$622,MATCH(53,Engine!$C$2:$C$622,0))) | F66: =IF(ISNA(MATCH(53,Engine!$C$2:$C$622,0)),"",INDEX('Compliance Database'!$F$2:$F$622,MATCH(53,Engine!$C$2:$C$622,0))) | G66: =IF(ISNA(MATCH(53,Engine!$C$2:$C$622,0)),"",INDEX('Compliance Database'!$G$2:$G$622,MATCH(53,Engine!$C$2:$C$622,0))) | H66: =IF(ISNA(MATCH(53,Engine!$C$2:$C$622,0)),"",INDEX('Compliance Database'!$H$2:$H$622,MATCH(53,Engine!$C$2:$C$622,0))) | I66: =IF(ISNA(MATCH(53,Engine!$C$2:$C$622,0)),"",INDEX('Compliance Database'!$I$2:$I$622,MATCH(53,Engine!$C$2:$C$622,0))) | J66: =IF(ISNA(MATCH(53,Engine!$C$2:$C$622,0)),"",INDEX('Compliance Database'!$J$2:$J$622,MATCH(53,Engine!$C$2:$C$622,0))) | K66: =IF(ISNA(MATCH(53,Engine!$C$2:$C$622,0)),"",INDEX('Compliance Database'!$K$2:$K$622,MATCH(53,Engine!$C$2:$C$622,0))) | L66: =IF(ISNA(MATCH(53,Engine!$C$2:$C$622,0)),"",INDEX('Compliance Database'!$L$2:$L$622,MATCH(53,Engine!$C$2:$C$622,0))) | M66: =IF(ISNA(MATCH(53,Engine!$C$2:$C$622,0)),"",INDEX('Compliance Database'!$M$2:$M$622,MATCH(53,Engine!$C$2:$C$622,0))) | N66: =IF(ISNA(MATCH(53,Engine!$C$2:$C$622,0)),"",INDEX('Compliance Database'!$N$2:$N$622,MATCH(53,Engine!$C$2:$C$622,0))) | O66: =IF(ISNA(MATCH(53,Engine!$C$2:$C$622,0)),"",INDEX('Compliance Database'!$O$2:$O$622,MATCH(53,Engine!$C$2:$C$622,0)))
A67: =IF(ISNA(MATCH(54,Engine!$C$2:$C$622,0)),"",INDEX('Compliance Database'!$A$2:$A$622,MATCH(54,Engine!$C$2:$C$622,0))) | B67: =IF(ISNA(MATCH(54,Engine!$C$2:$C$622,0)),"",INDEX('Compliance Database'!$B$2:$B$622,MATCH(54,Engine!$C$2:$C$622,0))) | C67: =IF(ISNA(MATCH(54,Engine!$C$2:$C$622,0)),"",INDEX('Compliance Database'!$C$2:$C$622,MATCH(54,Engine!$C$2:$C$622,0))) | D67: =IF(ISNA(MATCH(54,Engine!$C$2:$C$622,0)),"",INDEX('Compliance Database'!$D$2:$D$622,MATCH(54,Engine!$C$2:$C$622,0))) | E67: =IF(ISNA(MATCH(54,Engine!$C$2:$C$622,0)),"",INDEX('Compliance Database'!$E$2:$E$622,MATCH(54,Engine!$C$2:$C$622,0))) | F67: =IF(ISNA(MATCH(54,Engine!$C$2:$C$622,0)),"",INDEX('Compliance Database'!$F$2:$F$622,MATCH(54,Engine!$C$2:$C$622,0))) | G67: =IF(ISNA(MATCH(54,Engine!$C$2:$C$622,0)),"",INDEX('Compliance Database'!$G$2:$G$622,MATCH(54,Engine!$C$2:$C$622,0))) | H67: =IF(ISNA(MATCH(54,Engine!$C$2:$C$622,0)),"",INDEX('Compliance Database'!$H$2:$H$622,MATCH(54,Engine!$C$2:$C$622,0))) | I67: =IF(ISNA(MATCH(54,Engine!$C$2:$C$622,0)),"",INDEX('Compliance Database'!$I$2:$I$622,MATCH(54,Engine!$C$2:$C$622,0))) | J67: =IF(ISNA(MATCH(54,Engine!$C$2:$C$622,0)),"",INDEX('Compliance Database'!$J$2:$J$622,MATCH(54,Engine!$C$2:$C$622,0))) | K67: =IF(ISNA(MATCH(54,Engine!$C$2:$C$622,0)),"",INDEX('Compliance Database'!$K$2:$K$622,MATCH(54,Engine!$C$2:$C$622,0))) | L67: =IF(ISNA(MATCH(54,Engine!$C$2:$C$622,0)),"",INDEX('Compliance Database'!$L$2:$L$622,MATCH(54,Engine!$C$2:$C$622,0))) | M67: =IF(ISNA(MATCH(54,Engine!$C$2:$C$622,0)),"",INDEX('Compliance Database'!$M$2:$M$622,MATCH(54,Engine!$C$2:$C$622,0))) | N67: =IF(ISNA(MATCH(54,Engine!$C$2:$C$622,0)),"",INDEX('Compliance Database'!$N$2:$N$622,MATCH(54,Engine!$C$2:$C$622,0))) | O67: =IF(ISNA(MATCH(54,Engine!$C$2:$C$622,0)),"",INDEX('Compliance Database'!$O$2:$O$622,MATCH(54,Engine!$C$2:$C$622,0)))
A68: =IF(ISNA(MATCH(55,Engine!$C$2:$C$622,0)),"",INDEX('Compliance Database'!$A$2:$A$622,MATCH(55,Engine!$C$2:$C$622,0))) | B68: =IF(ISNA(MATCH(55,Engine!$C$2:$C$622,0)),"",INDEX('Compliance Database'!$B$2:$B$622,MATCH(55,Engine!$C$2:$C$622,0))) | C68: =IF(ISNA(MATCH(55,Engine!$C$2:$C$622,0)),"",INDEX('Compliance Database'!$C$2:$C$622,MATCH(55,Engine!$C$2:$C$622,0))) | D68: =IF(ISNA(MATCH(55,Engine!$C$2:$C$622,0)),"",INDEX('Compliance Database'!$D$2:$D$622,MATCH(55,Engine!$C$2:$C$622,0))) | E68: =IF(ISNA(MATCH(55,Engine!$C$2:$C$622,0)),"",INDEX('Compliance Database'!$E$2:$E$622,MATCH(55,Engine!$C$2:$C$622,0))) | F68: =IF(ISNA(MATCH(55,Engine!$C$2:$C$622,0)),"",INDEX('Compliance Database'!$F$2:$F$622,MATCH(55,Engine!$C$2:$C$622,0))) | G68: =IF(ISNA(MATCH(55,Engine!$C$2:$C$622,0)),"",INDEX('Compliance Database'!$G$2:$G$622,MATCH(55,Engine!$C$2:$C$622,0))) | H68: =IF(ISNA(MATCH(55,Engine!$C$2:$C$622,0)),"",INDEX('Compliance Database'!$H$2:$H$622,MATCH(55,Engine!$C$2:$C$622,0))) | I68: =IF(ISNA(MATCH(55,Engine!$C$2:$C$622,0)),"",INDEX('Compliance Database'!$I$2:$I$622,MATCH(55,Engine!$C$2:$C$622,0))) | J68: =IF(ISNA(MATCH(55,Engine!$C$2:$C$622,0)),"",INDEX('Compliance Database'!$J$2:$J$622,MATCH(55,Engine!$C$2:$C$622,0))) | K68: =IF(ISNA(MATCH(55,Engine!$C$2:$C$622,0)),"",INDEX('Compliance Database'!$K$2:$K$622,MATCH(55,Engine!$C$2:$C$622,0))) | L68: =IF(ISNA(MATCH(55,Engine!$C$2:$C$622,0)),"",INDEX('Compliance Database'!$L$2:$L$622,MATCH(55,Engine!$C$2:$C$622,0))) | M68: =IF(ISNA(MATCH(55,Engine!$C$2:$C$622,0)),"",INDEX('Compliance Database'!$M$2:$M$622,MATCH(55,Engine!$C$2:$C$622,0))) | N68: =IF(ISNA(MATCH(55,Engine!$C$2:$C$622,0)),"",INDEX('Compliance Database'!$N$2:$N$622,MATCH(55,Engine!$C$2:$C$622,0))) | O68: =IF(ISNA(MATCH(55,Engine!$C$2:$C$622,0)),"",INDEX('Compliance Database'!$O$2:$O$622,MATCH(55,Engine!$C$2:$C$622,0)))
A69: =IF(ISNA(MATCH(56,Engine!$C$2:$C$622,0)),"",INDEX('Compliance Database'!$A$2:$A$622,MATCH(56,Engine!$C$2:$C$622,0))) | B69: =IF(ISNA(MATCH(56,Engine!$C$2:$C$622,0)),"",INDEX('Compliance Database'!$B$2:$B$622,MATCH(56,Engine!$C$2:$C$622,0))) | C69: =IF(ISNA(MATCH(56,Engine!$C$2:$C$622,0)),"",INDEX('Compliance Database'!$C$2:$C$622,MATCH(56,Engine!$C$2:$C$622,0))) | D69: =IF(ISNA(MATCH(56,Engine!$C$2:$C$622,0)),"",INDEX('Compliance Database'!$D$2:$D$622,MATCH(56,Engine!$C$2:$C$622,0))) | E69: =IF(ISNA(MATCH(56,Engine!$C$2:$C$622,0)),"",INDEX('Compliance Database'!$E$2:$E$622,MATCH(56,Engine!$C$2:$C$622,0))) | F69: =IF(ISNA(MATCH(56,Engine!$C$2:$C$622,0)),"",INDEX('Compliance Database'!$F$2:$F$622,MATCH(56,Engine!$C$2:$C$622,0))) | G69: =IF(ISNA(MATCH(56,Engine!$C$2:$C$622,0)),"",INDEX('Compliance Database'!$G$2:$G$622,MATCH(56,Engine!$C$2:$C$622,0))) | H69: =IF(ISNA(MATCH(56,Engine!$C$2:$C$622,0)),"",INDEX('Compliance Database'!$H$2:$H$622,MATCH(56,Engine!$C$2:$C$622,0))) | I69: =IF(ISNA(MATCH(56,Engine!$C$2:$C$622,0)),"",INDEX('Compliance Database'!$I$2:$I$622,MATCH(56,Engine!$C$2:$C$622,0))) | J69: =IF(ISNA(MATCH(56,Engine!$C$2:$C$622,0)),"",INDEX('Compliance Database'!$J$2:$J$622,MATCH(56,Engine!$C$2:$C$622,0))) | K69: =IF(ISNA(MATCH(56,Engine!$C$2:$C$622,0)),"",INDEX('Compliance Database'!$K$2:$K$622,MATCH(56,Engine!$C$2:$C$622,0))) | L69: =IF(ISNA(MATCH(56,Engine!$C$2:$C$622,0)),"",INDEX('Compliance Database'!$L$2:$L$622,MATCH(56,Engine!$C$2:$C$622,0))) | M69: =IF(ISNA(MATCH(56,Engine!$C$2:$C$622,0)),"",INDEX('Compliance Database'!$M$2:$M$622,MATCH(56,Engine!$C$2:$C$622,0))) | N69: =IF(ISNA(MATCH(56,Engine!$C$2:$C$622,0)),"",INDEX('Compliance Database'!$N$2:$N$622,MATCH(56,Engine!$C$2:$C$622,0))) | O69: =IF(ISNA(MATCH(56,Engine!$C$2:$C$622,0)),"",INDEX('Compliance Database'!$O$2:$O$622,MATCH(56,Engine!$C$2:$C$622,0)))
A70: =IF(ISNA(MATCH(57,Engine!$C$2:$C$622,0)),"",INDEX('Compliance Database'!$A$2:$A$622,MATCH(57,Engine!$C$2:$C$622,0))) | B70: =IF(ISNA(MATCH(57,Engine!$C$2:$C$622,0)),"",INDEX('Compliance Database'!$B$2:$B$622,MATCH(57,Engine!$C$2:$C$622,0))) | C70: =IF(ISNA(MATCH(57,Engine!$C$2:$C$622,0)),"",INDEX('Compliance Database'!$C$2:$C$622,MATCH(57,Engine!$C$2:$C$622,0))) | D70: =IF(ISNA(MATCH(57,Engine!$C$2:$C$622,0)),"",INDEX('Compliance Database'!$D$2:$D$622,MATCH(57,Engine!$C$2:$C$622,0))) | E70: =IF(ISNA(MATCH(57,Engine!$C$2:$C$622,0)),"",INDEX('Compliance Database'!$E$2:$E$622,MATCH(57,Engine!$C$2:$C$622,0))) | F70: =IF(ISNA(MATCH(57,Engine!$C$2:$C$622,0)),"",INDEX('Compliance Database'!$F$2:$F$622,MATCH(57,Engine!$C$2:$C$622,0))) | G70: =IF(ISNA(MATCH(57,Engine!$C$2:$C$622,0)),"",INDEX('Compliance Database'!$G$2:$G$622,MATCH(57,Engine!$C$2:$C$622,0))) | H70: =IF(ISNA(MATCH(57,Engine!$C$2:$C$622,0)),"",INDEX('Compliance Database'!$H$2:$H$622,MATCH(57,Engine!$C$2:$C$622,0))) | I70: =IF(ISNA(MATCH(57,Engine!$C$2:$C$622,0)),"",INDEX('Compliance Database'!$I$2:$I$622,MATCH(57,Engine!$C$2:$C$622,0))) | J70: =IF(ISNA(MATCH(57,Engine!$C$2:$C$622,0)),"",INDEX('Compliance Database'!$J$2:$J$622,MATCH(57,Engine!$C$2:$C$622,0))) | K70: =IF(ISNA(MATCH(57,Engine!$C$2:$C$622,0)),"",INDEX('Compliance Database'!$K$2:$K$622,MATCH(57,Engine!$C$2:$C$622,0))) | L70: =IF(ISNA(MATCH(57,Engine!$C$2:$C$622,0)),"",INDEX('Compliance Database'!$L$2:$L$622,MATCH(57,Engine!$C$2:$C$622,0))) | M70: =IF(ISNA(MATCH(57,Engine!$C$2:$C$622,0)),"",INDEX('Compliance Database'!$M$2:$M$622,MATCH(57,Engine!$C$2:$C$622,0))) | N70: =IF(ISNA(MATCH(57,Engine!$C$2:$C$622,0)),"",INDEX('Compliance Database'!$N$2:$N$622,MATCH(57,Engine!$C$2:$C$622,0))) | O70: =IF(ISNA(MATCH(57,Engine!$C$2:$C$622,0)),"",INDEX('Compliance Database'!$O$2:$O$622,MATCH(57,Engine!$C$2:$C$622,0)))
A71: =IF(ISNA(MATCH(58,Engine!$C$2:$C$622,0)),"",INDEX('Compliance Database'!$A$2:$A$622,MATCH(58,Engine!$C$2:$C$622,0))) | B71: =IF(ISNA(MATCH(58,Engine!$C$2:$C$622,0)),"",INDEX('Compliance Database'!$B$2:$B$622,MATCH(58,Engine!$C$2:$C$622,0))) | C71: =IF(ISNA(MATCH(58,Engine!$C$2:$C$622,0)),"",INDEX('Compliance Database'!$C$2:$C$622,MATCH(58,Engine!$C$2:$C$622,0))) | D71: =IF(ISNA(MATCH(58,Engine!$C$2:$C$622,0)),"",INDEX('Compliance Database'!$D$2:$D$622,MATCH(58,Engine!$C$2:$C$622,0))) | E71: =IF(ISNA(MATCH(58,Engine!$C$2:$C$622,0)),"",INDEX('Compliance Database'!$E$2:$E$622,MATCH(58,Engine!$C$2:$C$622,0))) | F71: =IF(ISNA(MATCH(58,Engine!$C$2:$C$622,0)),"",INDEX('Compliance Database'!$F$2:$F$622,MATCH(58,Engine!$C$2:$C$622,0))) | G71: =IF(ISNA(MATCH(58,Engine!$C$2:$C$622,0)),"",INDEX('Compliance Database'!$G$2:$G$622,MATCH(58,Engine!$C$2:$C$622,0))) | H71: =IF(ISNA(MATCH(58,Engine!$C$2:$C$622,0)),"",INDEX('Compliance Database'!$H$2:$H$622,MATCH(58,Engine!$C$2:$C$622,0))) | I71: =IF(ISNA(MATCH(58,Engine!$C$2:$C$622,0)),"",INDEX('Compliance Database'!$I$2:$I$622,MATCH(58,Engine!$C$2:$C$622,0))) | J71: =IF(ISNA(MATCH(58,Engine!$C$2:$C$622,0)),"",INDEX('Compliance Database'!$J$2:$J$622,MATCH(58,Engine!$C$2:$C$622,0))) | K71: =IF(ISNA(MATCH(58,Engine!$C$2:$C$622,0)),"",INDEX('Compliance Database'!$K$2:$K$622,MATCH(58,Engine!$C$2:$C$622,0))) | L71: =IF(ISNA(MATCH(58,Engine!$C$2:$C$622,0)),"",INDEX('Compliance Database'!$L$2:$L$622,MATCH(58,Engine!$C$2:$C$622,0))) | M71: =IF(ISNA(MATCH(58,Engine!$C$2:$C$622,0)),"",INDEX('Compliance Database'!$M$2:$M$622,MATCH(58,Engine!$C$2:$C$622,0))) | N71: =IF(ISNA(MATCH(58,Engine!$C$2:$C$622,0)),"",INDEX('Compliance Database'!$N$2:$N$622,MATCH(58,Engine!$C$2:$C$622,0))) | O71: =IF(ISNA(MATCH(58,Engine!$C$2:$C$622,0)),"",INDEX('Compliance Database'!$O$2:$O$622,MATCH(58,Engine!$C$2:$C$622,0)))
A72: =IF(ISNA(MATCH(59,Engine!$C$2:$C$622,0)),"",INDEX('Compliance Database'!$A$2:$A$622,MATCH(59,Engine!$C$2:$C$622,0))) | B72: =IF(ISNA(MATCH(59,Engine!$C$2:$C$622,0)),"",INDEX('Compliance Database'!$B$2:$B$622,MATCH(59,Engine!$C$2:$C$622,0))) | C72: =IF(ISNA(MATCH(59,Engine!$C$2:$C$622,0)),"",INDEX('Compliance Database'!$C$2:$C$622,MATCH(59,Engine!$C$2:$C$622,0))) | D72: =IF(ISNA(MATCH(59,Engine!$C$2:$C$622,0)),"",INDEX('Compliance Database'!$D$2:$D$622,MATCH(59,Engine!$C$2:$C$622,0))) | E72: =IF(ISNA(MATCH(59,Engine!$C$2:$C$622,0)),"",INDEX('Compliance Database'!$E$2:$E$622,MATCH(59,Engine!$C$2:$C$622,0))) | F72: =IF(ISNA(MATCH(59,Engine!$C$2:$C$622,0)),"",INDEX('Compliance Database'!$F$2:$F$622,MATCH(59,Engine!$C$2:$C$622,0))) | G72: =IF(ISNA(MATCH(59,Engine!$C$2:$C$622,0)),"",INDEX('Compliance Database'!$G$2:$G$622,MATCH(59,Engine!$C$2:$C$622,0))) | H72: =IF(ISNA(MATCH(59,Engine!$C$2:$C$622,0)),"",INDEX('Compliance Database'!$H$2:$H$622,MATCH(59,Engine!$C$2:$C$622,0))) | I72: =IF(ISNA(MATCH(59,Engine!$C$2:$C$622,0)),"",INDEX('Compliance Database'!$I$2:$I$622,MATCH(59,Engine!$C$2:$C$622,0))) | J72: =IF(ISNA(MATCH(59,Engine!$C$2:$C$622,0)),"",INDEX('Compliance Database'!$J$2:$J$622,MATCH(59,Engine!$C$2:$C$622,0))) | K72: =IF(ISNA(MATCH(59,Engine!$C$2:$C$622,0)),"",INDEX('Compliance Database'!$K$2:$K$622,MATCH(59,Engine!$C$2:$C$622,0))) | L72: =IF(ISNA(MATCH(59,Engine!$C$2:$C$622,0)),"",INDEX('Compliance Database'!$L$2:$L$622,MATCH(59,Engine!$C$2:$C$622,0))) | M72: =IF(ISNA(MATCH(59,Engine!$C$2:$C$622,0)),"",INDEX('Compliance Database'!$M$2:$M$622,MATCH(59,Engine!$C$2:$C$622,0))) | N72: =IF(ISNA(MATCH(59,Engine!$C$2:$C$622,0)),"",INDEX('Compliance Database'!$N$2:$N$622,MATCH(59,Engine!$C$2:$C$622,0))) | O72: =IF(ISNA(MATCH(59,Engine!$C$2:$C$622,0)),"",INDEX('Compliance Database'!$O$2:$O$622,MATCH(59,Engine!$C$2:$C$622,0)))
A73: =IF(ISNA(MATCH(60,Engine!$C$2:$C$622,0)),"",INDEX('Compliance Database'!$A$2:$A$622,MATCH(60,Engine!$C$2:$C$622,0))) | B73: =IF(ISNA(MATCH(60,Engine!$C$2:$C$622,0)),"",INDEX('Compliance Database'!$B$2:$B$622,MATCH(60,Engine!$C$2:$C$622,0))) | C73: =IF(ISNA(MATCH(60,Engine!$C$2:$C$622,0)),"",INDEX('Compliance Database'!$C$2:$C$622,MATCH(60,Engine!$C$2:$C$622,0))) | D73: =IF(ISNA(MATCH(60,Engine!$C$2:$C$622,0)),"",INDEX('Compliance Database'!$D$2:$D$622,MATCH(60,Engine!$C$2:$C$622,0))) | E73: =IF(ISNA(MATCH(60,Engine!$C$2:$C$622,0)),"",INDEX('Compliance Database'!$E$2:$E$622,MATCH(60,Engine!$C$2:$C$622,0))) | F73: =IF(ISNA(MATCH(60,Engine!$C$2:$C$622,0)),"",INDEX('Compliance Database'!$F$2:$F$622,MATCH(60,Engine!$C$2:$C$622,0))) | G73: =IF(ISNA(MATCH(60,Engine!$C$2:$C$622,0)),"",INDEX('Compliance Database'!$G$2:$G$622,MATCH(60,Engine!$C$2:$C$622,0))) | H73: =IF(ISNA(MATCH(60,Engine!$C$2:$C$622,0)),"",INDEX('Compliance Database'!$H$2:$H$622,MATCH(60,Engine!$C$2:$C$622,0))) | I73: =IF(ISNA(MATCH(60,Engine!$C$2:$C$622,0)),"",INDEX('Compliance Database'!$I$2:$I$622,MATCH(60,Engine!$C$2:$C$622,0))) | J73: =IF(ISNA(MATCH(60,Engine!$C$2:$C$622,0)),"",INDEX('Compliance Database'!$J$2:$J$622,MATCH(60,Engine!$C$2:$C$622,0))) | K73: =IF(ISNA(MATCH(60,Engine!$C$2:$C$622,0)),"",INDEX('Compliance Database'!$K$2:$K$622,MATCH(60,Engine!$C$2:$C$622,0))) | L73: =IF(ISNA(MATCH(60,Engine!$C$2:$C$622,0)),"",INDEX('Compliance Database'!$L$2:$L$622,MATCH(60,Engine!$C$2:$C$622,0))) | M73: =IF(ISNA(MATCH(60,Engine!$C$2:$C$622,0)),"",INDEX('Compliance Database'!$M$2:$M$622,MATCH(60,Engine!$C$2:$C$622,0))) | N73: =IF(ISNA(MATCH(60,Engine!$C$2:$C$622,0)),"",INDEX('Compliance Database'!$N$2:$N$622,MATCH(60,Engine!$C$2:$C$622,0))) | O73: =IF(ISNA(MATCH(60,Engine!$C$2:$C$622,0)),"",INDEX('Compliance Database'!$O$2:$O$622,MATCH(60,Engine!$C$2:$C$622,0)))
A74: =IF(ISNA(MATCH(61,Engine!$C$2:$C$622,0)),"",INDEX('Compliance Database'!$A$2:$A$622,MATCH(61,Engine!$C$2:$C$622,0))) | B74: =IF(ISNA(MATCH(61,Engine!$C$2:$C$622,0)),"",INDEX('Compliance Database'!$B$2:$B$622,MATCH(61,Engine!$C$2:$C$622,0))) | C74: =IF(ISNA(MATCH(61,Engine!$C$2:$C$622,0)),"",INDEX('Compliance Database'!$C$2:$C$622,MATCH(61,Engine!$C$2:$C$622,0))) | D74: =IF(ISNA(MATCH(61,Engine!$C$2:$C$622,0)),"",INDEX('Compliance Database'!$D$2:$D$622,MATCH(61,Engine!$C$2:$C$622,0))) | E74: =IF(ISNA(MATCH(61,Engine!$C$2:$C$622,0)),"",INDEX('Compliance Database'!$E$2:$E$622,MATCH(61,Engine!$C$2:$C$622,0))) | F74: =IF(ISNA(MATCH(61,Engine!$C$2:$C$622,0)),"",INDEX('Compliance Database'!$F$2:$F$622,MATCH(61,Engine!$C$2:$C$622,0))) | G74: =IF(ISNA(MATCH(61,Engine!$C$2:$C$622,0)),"",INDEX('Compliance Database'!$G$2:$G$622,MATCH(61,Engine!$C$2:$C$622,0))) | H74: =IF(ISNA(MATCH(61,Engine!$C$2:$C$622,0)),"",INDEX('Compliance Database'!$H$2:$H$622,MATCH(61,Engine!$C$2:$C$622,0))) | I74: =IF(ISNA(MATCH(61,Engine!$C$2:$C$622,0)),"",INDEX('Compliance Database'!$I$2:$I$622,MATCH(61,Engine!$C$2:$C$622,0))) | J74: =IF(ISNA(MATCH(61,Engine!$C$2:$C$622,0)),"",INDEX('Compliance Database'!$J$2:$J$622,MATCH(61,Engine!$C$2:$C$622,0))) | K74: =IF(ISNA(MATCH(61,Engine!$C$2:$C$622,0)),"",INDEX('Compliance Database'!$K$2:$K$622,MATCH(61,Engine!$C$2:$C$622,0))) | L74: =IF(ISNA(MATCH(61,Engine!$C$2:$C$622,0)),"",INDEX('Compliance Database'!$L$2:$L$622,MATCH(61,Engine!$C$2:$C$622,0))) | M74: =IF(ISNA(MATCH(61,Engine!$C$2:$C$622,0)),"",INDEX('Compliance Database'!$M$2:$M$622,MATCH(61,Engine!$C$2:$C$622,0))) | N74: =IF(ISNA(MATCH(61,Engine!$C$2:$C$622,0)),"",INDEX('Compliance Database'!$N$2:$N$622,MATCH(61,Engine!$C$2:$C$622,0))) | O74: =IF(ISNA(MATCH(61,Engine!$C$2:$C$622,0)),"",INDEX('Compliance Database'!$O$2:$O$622,MATCH(61,Engine!$C$2:$C$622,0)))
A75: =IF(ISNA(MATCH(62,Engine!$C$2:$C$622,0)),"",INDEX('Compliance Database'!$A$2:$A$622,MATCH(62,Engine!$C$2:$C$622,0))) | B75: =IF(ISNA(MATCH(62,Engine!$C$2:$C$622,0)),"",INDEX('Compliance Database'!$B$2:$B$622,MATCH(62,Engine!$C$2:$C$622,0))) | C75: =IF(ISNA(MATCH(62,Engine!$C$2:$C$622,0)),"",INDEX('Compliance Database'!$C$2:$C$622,MATCH(62,Engine!$C$2:$C$622,0))) | D75: =IF(ISNA(MATCH(62,Engine!$C$2:$C$622,0)),"",INDEX('Compliance Database'!$D$2:$D$622,MATCH(62,Engine!$C$2:$C$622,0))) | E75: =IF(ISNA(MATCH(62,Engine!$C$2:$C$622,0)),"",INDEX('Compliance Database'!$E$2:$E$622,MATCH(62,Engine!$C$2:$C$622,0))) | F75: =IF(ISNA(MATCH(62,Engine!$C$2:$C$622,0)),"",INDEX('Compliance Database'!$F$2:$F$622,MATCH(62,Engine!$C$2:$C$622,0))) | G75: =IF(ISNA(MATCH(62,Engine!$C$2:$C$622,0)),"",INDEX('Compliance Database'!$G$2:$G$622,MATCH(62,Engine!$C$2:$C$622,0))) | H75: =IF(ISNA(MATCH(62,Engine!$C$2:$C$622,0)),"",INDEX('Compliance Database'!$H$2:$H$622,MATCH(62,Engine!$C$2:$C$622,0))) | I75: =IF(ISNA(MATCH(62,Engine!$C$2:$C$622,0)),"",INDEX('Compliance Database'!$I$2:$I$622,MATCH(62,Engine!$C$2:$C$622,0))) | J75: =IF(ISNA(MATCH(62,Engine!$C$2:$C$622,0)),"",INDEX('Compliance Database'!$J$2:$J$622,MATCH(62,Engine!$C$2:$C$622,0))) | K75: =IF(ISNA(MATCH(62,Engine!$C$2:$C$622,0)),"",INDEX('Compliance Database'!$K$2:$K$622,MATCH(62,Engine!$C$2:$C$622,0))) | L75: =IF(ISNA(MATCH(62,Engine!$C$2:$C$622,0)),"",INDEX('Compliance Database'!$L$2:$L$622,MATCH(62,Engine!$C$2:$C$622,0))) | M75: =IF(ISNA(MATCH(62,Engine!$C$2:$C$622,0)),"",INDEX('Compliance Database'!$M$2:$M$622,MATCH(62,Engine!$C$2:$C$622,0))) | N75: =IF(ISNA(MATCH(62,Engine!$C$2:$C$622,0)),"",INDEX('Compliance Database'!$N$2:$N$622,MATCH(62,Engine!$C$2:$C$622,0))) | O75: =IF(ISNA(MATCH(62,Engine!$C$2:$C$622,0)),"",INDEX('Compliance Database'!$O$2:$O$622,MATCH(62,Engine!$C$2:$C$622,0)))
A76: =IF(ISNA(MATCH(63,Engine!$C$2:$C$622,0)),"",INDEX('Compliance Database'!$A$2:$A$622,MATCH(63,Engine!$C$2:$C$622,0))) | B76: =IF(ISNA(MATCH(63,Engine!$C$2:$C$622,0)),"",INDEX('Compliance Database'!$B$2:$B$622,MATCH(63,Engine!$C$2:$C$622,0))) | C76: =IF(ISNA(MATCH(63,Engine!$C$2:$C$622,0)),"",INDEX('Compliance Database'!$C$2:$C$622,MATCH(63,Engine!$C$2:$C$622,0))) | D76: =IF(ISNA(MATCH(63,Engine!$C$2:$C$622,0)),"",INDEX('Compliance Database'!$D$2:$D$622,MATCH(63,Engine!$C$2:$C$622,0))) | E76: =IF(ISNA(MATCH(63,Engine!$C$2:$C$622,0)),"",INDEX('Compliance Database'!$E$2:$E$622,MATCH(63,Engine!$C$2:$C$622,0))) | F76: =IF(ISNA(MATCH(63,Engine!$C$2:$C$622,0)),"",INDEX('Compliance Database'!$F$2:$F$622,MATCH(63,Engine!$C$2:$C$622,0))) | G76: =IF(ISNA(MATCH(63,Engine!$C$2:$C$622,0)),"",INDEX('Compliance Database'!$G$2:$G$622,MATCH(63,Engine!$C$2:$C$622,0))) | H76: =IF(ISNA(MATCH(63,Engine!$C$2:$C$622,0)),"",INDEX('Compliance Database'!$H$2:$H$622,MATCH(63,Engine!$C$2:$C$622,0))) | I76: =IF(ISNA(MATCH(63,Engine!$C$2:$C$622,0)),"",INDEX('Compliance Database'!$I$2:$I$622,MATCH(63,Engine!$C$2:$C$622,0))) | J76: =IF(ISNA(MATCH(63,Engine!$C$2:$C$622,0)),"",INDEX('Compliance Database'!$J$2:$J$622,MATCH(63,Engine!$C$2:$C$622,0))) | K76: =IF(ISNA(MATCH(63,Engine!$C$2:$C$622,0)),"",INDEX('Compliance Database'!$K$2:$K$622,MATCH(63,Engine!$C$2:$C$622,0))) | L76: =IF(ISNA(MATCH(63,Engine!$C$2:$C$622,0)),"",INDEX('Compliance Database'!$L$2:$L$622,MATCH(63,Engine!$C$2:$C$622,0))) | M76: =IF(ISNA(MATCH(63,Engine!$C$2:$C$622,0)),"",INDEX('Compliance Database'!$M$2:$M$622,MATCH(63,Engine!$C$2:$C$622,0))) | N76: =IF(ISNA(MATCH(63,Engine!$C$2:$C$622,0)),"",INDEX('Compliance Database'!$N$2:$N$622,MATCH(63,Engine!$C$2:$C$622,0))) | O76: =IF(ISNA(MATCH(63,Engine!$C$2:$C$622,0)),"",INDEX('Compliance Database'!$O$2:$O$622,MATCH(63,Engine!$C$2:$C$622,0)))
A77: =IF(ISNA(MATCH(64,Engine!$C$2:$C$622,0)),"",INDEX('Compliance Database'!$A$2:$A$622,MATCH(64,Engine!$C$2:$C$622,0))) | B77: =IF(ISNA(MATCH(64,Engine!$C$2:$C$622,0)),"",INDEX('Compliance Database'!$B$2:$B$622,MATCH(64,Engine!$C$2:$C$622,0))) | C77: =IF(ISNA(MATCH(64,Engine!$C$2:$C$622,0)),"",INDEX('Compliance Database'!$C$2:$C$622,MATCH(64,Engine!$C$2:$C$622,0))) | D77: =IF(ISNA(MATCH(64,Engine!$C$2:$C$622,0)),"",INDEX('Compliance Database'!$D$2:$D$622,MATCH(64,Engine!$C$2:$C$622,0))) | E77: =IF(ISNA(MATCH(64,Engine!$C$2:$C$622,0)),"",INDEX('Compliance Database'!$E$2:$E$622,MATCH(64,Engine!$C$2:$C$622,0))) | F77: =IF(ISNA(MATCH(64,Engine!$C$2:$C$622,0)),"",INDEX('Compliance Database'!$F$2:$F$622,MATCH(64,Engine!$C$2:$C$622,0))) | G77: =IF(ISNA(MATCH(64,Engine!$C$2:$C$622,0)),"",INDEX('Compliance Database'!$G$2:$G$622,MATCH(64,Engine!$C$2:$C$622,0))) | H77: =IF(ISNA(MATCH(64,Engine!$C$2:$C$622,0)),"",INDEX('Compliance Database'!$H$2:$H$622,MATCH(64,Engine!$C$2:$C$622,0))) | I77: =IF(ISNA(MATCH(64,Engine!$C$2:$C$622,0)),"",INDEX('Compliance Database'!$I$2:$I$622,MATCH(64,Engine!$C$2:$C$622,0))) | J77: =IF(ISNA(MATCH(64,Engine!$C$2:$C$622,0)),"",INDEX('Compliance Database'!$J$2:$J$622,MATCH(64,Engine!$C$2:$C$622,0))) | K77: =IF(ISNA(MATCH(64,Engine!$C$2:$C$622,0)),"",INDEX('Compliance Database'!$K$2:$K$622,MATCH(64,Engine!$C$2:$C$622,0))) | L77: =IF(ISNA(MATCH(64,Engine!$C$2:$C$622,0)),"",INDEX('Compliance Database'!$L$2:$L$622,MATCH(64,Engine!$C$2:$C$622,0))) | M77: =IF(ISNA(MATCH(64,Engine!$C$2:$C$622,0)),"",INDEX('Compliance Database'!$M$2:$M$622,MATCH(64,Engine!$C$2:$C$622,0))) | N77: =IF(ISNA(MATCH(64,Engine!$C$2:$C$622,0)),"",INDEX('Compliance Database'!$N$2:$N$622,MATCH(64,Engine!$C$2:$C$622,0))) | O77: =IF(ISNA(MATCH(64,Engine!$C$2:$C$622,0)),"",INDEX('Compliance Database'!$O$2:$O$622,MATCH(64,Engine!$C$2:$C$622,0)))
A78: =IF(ISNA(MATCH(65,Engine!$C$2:$C$622,0)),"",INDEX('Compliance Database'!$A$2:$A$622,MATCH(65,Engine!$C$2:$C$622,0))) | B78: =IF(ISNA(MATCH(65,Engine!$C$2:$C$622,0)),"",INDEX('Compliance Database'!$B$2:$B$622,MATCH(65,Engine!$C$2:$C$622,0))) | C78: =IF(ISNA(MATCH(65,Engine!$C$2:$C$622,0)),"",INDEX('Compliance Database'!$C$2:$C$622,MATCH(65,Engine!$C$2:$C$622,0))) | D78: =IF(ISNA(MATCH(65,Engine!$C$2:$C$622,0)),"",INDEX('Compliance Database'!$D$2:$D$622,MATCH(65,Engine!$C$2:$C$622,0))) | E78: =IF(ISNA(MATCH(65,Engine!$C$2:$C$622,0)),"",INDEX('Compliance Database'!$E$2:$E$622,MATCH(65,Engine!$C$2:$C$622,0))) | F78: =IF(ISNA(MATCH(65,Engine!$C$2:$C$622,0)),"",INDEX('Compliance Database'!$F$2:$F$622,MATCH(65,Engine!$C$2:$C$622,0))) | G78: =IF(ISNA(MATCH(65,Engine!$C$2:$C$622,0)),"",INDEX('Compliance Database'!$G$2:$G$622,MATCH(65,Engine!$C$2:$C$622,0))) | H78: =IF(ISNA(MATCH(65,Engine!$C$2:$C$622,0)),"",INDEX('Compliance Database'!$H$2:$H$622,MATCH(65,Engine!$C$2:$C$622,0))) | I78: =IF(ISNA(MATCH(65,Engine!$C$2:$C$622,0)),"",INDEX('Compliance Database'!$I$2:$I$622,MATCH(65,Engine!$C$2:$C$622,0))) | J78: =IF(ISNA(MATCH(65,Engine!$C$2:$C$622,0)),"",INDEX('Compliance Database'!$J$2:$J$622,MATCH(65,Engine!$C$2:$C$622,0))) | K78: =IF(ISNA(MATCH(65,Engine!$C$2:$C$622,0)),"",INDEX('Compliance Database'!$K$2:$K$622,MATCH(65,Engine!$C$2:$C$622,0))) | L78: =IF(ISNA(MATCH(65,Engine!$C$2:$C$622,0)),"",INDEX('Compliance Database'!$L$2:$L$622,MATCH(65,Engine!$C$2:$C$622,0))) | M78: =IF(ISNA(MATCH(65,Engine!$C$2:$C$622,0)),"",INDEX('Compliance Database'!$M$2:$M$622,MATCH(65,Engine!$C$2:$C$622,0))) | N78: =IF(ISNA(MATCH(65,Engine!$C$2:$C$622,0)),"",INDEX('Compliance Database'!$N$2:$N$622,MATCH(65,Engine!$C$2:$C$622,0))) | O78: =IF(ISNA(MATCH(65,Engine!$C$2:$C$622,0)),"",INDEX('Compliance Database'!$O$2:$O$622,MATCH(65,Engine!$C$2:$C$622,0)))
A79: =IF(ISNA(MATCH(66,Engine!$C$2:$C$622,0)),"",INDEX('Compliance Database'!$A$2:$A$622,MATCH(66,Engine!$C$2:$C$622,0))) | B79: =IF(ISNA(MATCH(66,Engine!$C$2:$C$622,0)),"",INDEX('Compliance Database'!$B$2:$B$622,MATCH(66,Engine!$C$2:$C$622,0))) | C79: =IF(ISNA(MATCH(66,Engine!$C$2:$C$622,0)),"",INDEX('Compliance Database'!$C$2:$C$622,MATCH(66,Engine!$C$2:$C$622,0))) | D79: =IF(ISNA(MATCH(66,Engine!$C$2:$C$622,0)),"",INDEX('Compliance Database'!$D$2:$D$622,MATCH(66,Engine!$C$2:$C$622,0))) | E79: =IF(ISNA(MATCH(66,Engine!$C$2:$C$622,0)),"",INDEX('Compliance Database'!$E$2:$E$622,MATCH(66,Engine!$C$2:$C$622,0))) | F79: =IF(ISNA(MATCH(66,Engine!$C$2:$C$622,0)),"",INDEX('Compliance Database'!$F$2:$F$622,MATCH(66,Engine!$C$2:$C$622,0))) | G79: =IF(ISNA(MATCH(66,Engine!$C$2:$C$622,0)),"",INDEX('Compliance Database'!$G$2:$G$622,MATCH(66,Engine!$C$2:$C$622,0))) | H79: =IF(ISNA(MATCH(66,Engine!$C$2:$C$622,0)),"",INDEX('Compliance Database'!$H$2:$H$622,MATCH(66,Engine!$C$2:$C$622,0))) | I79: =IF(ISNA(MATCH(66,Engine!$C$2:$C$622,0)),"",INDEX('Compliance Database'!$I$2:$I$622,MATCH(66,Engine!$C$2:$C$622,0))) | J79: =IF(ISNA(MATCH(66,Engine!$C$2:$C$622,0)),"",INDEX('Compliance Database'!$J$2:$J$622,MATCH(66,Engine!$C$2:$C$622,0))) | K79: =IF(ISNA(MATCH(66,Engine!$C$2:$C$622,0)),"",INDEX('Compliance Database'!$K$2:$K$622,MATCH(66,Engine!$C$2:$C$622,0))) | L79: =IF(ISNA(MATCH(66,Engine!$C$2:$C$622,0)),"",INDEX('Compliance Database'!$L$2:$L$622,MATCH(66,Engine!$C$2:$C$622,0))) | M79: =IF(ISNA(MATCH(66,Engine!$C$2:$C$622,0)),"",INDEX('Compliance Database'!$M$2:$M$622,MATCH(66,Engine!$C$2:$C$622,0))) | N79: =IF(ISNA(MATCH(66,Engine!$C$2:$C$622,0)),"",INDEX('Compliance Database'!$N$2:$N$622,MATCH(66,Engine!$C$2:$C$622,0))) | O79: =IF(ISNA(MATCH(66,Engine!$C$2:$C$622,0)),"",INDEX('Compliance Database'!$O$2:$O$622,MATCH(66,Engine!$C$2:$C$622,0)))
A80: =IF(ISNA(MATCH(67,Engine!$C$2:$C$622,0)),"",INDEX('Compliance Database'!$A$2:$A$622,MATCH(67,Engine!$C$2:$C$622,0))) | B80: =IF(ISNA(MATCH(67,Engine!$C$2:$C$622,0)),"",INDEX('Compliance Database'!$B$2:$B$622,MATCH(67,Engine!$C$2:$C$622,0))) | C80: =IF(ISNA(MATCH(67,Engine!$C$2:$C$622,0)),"",INDEX('Compliance Database'!$C$2:$C$622,MATCH(67,Engine!$C$2:$C$622,0))) | D80: =IF(ISNA(MATCH(67,Engine!$C$2:$C$622,0)),"",INDEX('Compliance Database'!$D$2:$D$622,MATCH(67,Engine!$C$2:$C$622,0))) | E80: =IF(ISNA(MATCH(67,Engine!$C$2:$C$622,0)),"",INDEX('Compliance Database'!$E$2:$E$622,MATCH(67,Engine!$C$2:$C$622,0))) | F80: =IF(ISNA(MATCH(67,Engine!$C$2:$C$622,0)),"",INDEX('Compliance Database'!$F$2:$F$622,MATCH(67,Engine!$C$2:$C$622,0))) | G80: =IF(ISNA(MATCH(67,Engine!$C$2:$C$622,0)),"",INDEX('Compliance Database'!$G$2:$G$622,MATCH(67,Engine!$C$2:$C$622,0))) | H80: =IF(ISNA(MATCH(67,Engine!$C$2:$C$622,0)),"",INDEX('Compliance Database'!$H$2:$H$622,MATCH(67,Engine!$C$2:$C$622,0))) | I80: =IF(ISNA(MATCH(67,Engine!$C$2:$C$622,0)),"",INDEX('Compliance Database'!$I$2:$I$622,MATCH(67,Engine!$C$2:$C$622,0))) | J80: =IF(ISNA(MATCH(67,Engine!$C$2:$C$622,0)),"",INDEX('Compliance Database'!$J$2:$J$622,MATCH(67,Engine!$C$2:$C$622,0))) | K80: =IF(ISNA(MATCH(67,Engine!$C$2:$C$622,0)),"",INDEX('Compliance Database'!$K$2:$K$622,MATCH(67,Engine!$C$2:$C$622,0))) | L80: =IF(ISNA(MATCH(67,Engine!$C$2:$C$622,0)),"",INDEX('Compliance Database'!$L$2:$L$622,MATCH(67,Engine!$C$2:$C$622,0))) | M80: =IF(ISNA(MATCH(67,Engine!$C$2:$C$622,0)),"",INDEX('Compliance Database'!$M$2:$M$622,MATCH(67,Engine!$C$2:$C$622,0))) | N80: =IF(ISNA(MATCH(67,Engine!$C$2:$C$622,0)),"",INDEX('Compliance Database'!$N$2:$N$622,MATCH(67,Engine!$C$2:$C$622,0))) | O80: =IF(ISNA(MATCH(67,Engine!$C$2:$C$622,0)),"",INDEX('Compliance Database'!$O$2:$O$622,MATCH(67,Engine!$C$2:$C$622,0)))
A81: =IF(ISNA(MATCH(68,Engine!$C$2:$C$622,0)),"",INDEX('Compliance Database'!$A$2:$A$622,MATCH(68,Engine!$C$2:$C$622,0))) | B81: =IF(ISNA(MATCH(68,Engine!$C$2:$C$622,0)),"",INDEX('Compliance Database'!$B$2:$B$622,MATCH(68,Engine!$C$2:$C$622,0))) | C81: =IF(ISNA(MATCH(68,Engine!$C$2:$C$622,0)),"",INDEX('Compliance Database'!$C$2:$C$622,MATCH(68,Engine!$C$2:$C$622,0))) | D81: =IF(ISNA(MATCH(68,Engine!$C$2:$C$622,0)),"",INDEX('Compliance Database'!$D$2:$D$622,MATCH(68,Engine!$C$2:$C$622,0))) | E81: =IF(ISNA(MATCH(68,Engine!$C$2:$C$622,0)),"",INDEX('Compliance Database'!$E$2:$E$622,MATCH(68,Engine!$C$2:$C$622,0))) | F81: =IF(ISNA(MATCH(68,Engine!$C$2:$C$622,0)),"",INDEX('Compliance Database'!$F$2:$F$622,MATCH(68,Engine!$C$2:$C$622,0))) | G81: =IF(ISNA(MATCH(68,Engine!$C$2:$C$622,0)),"",INDEX('Compliance Database'!$G$2:$G$622,MATCH(68,Engine!$C$2:$C$622,0))) | H81: =IF(ISNA(MATCH(68,Engine!$C$2:$C$622,0)),"",INDEX('Compliance Database'!$H$2:$H$622,MATCH(68,Engine!$C$2:$C$622,0))) | I81: =IF(ISNA(MATCH(68,Engine!$C$2:$C$622,0)),"",INDEX('Compliance Database'!$I$2:$I$622,MATCH(68,Engine!$C$2:$C$622,0))) | J81: =IF(ISNA(MATCH(68,Engine!$C$2:$C$622,0)),"",INDEX('Compliance Database'!$J$2:$J$622,MATCH(68,Engine!$C$2:$C$622,0))) | K81: =IF(ISNA(MATCH(68,Engine!$C$2:$C$622,0)),"",INDEX('Compliance Database'!$K$2:$K$622,MATCH(68,Engine!$C$2:$C$622,0))) | L81: =IF(ISNA(MATCH(68,Engine!$C$2:$C$622,0)),"",INDEX('Compliance Database'!$L$2:$L$622,MATCH(68,Engine!$C$2:$C$622,0))) | M81: =IF(ISNA(MATCH(68,Engine!$C$2:$C$622,0)),"",INDEX('Compliance Database'!$M$2:$M$622,MATCH(68,Engine!$C$2:$C$622,0))) | N81: =IF(ISNA(MATCH(68,Engine!$C$2:$C$622,0)),"",INDEX('Compliance Database'!$N$2:$N$622,MATCH(68,Engine!$C$2:$C$622,0))) | O81: =IF(ISNA(MATCH(68,Engine!$C$2:$C$622,0)),"",INDEX('Compliance Database'!$O$2:$O$622,MATCH(68,Engine!$C$2:$C$622,0)))
A82: =IF(ISNA(MATCH(69,Engine!$C$2:$C$622,0)),"",INDEX('Compliance Database'!$A$2:$A$622,MATCH(69,Engine!$C$2:$C$622,0))) | B82: =IF(ISNA(MATCH(69,Engine!$C$2:$C$622,0)),"",INDEX('Compliance Database'!$B$2:$B$622,MATCH(69,Engine!$C$2:$C$622,0))) | C82: =IF(ISNA(MATCH(69,Engine!$C$2:$C$622,0)),"",INDEX('Compliance Database'!$C$2:$C$622,MATCH(69,Engine!$C$2:$C$622,0))) | D82: =IF(ISNA(MATCH(69,Engine!$C$2:$C$622,0)),"",INDEX('Compliance Database'!$D$2:$D$622,MATCH(69,Engine!$C$2:$C$622,0))) | E82: =IF(ISNA(MATCH(69,Engine!$C$2:$C$622,0)),"",INDEX('Compliance Database'!$E$2:$E$622,MATCH(69,Engine!$C$2:$C$622,0))) | F82: =IF(ISNA(MATCH(69,Engine!$C$2:$C$622,0)),"",INDEX('Compliance Database'!$F$2:$F$622,MATCH(69,Engine!$C$2:$C$622,0))) | G82: =IF(ISNA(MATCH(69,Engine!$C$2:$C$622,0)),"",INDEX('Compliance Database'!$G$2:$G$622,MATCH(69,Engine!$C$2:$C$622,0))) | H82: =IF(ISNA(MATCH(69,Engine!$C$2:$C$622,0)),"",INDEX('Compliance Database'!$H$2:$H$622,MATCH(69,Engine!$C$2:$C$622,0))) | I82: =IF(ISNA(MATCH(69,Engine!$C$2:$C$622,0)),"",INDEX('Compliance Database'!$I$2:$I$622,MATCH(69,Engine!$C$2:$C$622,0))) | J82: =IF(ISNA(MATCH(69,Engine!$C$2:$C$622,0)),"",INDEX('Compliance Database'!$J$2:$J$622,MATCH(69,Engine!$C$2:$C$622,0))) | K82: =IF(ISNA(MATCH(69,Engine!$C$2:$C$622,0)),"",INDEX('Compliance Database'!$K$2:$K$622,MATCH(69,Engine!$C$2:$C$622,0))) | L82: =IF(ISNA(MATCH(69,Engine!$C$2:$C$622,0)),"",INDEX('Compliance Database'!$L$2:$L$622,MATCH(69,Engine!$C$2:$C$622,0))) | M82: =IF(ISNA(MATCH(69,Engine!$C$2:$C$622,0)),"",INDEX('Compliance Database'!$M$2:$M$622,MATCH(69,Engine!$C$2:$C$622,0))) | N82: =IF(ISNA(MATCH(69,Engine!$C$2:$C$622,0)),"",INDEX('Compliance Database'!$N$2:$N$622,MATCH(69,Engine!$C$2:$C$622,0))) | O82: =IF(ISNA(MATCH(69,Engine!$C$2:$C$622,0)),"",INDEX('Compliance Database'!$O$2:$O$622,MATCH(69,Engine!$C$2:$C$622,0)))
A83: =IF(ISNA(MATCH(70,Engine!$C$2:$C$622,0)),"",INDEX('Compliance Database'!$A$2:$A$622,MATCH(70,Engine!$C$2:$C$622,0))) | B83: =IF(ISNA(MATCH(70,Engine!$C$2:$C$622,0)),"",INDEX('Compliance Database'!$B$2:$B$622,MATCH(70,Engine!$C$2:$C$622,0))) | C83: =IF(ISNA(MATCH(70,Engine!$C$2:$C$622,0)),"",INDEX('Compliance Database'!$C$2:$C$622,MATCH(70,Engine!$C$2:$C$622,0))) | D83: =IF(ISNA(MATCH(70,Engine!$C$2:$C$622,0)),"",INDEX('Compliance Database'!$D$2:$D$622,MATCH(70,Engine!$C$2:$C$622,0))) | E83: =IF(ISNA(MATCH(70,Engine!$C$2:$C$622,0)),"",INDEX('Compliance Database'!$E$2:$E$622,MATCH(70,Engine!$C$2:$C$622,0))) | F83: =IF(ISNA(MATCH(70,Engine!$C$2:$C$622,0)),"",INDEX('Compliance Database'!$F$2:$F$622,MATCH(70,Engine!$C$2:$C$622,0))) | G83: =IF(ISNA(MATCH(70,Engine!$C$2:$C$622,0)),"",INDEX('Compliance Database'!$G$2:$G$622,MATCH(70,Engine!$C$2:$C$622,0))) | H83: =IF(ISNA(MATCH(70,Engine!$C$2:$C$622,0)),"",INDEX('Compliance Database'!$H$2:$H$622,MATCH(70,Engine!$C$2:$C$622,0))) | I83: =IF(ISNA(MATCH(70,Engine!$C$2:$C$622,0)),"",INDEX('Compliance Database'!$I$2:$I$622,MATCH(70,Engine!$C$2:$C$622,0))) | J83: =IF(ISNA(MATCH(70,Engine!$C$2:$C$622,0)),"",INDEX('Compliance Database'!$J$2:$J$622,MATCH(70,Engine!$C$2:$C$622,0))) | K83: =IF(ISNA(MATCH(70,Engine!$C$2:$C$622,0)),"",INDEX('Compliance Database'!$K$2:$K$622,MATCH(70,Engine!$C$2:$C$622,0))) | L83: =IF(ISNA(MATCH(70,Engine!$C$2:$C$622,0)),"",INDEX('Compliance Database'!$L$2:$L$622,MATCH(70,Engine!$C$2:$C$622,0))) | M83: =IF(ISNA(MATCH(70,Engine!$C$2:$C$622,0)),"",INDEX('Compliance Database'!$M$2:$M$622,MATCH(70,Engine!$C$2:$C$622,0))) | N83: =IF(ISNA(MATCH(70,Engine!$C$2:$C$622,0)),"",INDEX('Compliance Database'!$N$2:$N$622,MATCH(70,Engine!$C$2:$C$622,0))) | O83: =IF(ISNA(MATCH(70,Engine!$C$2:$C$622,0)),"",INDEX('Compliance Database'!$O$2:$O$622,MATCH(70,Engine!$C$2:$C$622,0)))
A84: =IF(ISNA(MATCH(71,Engine!$C$2:$C$622,0)),"",INDEX('Compliance Database'!$A$2:$A$622,MATCH(71,Engine!$C$2:$C$622,0))) | B84: =IF(ISNA(MATCH(71,Engine!$C$2:$C$622,0)),"",INDEX('Compliance Database'!$B$2:$B$622,MATCH(71,Engine!$C$2:$C$622,0))) | C84: =IF(ISNA(MATCH(71,Engine!$C$2:$C$622,0)),"",INDEX('Compliance Database'!$C$2:$C$622,MATCH(71,Engine!$C$2:$C$622,0))) | D84: =IF(ISNA(MATCH(71,Engine!$C$2:$C$622,0)),"",INDEX('Compliance Database'!$D$2:$D$622,MATCH(71,Engine!$C$2:$C$622,0))) | E84: =IF(ISNA(MATCH(71,Engine!$C$2:$C$622,0)),"",INDEX('Compliance Database'!$E$2:$E$622,MATCH(71,Engine!$C$2:$C$622,0))) | F84: =IF(ISNA(MATCH(71,Engine!$C$2:$C$622,0)),"",INDEX('Compliance Database'!$F$2:$F$622,MATCH(71,Engine!$C$2:$C$622,0))) | G84: =IF(ISNA(MATCH(71,Engine!$C$2:$C$622,0)),"",INDEX('Compliance Database'!$G$2:$G$622,MATCH(71,Engine!$C$2:$C$622,0))) | H84: =IF(ISNA(MATCH(71,Engine!$C$2:$C$622,0)),"",INDEX('Compliance Database'!$H$2:$H$622,MATCH(71,Engine!$C$2:$C$622,0))) | I84: =IF(ISNA(MATCH(71,Engine!$C$2:$C$622,0)),"",INDEX('Compliance Database'!$I$2:$I$622,MATCH(71,Engine!$C$2:$C$622,0))) | J84: =IF(ISNA(MATCH(71,Engine!$C$2:$C$622,0)),"",INDEX('Compliance Database'!$J$2:$J$622,MATCH(71,Engine!$C$2:$C$622,0))) | K84: =IF(ISNA(MATCH(71,Engine!$C$2:$C$622,0)),"",INDEX('Compliance Database'!$K$2:$K$622,MATCH(71,Engine!$C$2:$C$622,0))) | L84: =IF(ISNA(MATCH(71,Engine!$C$2:$C$622,0)),"",INDEX('Compliance Database'!$L$2:$L$622,MATCH(71,Engine!$C$2:$C$622,0))) | M84: =IF(ISNA(MATCH(71,Engine!$C$2:$C$622,0)),"",INDEX('Compliance Database'!$M$2:$M$622,MATCH(71,Engine!$C$2:$C$622,0))) | N84: =IF(ISNA(MATCH(71,Engine!$C$2:$C$622,0)),"",INDEX('Compliance Database'!$N$2:$N$622,MATCH(71,Engine!$C$2:$C$622,0))) | O84: =IF(ISNA(MATCH(71,Engine!$C$2:$C$622,0)),"",INDEX('Compliance Database'!$O$2:$O$622,MATCH(71,Engine!$C$2:$C$622,0)))
A85: =IF(ISNA(MATCH(72,Engine!$C$2:$C$622,0)),"",INDEX('Compliance Database'!$A$2:$A$622,MATCH(72,Engine!$C$2:$C$622,0))) | B85: =IF(ISNA(MATCH(72,Engine!$C$2:$C$622,0)),"",INDEX('Compliance Database'!$B$2:$B$622,MATCH(72,Engine!$C$2:$C$622,0))) | C85: =IF(ISNA(MATCH(72,Engine!$C$2:$C$622,0)),"",INDEX('Compliance Database'!$C$2:$C$622,MATCH(72,Engine!$C$2:$C$622,0))) | D85: =IF(ISNA(MATCH(72,Engine!$C$2:$C$622,0)),"",INDEX('Compliance Database'!$D$2:$D$622,MATCH(72,Engine!$C$2:$C$622,0))) | E85: =IF(ISNA(MATCH(72,Engine!$C$2:$C$622,0)),"",INDEX('Compliance Database'!$E$2:$E$622,MATCH(72,Engine!$C$2:$C$622,0))) | F85: =IF(ISNA(MATCH(72,Engine!$C$2:$C$622,0)),"",INDEX('Compliance Database'!$F$2:$F$622,MATCH(72,Engine!$C$2:$C$622,0))) | G85: =IF(ISNA(MATCH(72,Engine!$C$2:$C$622,0)),"",INDEX('Compliance Database'!$G$2:$G$622,MATCH(72,Engine!$C$2:$C$622,0))) | H85: =IF(ISNA(MATCH(72,Engine!$C$2:$C$622,0)),"",INDEX('Compliance Database'!$H$2:$H$622,MATCH(72,Engine!$C$2:$C$622,0))) | I85: =IF(ISNA(MATCH(72,Engine!$C$2:$C$622,0)),"",INDEX('Compliance Database'!$I$2:$I$622,MATCH(72,Engine!$C$2:$C$622,0))) | J85: =IF(ISNA(MATCH(72,Engine!$C$2:$C$622,0)),"",INDEX('Compliance Database'!$J$2:$J$622,MATCH(72,Engine!$C$2:$C$622,0))) | K85: =IF(ISNA(MATCH(72,Engine!$C$2:$C$622,0)),"",INDEX('Compliance Database'!$K$2:$K$622,MATCH(72,Engine!$C$2:$C$622,0))) | L85: =IF(ISNA(MATCH(72,Engine!$C$2:$C$622,0)),"",INDEX('Compliance Database'!$L$2:$L$622,MATCH(72,Engine!$C$2:$C$622,0))) | M85: =IF(ISNA(MATCH(72,Engine!$C$2:$C$622,0)),"",INDEX('Compliance Database'!$M$2:$M$622,MATCH(72,Engine!$C$2:$C$622,0))) | N85: =IF(ISNA(MATCH(72,Engine!$C$2:$C$622,0)),"",INDEX('Compliance Database'!$N$2:$N$622,MATCH(72,Engine!$C$2:$C$622,0))) | O85: =IF(ISNA(MATCH(72,Engine!$C$2:$C$622,0)),"",INDEX('Compliance Database'!$O$2:$O$622,MATCH(72,Engine!$C$2:$C$622,0)))
A86: =IF(ISNA(MATCH(73,Engine!$C$2:$C$622,0)),"",INDEX('Compliance Database'!$A$2:$A$622,MATCH(73,Engine!$C$2:$C$622,0))) | B86: =IF(ISNA(MATCH(73,Engine!$C$2:$C$622,0)),"",INDEX('Compliance Database'!$B$2:$B$622,MATCH(73,Engine!$C$2:$C$622,0))) | C86: =IF(ISNA(MATCH(73,Engine!$C$2:$C$622,0)),"",INDEX('Compliance Database'!$C$2:$C$622,MATCH(73,Engine!$C$2:$C$622,0))) | D86: =IF(ISNA(MATCH(73,Engine!$C$2:$C$622,0)),"",INDEX('Compliance Database'!$D$2:$D$622,MATCH(73,Engine!$C$2:$C$622,0))) | E86: =IF(ISNA(MATCH(73,Engine!$C$2:$C$622,0)),"",INDEX('Compliance Database'!$E$2:$E$622,MATCH(73,Engine!$C$2:$C$622,0))) | F86: =IF(ISNA(MATCH(73,Engine!$C$2:$C$622,0)),"",INDEX('Compliance Database'!$F$2:$F$622,MATCH(73,Engine!$C$2:$C$622,0))) | G86: =IF(ISNA(MATCH(73,Engine!$C$2:$C$622,0)),"",INDEX('Compliance Database'!$G$2:$G$622,MATCH(73,Engine!$C$2:$C$622,0))) | H86: =IF(ISNA(MATCH(73,Engine!$C$2:$C$622,0)),"",INDEX('Compliance Database'!$H$2:$H$622,MATCH(73,Engine!$C$2:$C$622,0))) | I86: =IF(ISNA(MATCH(73,Engine!$C$2:$C$622,0)),"",INDEX('Compliance Database'!$I$2:$I$622,MATCH(73,Engine!$C$2:$C$622,0))) | J86: =IF(ISNA(MATCH(73,Engine!$C$2:$C$622,0)),"",INDEX('Compliance Database'!$J$2:$J$622,MATCH(73,Engine!$C$2:$C$622,0))) | K86: =IF(ISNA(MATCH(73,Engine!$C$2:$C$622,0)),"",INDEX('Compliance Database'!$K$2:$K$622,MATCH(73,Engine!$C$2:$C$622,0))) | L86: =IF(ISNA(MATCH(73,Engine!$C$2:$C$622,0)),"",INDEX('Compliance Database'!$L$2:$L$622,MATCH(73,Engine!$C$2:$C$622,0))) | M86: =IF(ISNA(MATCH(73,Engine!$C$2:$C$622,0)),"",INDEX('Compliance Database'!$M$2:$M$622,MATCH(73,Engine!$C$2:$C$622,0))) | N86: =IF(ISNA(MATCH(73,Engine!$C$2:$C$622,0)),"",INDEX('Compliance Database'!$N$2:$N$622,MATCH(73,Engine!$C$2:$C$622,0))) | O86: =IF(ISNA(MATCH(73,Engine!$C$2:$C$622,0)),"",INDEX('Compliance Database'!$O$2:$O$622,MATCH(73,Engine!$C$2:$C$622,0)))
A87: =IF(ISNA(MATCH(74,Engine!$C$2:$C$622,0)),"",INDEX('Compliance Database'!$A$2:$A$622,MATCH(74,Engine!$C$2:$C$622,0))) | B87: =IF(ISNA(MATCH(74,Engine!$C$2:$C$622,0)),"",INDEX('Compliance Database'!$B$2:$B$622,MATCH(74,Engine!$C$2:$C$622,0))) | C87: =IF(ISNA(MATCH(74,Engine!$C$2:$C$622,0)),"",INDEX('Compliance Database'!$C$2:$C$622,MATCH(74,Engine!$C$2:$C$622,0))) | D87: =IF(ISNA(MATCH(74,Engine!$C$2:$C$622,0)),"",INDEX('Compliance Database'!$D$2:$D$622,MATCH(74,Engine!$C$2:$C$622,0))) | E87: =IF(ISNA(MATCH(74,Engine!$C$2:$C$622,0)),"",INDEX('Compliance Database'!$E$2:$E$622,MATCH(74,Engine!$C$2:$C$622,0))) | F87: =IF(ISNA(MATCH(74,Engine!$C$2:$C$622,0)),"",INDEX('Compliance Database'!$F$2:$F$622,MATCH(74,Engine!$C$2:$C$622,0))) | G87: =IF(ISNA(MATCH(74,Engine!$C$2:$C$622,0)),"",INDEX('Compliance Database'!$G$2:$G$622,MATCH(74,Engine!$C$2:$C$622,0))) | H87: =IF(ISNA(MATCH(74,Engine!$C$2:$C$622,0)),"",INDEX('Compliance Database'!$H$2:$H$622,MATCH(74,Engine!$C$2:$C$622,0))) | I87: =IF(ISNA(MATCH(74,Engine!$C$2:$C$622,0)),"",INDEX('Compliance Database'!$I$2:$I$622,MATCH(74,Engine!$C$2:$C$622,0))) | J87: =IF(ISNA(MATCH(74,Engine!$C$2:$C$622,0)),"",INDEX('Compliance Database'!$J$2:$J$622,MATCH(74,Engine!$C$2:$C$622,0))) | K87: =IF(ISNA(MATCH(74,Engine!$C$2:$C$622,0)),"",INDEX('Compliance Database'!$K$2:$K$622,MATCH(74,Engine!$C$2:$C$622,0))) | L87: =IF(ISNA(MATCH(74,Engine!$C$2:$C$622,0)),"",INDEX('Compliance Database'!$L$2:$L$622,MATCH(74,Engine!$C$2:$C$622,0))) | M87: =IF(ISNA(MATCH(74,Engine!$C$2:$C$622,0)),"",INDEX('Compliance Database'!$M$2:$M$622,MATCH(74,Engine!$C$2:$C$622,0))) | N87: =IF(ISNA(MATCH(74,Engine!$C$2:$C$622,0)),"",INDEX('Compliance Database'!$N$2:$N$622,MATCH(74,Engine!$C$2:$C$622,0))) | O87: =IF(ISNA(MATCH(74,Engine!$C$2:$C$622,0)),"",INDEX('Compliance Database'!$O$2:$O$622,MATCH(74,Engine!$C$2:$C$622,0)))
A88: =IF(ISNA(MATCH(75,Engine!$C$2:$C$622,0)),"",INDEX('Compliance Database'!$A$2:$A$622,MATCH(75,Engine!$C$2:$C$622,0))) | B88: =IF(ISNA(MATCH(75,Engine!$C$2:$C$622,0)),"",INDEX('Compliance Database'!$B$2:$B$622,MATCH(75,Engine!$C$2:$C$622,0))) | C88: =IF(ISNA(MATCH(75,Engine!$C$2:$C$622,0)),"",INDEX('Compliance Database'!$C$2:$C$622,MATCH(75,Engine!$C$2:$C$622,0))) | D88: =IF(ISNA(MATCH(75,Engine!$C$2:$C$622,0)),"",INDEX('Compliance Database'!$D$2:$D$622,MATCH(75,Engine!$C$2:$C$622,0))) | E88: =IF(ISNA(MATCH(75,Engine!$C$2:$C$622,0)),"",INDEX('Compliance Database'!$E$2:$E$622,MATCH(75,Engine!$C$2:$C$622,0))) | F88: =IF(ISNA(MATCH(75,Engine!$C$2:$C$622,0)),"",INDEX('Compliance Database'!$F$2:$F$622,MATCH(75,Engine!$C$2:$C$622,0))) | G88: =IF(ISNA(MATCH(75,Engine!$C$2:$C$622,0)),"",INDEX('Compliance Database'!$G$2:$G$622,MATCH(75,Engine!$C$2:$C$622,0))) | H88: =IF(ISNA(MATCH(75,Engine!$C$2:$C$622,0)),"",INDEX('Compliance Database'!$H$2:$H$622,MATCH(75,Engine!$C$2:$C$622,0))) | I88: =IF(ISNA(MATCH(75,Engine!$C$2:$C$622,0)),"",INDEX('Compliance Database'!$I$2:$I$622,MATCH(75,Engine!$C$2:$C$622,0))) | J88: =IF(ISNA(MATCH(75,Engine!$C$2:$C$622,0)),"",INDEX('Compliance Database'!$J$2:$J$622,MATCH(75,Engine!$C$2:$C$622,0))) | K88: =IF(ISNA(MATCH(75,Engine!$C$2:$C$622,0)),"",INDEX('Compliance Database'!$K$2:$K$622,MATCH(75,Engine!$C$2:$C$622,0))) | L88: =IF(ISNA(MATCH(75,Engine!$C$2:$C$622,0)),"",INDEX('Compliance Database'!$L$2:$L$622,MATCH(75,Engine!$C$2:$C$622,0))) | M88: =IF(ISNA(MATCH(75,Engine!$C$2:$C$622,0)),"",INDEX('Compliance Database'!$M$2:$M$622,MATCH(75,Engine!$C$2:$C$622,0))) | N88: =IF(ISNA(MATCH(75,Engine!$C$2:$C$622,0)),"",INDEX('Compliance Database'!$N$2:$N$622,MATCH(75,Engine!$C$2:$C$622,0))) | O88: =IF(ISNA(MATCH(75,Engine!$C$2:$C$622,0)),"",INDEX('Compliance Database'!$O$2:$O$622,MATCH(75,Engine!$C$2:$C$622,0)))
A89: =IF(ISNA(MATCH(76,Engine!$C$2:$C$622,0)),"",INDEX('Compliance Database'!$A$2:$A$622,MATCH(76,Engine!$C$2:$C$622,0))) | B89: =IF(ISNA(MATCH(76,Engine!$C$2:$C$622,0)),"",INDEX('Compliance Database'!$B$2:$B$622,MATCH(76,Engine!$C$2:$C$622,0))) | C89: =IF(ISNA(MATCH(76,Engine!$C$2:$C$622,0)),"",INDEX('Compliance Database'!$C$2:$C$622,MATCH(76,Engine!$C$2:$C$622,0))) | D89: =IF(ISNA(MATCH(76,Engine!$C$2:$C$622,0)),"",INDEX('Compliance Database'!$D$2:$D$622,MATCH(76,Engine!$C$2:$C$622,0))) | E89: =IF(ISNA(MATCH(76,Engine!$C$2:$C$622,0)),"",INDEX('Compliance Database'!$E$2:$E$622,MATCH(76,Engine!$C$2:$C$622,0))) | F89: =IF(ISNA(MATCH(76,Engine!$C$2:$C$622,0)),"",INDEX('Compliance Database'!$F$2:$F$622,MATCH(76,Engine!$C$2:$C$622,0))) | G89: =IF(ISNA(MATCH(76,Engine!$C$2:$C$622,0)),"",INDEX('Compliance Database'!$G$2:$G$622,MATCH(76,Engine!$C$2:$C$622,0))) | H89: =IF(ISNA(MATCH(76,Engine!$C$2:$C$622,0)),"",INDEX('Compliance Database'!$H$2:$H$622,MATCH(76,Engine!$C$2:$C$622,0))) | I89: =IF(ISNA(MATCH(76,Engine!$C$2:$C$622,0)),"",INDEX('Compliance Database'!$I$2:$I$622,MATCH(76,Engine!$C$2:$C$622,0))) | J89: =IF(ISNA(MATCH(76,Engine!$C$2:$C$622,0)),"",INDEX('Compliance Database'!$J$2:$J$622,MATCH(76,Engine!$C$2:$C$622,0))) | K89: =IF(ISNA(MATCH(76,Engine!$C$2:$C$622,0)),"",INDEX('Compliance Database'!$K$2:$K$622,MATCH(76,Engine!$C$2:$C$622,0))) | L89: =IF(ISNA(MATCH(76,Engine!$C$2:$C$622,0)),"",INDEX('Compliance Database'!$L$2:$L$622,MATCH(76,Engine!$C$2:$C$622,0))) | M89: =IF(ISNA(MATCH(76,Engine!$C$2:$C$622,0)),"",INDEX('Compliance Database'!$M$2:$M$622,MATCH(76,Engine!$C$2:$C$622,0))) | N89: =IF(ISNA(MATCH(76,Engine!$C$2:$C$622,0)),"",INDEX('Compliance Database'!$N$2:$N$622,MATCH(76,Engine!$C$2:$C$622,0))) | O89: =IF(ISNA(MATCH(76,Engine!$C$2:$C$622,0)),"",INDEX('Compliance Database'!$O$2:$O$622,MATCH(76,Engine!$C$2:$C$622,0)))
A90: =IF(ISNA(MATCH(77,Engine!$C$2:$C$622,0)),"",INDEX('Compliance Database'!$A$2:$A$622,MATCH(77,Engine!$C$2:$C$622,0))) | B90: =IF(ISNA(MATCH(77,Engine!$C$2:$C$622,0)),"",INDEX('Compliance Database'!$B$2:$B$622,MATCH(77,Engine!$C$2:$C$622,0))) | C90: =IF(ISNA(MATCH(77,Engine!$C$2:$C$622,0)),"",INDEX('Compliance Database'!$C$2:$C$622,MATCH(77,Engine!$C$2:$C$622,0))) | D90: =IF(ISNA(MATCH(77,Engine!$C$2:$C$622,0)),"",INDEX('Compliance Database'!$D$2:$D$622,MATCH(77,Engine!$C$2:$C$622,0))) | E90: =IF(ISNA(MATCH(77,Engine!$C$2:$C$622,0)),"",INDEX('Compliance Database'!$E$2:$E$622,MATCH(77,Engine!$C$2:$C$622,0))) | F90: =IF(ISNA(MATCH(77,Engine!$C$2:$C$622,0)),"",INDEX('Compliance Database'!$F$2:$F$622,MATCH(77,Engine!$C$2:$C$622,0))) | G90: =IF(ISNA(MATCH(77,Engine!$C$2:$C$622,0)),"",INDEX('Compliance Database'!$G$2:$G$622,MATCH(77,Engine!$C$2:$C$622,0))) | H90: =IF(ISNA(MATCH(77,Engine!$C$2:$C$622,0)),"",INDEX('Compliance Database'!$H$2:$H$622,MATCH(77,Engine!$C$2:$C$622,0))) | I90: =IF(ISNA(MATCH(77,Engine!$C$2:$C$622,0)),"",INDEX('Compliance Database'!$I$2:$I$622,MATCH(77,Engine!$C$2:$C$622,0))) | J90: =IF(ISNA(MATCH(77,Engine!$C$2:$C$622,0)),"",INDEX('Compliance Database'!$J$2:$J$622,MATCH(77,Engine!$C$2:$C$622,0))) | K90: =IF(ISNA(MATCH(77,Engine!$C$2:$C$622,0)),"",INDEX('Compliance Database'!$K$2:$K$622,MATCH(77,Engine!$C$2:$C$622,0))) | L90: =IF(ISNA(MATCH(77,Engine!$C$2:$C$622,0)),"",INDEX('Compliance Database'!$L$2:$L$622,MATCH(77,Engine!$C$2:$C$622,0))) | M90: =IF(ISNA(MATCH(77,Engine!$C$2:$C$622,0)),"",INDEX('Compliance Database'!$M$2:$M$622,MATCH(77,Engine!$C$2:$C$622,0))) | N90: =IF(ISNA(MATCH(77,Engine!$C$2:$C$622,0)),"",INDEX('Compliance Database'!$N$2:$N$622,MATCH(77,Engine!$C$2:$C$622,0))) | O90: =IF(ISNA(MATCH(77,Engine!$C$2:$C$622,0)),"",INDEX('Compliance Database'!$O$2:$O$622,MATCH(77,Engine!$C$2:$C$622,0)))
A91: =IF(ISNA(MATCH(78,Engine!$C$2:$C$622,0)),"",INDEX('Compliance Database'!$A$2:$A$622,MATCH(78,Engine!$C$2:$C$622,0))) | B91: =IF(ISNA(MATCH(78,Engine!$C$2:$C$622,0)),"",INDEX('Compliance Database'!$B$2:$B$622,MATCH(78,Engine!$C$2:$C$622,0))) | C91: =IF(ISNA(MATCH(78,Engine!$C$2:$C$622,0)),"",INDEX('Compliance Database'!$C$2:$C$622,MATCH(78,Engine!$C$2:$C$622,0))) | D91: =IF(ISNA(MATCH(78,Engine!$C$2:$C$622,0)),"",INDEX('Compliance Database'!$D$2:$D$622,MATCH(78,Engine!$C$2:$C$622,0))) | E91: =IF(ISNA(MATCH(78,Engine!$C$2:$C$622,0)),"",INDEX('Compliance Database'!$E$2:$E$622,MATCH(78,Engine!$C$2:$C$622,0))) | F91: =IF(ISNA(MATCH(78,Engine!$C$2:$C$622,0)),"",INDEX('Compliance Database'!$F$2:$F$622,MATCH(78,Engine!$C$2:$C$622,0))) | G91: =IF(ISNA(MATCH(78,Engine!$C$2:$C$622,0)),"",INDEX('Compliance Database'!$G$2:$G$622,MATCH(78,Engine!$C$2:$C$622,0))) | H91: =IF(ISNA(MATCH(78,Engine!$C$2:$C$622,0)),"",INDEX('Compliance Database'!$H$2:$H$622,MATCH(78,Engine!$C$2:$C$622,0))) | I91: =IF(ISNA(MATCH(78,Engine!$C$2:$C$622,0)),"",INDEX('Compliance Database'!$I$2:$I$622,MATCH(78,Engine!$C$2:$C$622,0))) | J91: =IF(ISNA(MATCH(78,Engine!$C$2:$C$622,0)),"",INDEX('Compliance Database'!$J$2:$J$622,MATCH(78,Engine!$C$2:$C$622,0))) | K91: =IF(ISNA(MATCH(78,Engine!$C$2:$C$622,0)),"",INDEX('Compliance Database'!$K$2:$K$622,MATCH(78,Engine!$C$2:$C$622,0))) | L91: =IF(ISNA(MATCH(78,Engine!$C$2:$C$622,0)),"",INDEX('Compliance Database'!$L$2:$L$622,MATCH(78,Engine!$C$2:$C$622,0))) | M91: =IF(ISNA(MATCH(78,Engine!$C$2:$C$622,0)),"",INDEX('Compliance Database'!$M$2:$M$622,MATCH(78,Engine!$C$2:$C$622,0))) | N91: =IF(ISNA(MATCH(78,Engine!$C$2:$C$622,0)),"",INDEX('Compliance Database'!$N$2:$N$622,MATCH(78,Engine!$C$2:$C$622,0))) | O91: =IF(ISNA(MATCH(78,Engine!$C$2:$C$622,0)),"",INDEX('Compliance Database'!$O$2:$O$622,MATCH(78,Engine!$C$2:$C$622,0)))
A92: =IF(ISNA(MATCH(79,Engine!$C$2:$C$622,0)),"",INDEX('Compliance Database'!$A$2:$A$622,MATCH(79,Engine!$C$2:$C$622,0))) | B92: =IF(ISNA(MATCH(79,Engine!$C$2:$C$622,0)),"",INDEX('Compliance Database'!$B$2:$B$622,MATCH(79,Engine!$C$2:$C$622,0))) | C92: =IF(ISNA(MATCH(79,Engine!$C$2:$C$622,0)),"",INDEX('Compliance Database'!$C$2:$C$622,MATCH(79,Engine!$C$2:$C$622,0))) | D92: =IF(ISNA(MATCH(79,Engine!$C$2:$C$622,0)),"",INDEX('Compliance Database'!$D$2:$D$622,MATCH(79,Engine!$C$2:$C$622,0))) | E92: =IF(ISNA(MATCH(79,Engine!$C$2:$C$622,0)),"",INDEX('Compliance Database'!$E$2:$E$622,MATCH(79,Engine!$C$2:$C$622,0))) | F92: =IF(ISNA(MATCH(79,Engine!$C$2:$C$622,0)),"",INDEX('Compliance Database'!$F$2:$F$622,MATCH(79,Engine!$C$2:$C$622,0))) | G92: =IF(ISNA(MATCH(79,Engine!$C$2:$C$622,0)),"",INDEX('Compliance Database'!$G$2:$G$622,MATCH(79,Engine!$C$2:$C$622,0))) | H92: =IF(ISNA(MATCH(79,Engine!$C$2:$C$622,0)),"",INDEX('Compliance Database'!$H$2:$H$622,MATCH(79,Engine!$C$2:$C$622,0))) | I92: =IF(ISNA(MATCH(79,Engine!$C$2:$C$622,0)),"",INDEX('Compliance Database'!$I$2:$I$622,MATCH(79,Engine!$C$2:$C$622,0))) | J92: =IF(ISNA(MATCH(79,Engine!$C$2:$C$622,0)),"",INDEX('Compliance Database'!$J$2:$J$622,MATCH(79,Engine!$C$2:$C$622,0))) | K92: =IF(ISNA(MATCH(79,Engine!$C$2:$C$622,0)),"",INDEX('Compliance Database'!$K$2:$K$622,MATCH(79,Engine!$C$2:$C$622,0))) | L92: =IF(ISNA(MATCH(79,Engine!$C$2:$C$622,0)),"",INDEX('Compliance Database'!$L$2:$L$622,MATCH(79,Engine!$C$2:$C$622,0))) | M92: =IF(ISNA(MATCH(79,Engine!$C$2:$C$622,0)),"",INDEX('Compliance Database'!$M$2:$M$622,MATCH(79,Engine!$C$2:$C$622,0))) | N92: =IF(ISNA(MATCH(79,Engine!$C$2:$C$622,0)),"",INDEX('Compliance Database'!$N$2:$N$622,MATCH(79,Engine!$C$2:$C$622,0))) | O92: =IF(ISNA(MATCH(79,Engine!$C$2:$C$622,0)),"",INDEX('Compliance Database'!$O$2:$O$622,MATCH(79,Engine!$C$2:$C$622,0)))
A93: =IF(ISNA(MATCH(80,Engine!$C$2:$C$622,0)),"",INDEX('Compliance Database'!$A$2:$A$622,MATCH(80,Engine!$C$2:$C$622,0))) | B93: =IF(ISNA(MATCH(80,Engine!$C$2:$C$622,0)),"",INDEX('Compliance Database'!$B$2:$B$622,MATCH(80,Engine!$C$2:$C$622,0))) | C93: =IF(ISNA(MATCH(80,Engine!$C$2:$C$622,0)),"",INDEX('Compliance Database'!$C$2:$C$622,MATCH(80,Engine!$C$2:$C$622,0))) | D93: =IF(ISNA(MATCH(80,Engine!$C$2:$C$622,0)),"",INDEX('Compliance Database'!$D$2:$D$622,MATCH(80,Engine!$C$2:$C$622,0))) | E93: =IF(ISNA(MATCH(80,Engine!$C$2:$C$622,0)),"",INDEX('Compliance Database'!$E$2:$E$622,MATCH(80,Engine!$C$2:$C$622,0))) | F93: =IF(ISNA(MATCH(80,Engine!$C$2:$C$622,0)),"",INDEX('Compliance Database'!$F$2:$F$622,MATCH(80,Engine!$C$2:$C$622,0))) | G93: =IF(ISNA(MATCH(80,Engine!$C$2:$C$622,0)),"",INDEX('Compliance Database'!$G$2:$G$622,MATCH(80,Engine!$C$2:$C$622,0))) | H93: =IF(ISNA(MATCH(80,Engine!$C$2:$C$622,0)),"",INDEX('Compliance Database'!$H$2:$H$622,MATCH(80,Engine!$C$2:$C$622,0))) | I93: =IF(ISNA(MATCH(80,Engine!$C$2:$C$622,0)),"",INDEX('Compliance Database'!$I$2:$I$622,MATCH(80,Engine!$C$2:$C$622,0))) | J93: =IF(ISNA(MATCH(80,Engine!$C$2:$C$622,0)),"",INDEX('Compliance Database'!$J$2:$J$622,MATCH(80,Engine!$C$2:$C$622,0))) | K93: =IF(ISNA(MATCH(80,Engine!$C$2:$C$622,0)),"",INDEX('Compliance Database'!$K$2:$K$622,MATCH(80,Engine!$C$2:$C$622,0))) | L93: =IF(ISNA(MATCH(80,Engine!$C$2:$C$622,0)),"",INDEX('Compliance Database'!$L$2:$L$622,MATCH(80,Engine!$C$2:$C$622,0))) | M93: =IF(ISNA(MATCH(80,Engine!$C$2:$C$622,0)),"",INDEX('Compliance Database'!$M$2:$M$622,MATCH(80,Engine!$C$2:$C$622,0))) | N93: =IF(ISNA(MATCH(80,Engine!$C$2:$C$622,0)),"",INDEX('Compliance Database'!$N$2:$N$622,MATCH(80,Engine!$C$2:$C$622,0))) | O93: =IF(ISNA(MATCH(80,Engine!$C$2:$C$622,0)),"",INDEX('Compliance Database'!$O$2:$O$622,MATCH(80,Engine!$C$2:$C$622,0)))
A94: =IF(ISNA(MATCH(81,Engine!$C$2:$C$622,0)),"",INDEX('Compliance Database'!$A$2:$A$622,MATCH(81,Engine!$C$2:$C$622,0))) | B94: =IF(ISNA(MATCH(81,Engine!$C$2:$C$622,0)),"",INDEX('Compliance Database'!$B$2:$B$622,MATCH(81,Engine!$C$2:$C$622,0))) | C94: =IF(ISNA(MATCH(81,Engine!$C$2:$C$622,0)),"",INDEX('Compliance Database'!$C$2:$C$622,MATCH(81,Engine!$C$2:$C$622,0))) | D94: =IF(ISNA(MATCH(81,Engine!$C$2:$C$622,0)),"",INDEX('Compliance Database'!$D$2:$D$622,MATCH(81,Engine!$C$2:$C$622,0))) | E94: =IF(ISNA(MATCH(81,Engine!$C$2:$C$622,0)),"",INDEX('Compliance Database'!$E$2:$E$622,MATCH(81,Engine!$C$2:$C$622,0))) | F94: =IF(ISNA(MATCH(81,Engine!$C$2:$C$622,0)),"",INDEX('Compliance Database'!$F$2:$F$622,MATCH(81,Engine!$C$2:$C$622,0))) | G94: =IF(ISNA(MATCH(81,Engine!$C$2:$C$622,0)),"",INDEX('Compliance Database'!$G$2:$G$622,MATCH(81,Engine!$C$2:$C$622,0))) | H94: =IF(ISNA(MATCH(81,Engine!$C$2:$C$622,0)),"",INDEX('Compliance Database'!$H$2:$H$622,MATCH(81,Engine!$C$2:$C$622,0))) | I94: =IF(ISNA(MATCH(81,Engine!$C$2:$C$622,0)),"",INDEX('Compliance Database'!$I$2:$I$622,MATCH(81,Engine!$C$2:$C$622,0))) | J94: =IF(ISNA(MATCH(81,Engine!$C$2:$C$622,0)),"",INDEX('Compliance Database'!$J$2:$J$622,MATCH(81,Engine!$C$2:$C$622,0))) | K94: =IF(ISNA(MATCH(81,Engine!$C$2:$C$622,0)),"",INDEX('Compliance Database'!$K$2:$K$622,MATCH(81,Engine!$C$2:$C$622,0))) | L94: =IF(ISNA(MATCH(81,Engine!$C$2:$C$622,0)),"",INDEX('Compliance Database'!$L$2:$L$622,MATCH(81,Engine!$C$2:$C$622,0))) | M94: =IF(ISNA(MATCH(81,Engine!$C$2:$C$622,0)),"",INDEX('Compliance Database'!$M$2:$M$622,MATCH(81,Engine!$C$2:$C$622,0))) | N94: =IF(ISNA(MATCH(81,Engine!$C$2:$C$622,0)),"",INDEX('Compliance Database'!$N$2:$N$622,MATCH(81,Engine!$C$2:$C$622,0))) | O94: =IF(ISNA(MATCH(81,Engine!$C$2:$C$622,0)),"",INDEX('Compliance Database'!$O$2:$O$622,MATCH(81,Engine!$C$2:$C$622,0)))
A95: =IF(ISNA(MATCH(82,Engine!$C$2:$C$622,0)),"",INDEX('Compliance Database'!$A$2:$A$622,MATCH(82,Engine!$C$2:$C$622,0))) | B95: =IF(ISNA(MATCH(82,Engine!$C$2:$C$622,0)),"",INDEX('Compliance Database'!$B$2:$B$622,MATCH(82,Engine!$C$2:$C$622,0))) | C95: =IF(ISNA(MATCH(82,Engine!$C$2:$C$622,0)),"",INDEX('Compliance Database'!$C$2:$C$622,MATCH(82,Engine!$C$2:$C$622,0))) | D95: =IF(ISNA(MATCH(82,Engine!$C$2:$C$622,0)),"",INDEX('Compliance Database'!$D$2:$D$622,MATCH(82,Engine!$C$2:$C$622,0))) | E95: =IF(ISNA(MATCH(82,Engine!$C$2:$C$622,0)),"",INDEX('Compliance Database'!$E$2:$E$622,MATCH(82,Engine!$C$2:$C$622,0))) | F95: =IF(ISNA(MATCH(82,Engine!$C$2:$C$622,0)),"",INDEX('Compliance Database'!$F$2:$F$622,MATCH(82,Engine!$C$2:$C$622,0))) | G95: =IF(ISNA(MATCH(82,Engine!$C$2:$C$622,0)),"",INDEX('Compliance Database'!$G$2:$G$622,MATCH(82,Engine!$C$2:$C$622,0))) | H95: =IF(ISNA(MATCH(82,Engine!$C$2:$C$622,0)),"",INDEX('Compliance Database'!$H$2:$H$622,MATCH(82,Engine!$C$2:$C$622,0))) | I95: =IF(ISNA(MATCH(82,Engine!$C$2:$C$622,0)),"",INDEX('Compliance Database'!$I$2:$I$622,MATCH(82,Engine!$C$2:$C$622,0))) | J95: =IF(ISNA(MATCH(82,Engine!$C$2:$C$622,0)),"",INDEX('Compliance Database'!$J$2:$J$622,MATCH(82,Engine!$C$2:$C$622,0))) | K95: =IF(ISNA(MATCH(82,Engine!$C$2:$C$622,0)),"",INDEX('Compliance Database'!$K$2:$K$622,MATCH(82,Engine!$C$2:$C$622,0))) | L95: =IF(ISNA(MATCH(82,Engine!$C$2:$C$622,0)),"",INDEX('Compliance Database'!$L$2:$L$622,MATCH(82,Engine!$C$2:$C$622,0))) | M95: =IF(ISNA(MATCH(82,Engine!$C$2:$C$622,0)),"",INDEX('Compliance Database'!$M$2:$M$622,MATCH(82,Engine!$C$2:$C$622,0))) | N95: =IF(ISNA(MATCH(82,Engine!$C$2:$C$622,0)),"",INDEX('Compliance Database'!$N$2:$N$622,MATCH(82,Engine!$C$2:$C$622,0))) | O95: =IF(ISNA(MATCH(82,Engine!$C$2:$C$622,0)),"",INDEX('Compliance Database'!$O$2:$O$622,MATCH(82,Engine!$C$2:$C$622,0)))
A96: =IF(ISNA(MATCH(83,Engine!$C$2:$C$622,0)),"",INDEX('Compliance Database'!$A$2:$A$622,MATCH(83,Engine!$C$2:$C$622,0))) | B96: =IF(ISNA(MATCH(83,Engine!$C$2:$C$622,0)),"",INDEX('Compliance Database'!$B$2:$B$622,MATCH(83,Engine!$C$2:$C$622,0))) | C96: =IF(ISNA(MATCH(83,Engine!$C$2:$C$622,0)),"",INDEX('Compliance Database'!$C$2:$C$622,MATCH(83,Engine!$C$2:$C$622,0))) | D96: =IF(ISNA(MATCH(83,Engine!$C$2:$C$622,0)),"",INDEX('Compliance Database'!$D$2:$D$622,MATCH(83,Engine!$C$2:$C$622,0))) | E96: =IF(ISNA(MATCH(83,Engine!$C$2:$C$622,0)),"",INDEX('Compliance Database'!$E$2:$E$622,MATCH(83,Engine!$C$2:$C$622,0))) | F96: =IF(ISNA(MATCH(83,Engine!$C$2:$C$622,0)),"",INDEX('Compliance Database'!$F$2:$F$622,MATCH(83,Engine!$C$2:$C$622,0))) | G96: =IF(ISNA(MATCH(83,Engine!$C$2:$C$622,0)),"",INDEX('Compliance Database'!$G$2:$G$622,MATCH(83,Engine!$C$2:$C$622,0))) | H96: =IF(ISNA(MATCH(83,Engine!$C$2:$C$622,0)),"",INDEX('Compliance Database'!$H$2:$H$622,MATCH(83,Engine!$C$2:$C$622,0))) | I96: =IF(ISNA(MATCH(83,Engine!$C$2:$C$622,0)),"",INDEX('Compliance Database'!$I$2:$I$622,MATCH(83,Engine!$C$2:$C$622,0))) | J96: =IF(ISNA(MATCH(83,Engine!$C$2:$C$622,0)),"",INDEX('Compliance Database'!$J$2:$J$622,MATCH(83,Engine!$C$2:$C$622,0))) | K96: =IF(ISNA(MATCH(83,Engine!$C$2:$C$622,0)),"",INDEX('Compliance Database'!$K$2:$K$622,MATCH(83,Engine!$C$2:$C$622,0))) | L96: =IF(ISNA(MATCH(83,Engine!$C$2:$C$622,0)),"",INDEX('Compliance Database'!$L$2:$L$622,MATCH(83,Engine!$C$2:$C$622,0))) | M96: =IF(ISNA(MATCH(83,Engine!$C$2:$C$622,0)),"",INDEX('Compliance Database'!$M$2:$M$622,MATCH(83,Engine!$C$2:$C$622,0))) | N96: =IF(ISNA(MATCH(83,Engine!$C$2:$C$622,0)),"",INDEX('Compliance Database'!$N$2:$N$622,MATCH(83,Engine!$C$2:$C$622,0))) | O96: =IF(ISNA(MATCH(83,Engine!$C$2:$C$622,0)),"",INDEX('Compliance Database'!$O$2:$O$622,MATCH(83,Engine!$C$2:$C$622,0)))
A97: =IF(ISNA(MATCH(84,Engine!$C$2:$C$622,0)),"",INDEX('Compliance Database'!$A$2:$A$622,MATCH(84,Engine!$C$2:$C$622,0))) | B97: =IF(ISNA(MATCH(84,Engine!$C$2:$C$622,0)),"",INDEX('Compliance Database'!$B$2:$B$622,MATCH(84,Engine!$C$2:$C$622,0))) | C97: =IF(ISNA(MATCH(84,Engine!$C$2:$C$622,0)),"",INDEX('Compliance Database'!$C$2:$C$622,MATCH(84,Engine!$C$2:$C$622,0))) | D97: =IF(ISNA(MATCH(84,Engine!$C$2:$C$622,0)),"",INDEX('Compliance Database'!$D$2:$D$622,MATCH(84,Engine!$C$2:$C$622,0))) | E97: =IF(ISNA(MATCH(84,Engine!$C$2:$C$622,0)),"",INDEX('Compliance Database'!$E$2:$E$622,MATCH(84,Engine!$C$2:$C$622,0))) | F97: =IF(ISNA(MATCH(84,Engine!$C$2:$C$622,0)),"",INDEX('Compliance Database'!$F$2:$F$622,MATCH(84,Engine!$C$2:$C$622,0))) | G97: =IF(ISNA(MATCH(84,Engine!$C$2:$C$622,0)),"",INDEX('Compliance Database'!$G$2:$G$622,MATCH(84,Engine!$C$2:$C$622,0))) | H97: =IF(ISNA(MATCH(84,Engine!$C$2:$C$622,0)),"",INDEX('Compliance Database'!$H$2:$H$622,MATCH(84,Engine!$C$2:$C$622,0))) | I97: =IF(ISNA(MATCH(84,Engine!$C$2:$C$622,0)),"",INDEX('Compliance Database'!$I$2:$I$622,MATCH(84,Engine!$C$2:$C$622,0))) | J97: =IF(ISNA(MATCH(84,Engine!$C$2:$C$622,0)),"",INDEX('Compliance Database'!$J$2:$J$622,MATCH(84,Engine!$C$2:$C$622,0))) | K97: =IF(ISNA(MATCH(84,Engine!$C$2:$C$622,0)),"",INDEX('Compliance Database'!$K$2:$K$622,MATCH(84,Engine!$C$2:$C$622,0))) | L97: =IF(ISNA(MATCH(84,Engine!$C$2:$C$622,0)),"",INDEX('Compliance Database'!$L$2:$L$622,MATCH(84,Engine!$C$2:$C$622,0))) | M97: =IF(ISNA(MATCH(84,Engine!$C$2:$C$622,0)),"",INDEX('Compliance Database'!$M$2:$M$622,MATCH(84,Engine!$C$2:$C$622,0))) | N97: =IF(ISNA(MATCH(84,Engine!$C$2:$C$622,0)),"",INDEX('Compliance Database'!$N$2:$N$622,MATCH(84,Engine!$C$2:$C$622,0))) | O97: =IF(ISNA(MATCH(84,Engine!$C$2:$C$622,0)),"",INDEX('Compliance Database'!$O$2:$O$622,MATCH(84,Engine!$C$2:$C$622,0)))
A98: =IF(ISNA(MATCH(85,Engine!$C$2:$C$622,0)),"",INDEX('Compliance Database'!$A$2:$A$622,MATCH(85,Engine!$C$2:$C$622,0))) | B98: =IF(ISNA(MATCH(85,Engine!$C$2:$C$622,0)),"",INDEX('Compliance Database'!$B$2:$B$622,MATCH(85,Engine!$C$2:$C$622,0))) | C98: =IF(ISNA(MATCH(85,Engine!$C$2:$C$622,0)),"",INDEX('Compliance Database'!$C$2:$C$622,MATCH(85,Engine!$C$2:$C$622,0))) | D98: =IF(ISNA(MATCH(85,Engine!$C$2:$C$622,0)),"",INDEX('Compliance Database'!$D$2:$D$622,MATCH(85,Engine!$C$2:$C$622,0))) | E98: =IF(ISNA(MATCH(85,Engine!$C$2:$C$622,0)),"",INDEX('Compliance Database'!$E$2:$E$622,MATCH(85,Engine!$C$2:$C$622,0))) | F98: =IF(ISNA(MATCH(85,Engine!$C$2:$C$622,0)),"",INDEX('Compliance Database'!$F$2:$F$622,MATCH(85,Engine!$C$2:$C$622,0))) | G98: =IF(ISNA(MATCH(85,Engine!$C$2:$C$622,0)),"",INDEX('Compliance Database'!$G$2:$G$622,MATCH(85,Engine!$C$2:$C$622,0))) | H98: =IF(ISNA(MATCH(85,Engine!$C$2:$C$622,0)),"",INDEX('Compliance Database'!$H$2:$H$622,MATCH(85,Engine!$C$2:$C$622,0))) | I98: =IF(ISNA(MATCH(85,Engine!$C$2:$C$622,0)),"",INDEX('Compliance Database'!$I$2:$I$622,MATCH(85,Engine!$C$2:$C$622,0))) | J98: =IF(ISNA(MATCH(85,Engine!$C$2:$C$622,0)),"",INDEX('Compliance Database'!$J$2:$J$622,MATCH(85,Engine!$C$2:$C$622,0))) | K98: =IF(ISNA(MATCH(85,Engine!$C$2:$C$622,0)),"",INDEX('Compliance Database'!$K$2:$K$622,MATCH(85,Engine!$C$2:$C$622,0))) | L98: =IF(ISNA(MATCH(85,Engine!$C$2:$C$622,0)),"",INDEX('Compliance Database'!$L$2:$L$622,MATCH(85,Engine!$C$2:$C$622,0))) | M98: =IF(ISNA(MATCH(85,Engine!$C$2:$C$622,0)),"",INDEX('Compliance Database'!$M$2:$M$622,MATCH(85,Engine!$C$2:$C$622,0))) | N98: =IF(ISNA(MATCH(85,Engine!$C$2:$C$622,0)),"",INDEX('Compliance Database'!$N$2:$N$622,MATCH(85,Engine!$C$2:$C$622,0))) | O98: =IF(ISNA(MATCH(85,Engine!$C$2:$C$622,0)),"",INDEX('Compliance Database'!$O$2:$O$622,MATCH(85,Engine!$C$2:$C$622,0)))
A99: =IF(ISNA(MATCH(86,Engine!$C$2:$C$622,0)),"",INDEX('Compliance Database'!$A$2:$A$622,MATCH(86,Engine!$C$2:$C$622,0))) | B99: =IF(ISNA(MATCH(86,Engine!$C$2:$C$622,0)),"",INDEX('Compliance Database'!$B$2:$B$622,MATCH(86,Engine!$C$2:$C$622,0))) | C99: =IF(ISNA(MATCH(86,Engine!$C$2:$C$622,0)),"",INDEX('Compliance Database'!$C$2:$C$622,MATCH(86,Engine!$C$2:$C$622,0))) | D99: =IF(ISNA(MATCH(86,Engine!$C$2:$C$622,0)),"",INDEX('Compliance Database'!$D$2:$D$622,MATCH(86,Engine!$C$2:$C$622,0))) | E99: =IF(ISNA(MATCH(86,Engine!$C$2:$C$622,0)),"",INDEX('Compliance Database'!$E$2:$E$622,MATCH(86,Engine!$C$2:$C$622,0))) | F99: =IF(ISNA(MATCH(86,Engine!$C$2:$C$622,0)),"",INDEX('Compliance Database'!$F$2:$F$622,MATCH(86,Engine!$C$2:$C$622,0))) | G99: =IF(ISNA(MATCH(86,Engine!$C$2:$C$622,0)),"",INDEX('Compliance Database'!$G$2:$G$622,MATCH(86,Engine!$C$2:$C$622,0))) | H99: =IF(ISNA(MATCH(86,Engine!$C$2:$C$622,0)),"",INDEX('Compliance Database'!$H$2:$H$622,MATCH(86,Engine!$C$2:$C$622,0))) | I99: =IF(ISNA(MATCH(86,Engine!$C$2:$C$622,0)),"",INDEX('Compliance Database'!$I$2:$I$622,MATCH(86,Engine!$C$2:$C$622,0))) | J99: =IF(ISNA(MATCH(86,Engine!$C$2:$C$622,0)),"",INDEX('Compliance Database'!$J$2:$J$622,MATCH(86,Engine!$C$2:$C$622,0))) | K99: =IF(ISNA(MATCH(86,Engine!$C$2:$C$622,0)),"",INDEX('Compliance Database'!$K$2:$K$622,MATCH(86,Engine!$C$2:$C$622,0))) | L99: =IF(ISNA(MATCH(86,Engine!$C$2:$C$622,0)),"",INDEX('Compliance Database'!$L$2:$L$622,MATCH(86,Engine!$C$2:$C$622,0))) | M99: =IF(ISNA(MATCH(86,Engine!$C$2:$C$622,0)),"",INDEX('Compliance Database'!$M$2:$M$622,MATCH(86,Engine!$C$2:$C$622,0))) | N99: =IF(ISNA(MATCH(86,Engine!$C$2:$C$622,0)),"",INDEX('Compliance Database'!$N$2:$N$622,MATCH(86,Engine!$C$2:$C$622,0))) | O99: =IF(ISNA(MATCH(86,Engine!$C$2:$C$622,0)),"",INDEX('Compliance Database'!$O$2:$O$622,MATCH(86,Engine!$C$2:$C$622,0)))
A100: =IF(ISNA(MATCH(87,Engine!$C$2:$C$622,0)),"",INDEX('Compliance Database'!$A$2:$A$622,MATCH(87,Engine!$C$2:$C$622,0))) | B100: =IF(ISNA(MATCH(87,Engine!$C$2:$C$622,0)),"",INDEX('Compliance Database'!$B$2:$B$622,MATCH(87,Engine!$C$2:$C$622,0))) | C100: =IF(ISNA(MATCH(87,Engine!$C$2:$C$622,0)),"",INDEX('Compliance Database'!$C$2:$C$622,MATCH(87,Engine!$C$2:$C$622,0))) | D100: =IF(ISNA(MATCH(87,Engine!$C$2:$C$622,0)),"",INDEX('Compliance Database'!$D$2:$D$622,MATCH(87,Engine!$C$2:$C$622,0))) | E100: =IF(ISNA(MATCH(87,Engine!$C$2:$C$622,0)),"",INDEX('Compliance Database'!$E$2:$E$622,MATCH(87,Engine!$C$2:$C$622,0))) | F100: =IF(ISNA(MATCH(87,Engine!$C$2:$C$622,0)),"",INDEX('Compliance Database'!$F$2:$F$622,MATCH(87,Engine!$C$2:$C$622,0))) | G100: =IF(ISNA(MATCH(87,Engine!$C$2:$C$622,0)),"",INDEX('Compliance Database'!$G$2:$G$622,MATCH(87,Engine!$C$2:$C$622,0))) | H100: =IF(ISNA(MATCH(87,Engine!$C$2:$C$622,0)),"",INDEX('Compliance Database'!$H$2:$H$622,MATCH(87,Engine!$C$2:$C$622,0))) | I100: =IF(ISNA(MATCH(87,Engine!$C$2:$C$622,0)),"",INDEX('Compliance Database'!$I$2:$I$622,MATCH(87,Engine!$C$2:$C$622,0))) | J100: =IF(ISNA(MATCH(87,Engine!$C$2:$C$622,0)),"",INDEX('Compliance Database'!$J$2:$J$622,MATCH(87,Engine!$C$2:$C$622,0))) | K100: =IF(ISNA(MATCH(87,Engine!$C$2:$C$622,0)),"",INDEX('Compliance Database'!$K$2:$K$622,MATCH(87,Engine!$C$2:$C$622,0))) | L100: =IF(ISNA(MATCH(87,Engine!$C$2:$C$622,0)),"",INDEX('Compliance Database'!$L$2:$L$622,MATCH(87,Engine!$C$2:$C$622,0))) | M100: =IF(ISNA(MATCH(87,Engine!$C$2:$C$622,0)),"",INDEX('Compliance Database'!$M$2:$M$622,MATCH(87,Engine!$C$2:$C$622,0))) | N100: =IF(ISNA(MATCH(87,Engine!$C$2:$C$622,0)),"",INDEX('Compliance Database'!$N$2:$N$622,MATCH(87,Engine!$C$2:$C$622,0))) | O100: =IF(ISNA(MATCH(87,Engine!$C$2:$C$622,0)),"",INDEX('Compliance Database'!$O$2:$O$622,MATCH(87,Engine!$C$2:$C$622,0)))
A101: =IF(ISNA(MATCH(88,Engine!$C$2:$C$622,0)),"",INDEX('Compliance Database'!$A$2:$A$622,MATCH(88,Engine!$C$2:$C$622,0))) | B101: =IF(ISNA(MATCH(88,Engine!$C$2:$C$622,0)),"",INDEX('Compliance Database'!$B$2:$B$622,MATCH(88,Engine!$C$2:$C$622,0))) | C101: =IF(ISNA(MATCH(88,Engine!$C$2:$C$622,0)),"",INDEX('Compliance Database'!$C$2:$C$622,MATCH(88,Engine!$C$2:$C$622,0))) | D101: =IF(ISNA(MATCH(88,Engine!$C$2:$C$622,0)),"",INDEX('Compliance Database'!$D$2:$D$622,MATCH(88,Engine!$C$2:$C$622,0))) | E101: =IF(ISNA(MATCH(88,Engine!$C$2:$C$622,0)),"",INDEX('Compliance Database'!$E$2:$E$622,MATCH(88,Engine!$C$2:$C$622,0))) | F101: =IF(ISNA(MATCH(88,Engine!$C$2:$C$622,0)),"",INDEX('Compliance Database'!$F$2:$F$622,MATCH(88,Engine!$C$2:$C$622,0))) | G101: =IF(ISNA(MATCH(88,Engine!$C$2:$C$622,0)),"",INDEX('Compliance Database'!$G$2:$G$622,MATCH(88,Engine!$C$2:$C$622,0))) | H101: =IF(ISNA(MATCH(88,Engine!$C$2:$C$622,0)),"",INDEX('Compliance Database'!$H$2:$H$622,MATCH(88,Engine!$C$2:$C$622,0))) | I101: =IF(ISNA(MATCH(88,Engine!$C$2:$C$622,0)),"",INDEX('Compliance Database'!$I$2:$I$622,MATCH(88,Engine!$C$2:$C$622,0))) | J101: =IF(ISNA(MATCH(88,Engine!$C$2:$C$622,0)),"",INDEX('Compliance Database'!$J$2:$J$622,MATCH(88,Engine!$C$2:$C$622,0))) | K101: =IF(ISNA(MATCH(88,Engine!$C$2:$C$622,0)),"",INDEX('Compliance Database'!$K$2:$K$622,MATCH(88,Engine!$C$2:$C$622,0))) | L101: =IF(ISNA(MATCH(88,Engine!$C$2:$C$622,0)),"",INDEX('Compliance Database'!$L$2:$L$622,MATCH(88,Engine!$C$2:$C$622,0))) | M101: =IF(ISNA(MATCH(88,Engine!$C$2:$C$622,0)),"",INDEX('Compliance Database'!$M$2:$M$622,MATCH(88,Engine!$C$2:$C$622,0))) | N101: =IF(ISNA(MATCH(88,Engine!$C$2:$C$622,0)),"",INDEX('Compliance Database'!$N$2:$N$622,MATCH(88,Engine!$C$2:$C$622,0))) | O101: =IF(ISNA(MATCH(88,Engine!$C$2:$C$622,0)),"",INDEX('Compliance Database'!$O$2:$O$622,MATCH(88,Engine!$C$2:$C$622,0)))
A102: =IF(ISNA(MATCH(89,Engine!$C$2:$C$622,0)),"",INDEX('Compliance Database'!$A$2:$A$622,MATCH(89,Engine!$C$2:$C$622,0))) | B102: =IF(ISNA(MATCH(89,Engine!$C$2:$C$622,0)),"",INDEX('Compliance Database'!$B$2:$B$622,MATCH(89,Engine!$C$2:$C$622,0))) | C102: =IF(ISNA(MATCH(89,Engine!$C$2:$C$622,0)),"",INDEX('Compliance Database'!$C$2:$C$622,MATCH(89,Engine!$C$2:$C$622,0))) | D102: =IF(ISNA(MATCH(89,Engine!$C$2:$C$622,0)),"",INDEX('Compliance Database'!$D$2:$D$622,MATCH(89,Engine!$C$2:$C$622,0))) | E102: =IF(ISNA(MATCH(89,Engine!$C$2:$C$622,0)),"",INDEX('Compliance Database'!$E$2:$E$622,MATCH(89,Engine!$C$2:$C$622,0))) | F102: =IF(ISNA(MATCH(89,Engine!$C$2:$C$622,0)),"",INDEX('Compliance Database'!$F$2:$F$622,MATCH(89,Engine!$C$2:$C$622,0))) | G102: =IF(ISNA(MATCH(89,Engine!$C$2:$C$622,0)),"",INDEX('Compliance Database'!$G$2:$G$622,MATCH(89,Engine!$C$2:$C$622,0))) | H102: =IF(ISNA(MATCH(89,Engine!$C$2:$C$622,0)),"",INDEX('Compliance Database'!$H$2:$H$622,MATCH(89,Engine!$C$2:$C$622,0))) | I102: =IF(ISNA(MATCH(89,Engine!$C$2:$C$622,0)),"",INDEX('Compliance Database'!$I$2:$I$622,MATCH(89,Engine!$C$2:$C$622,0))) | J102: =IF(ISNA(MATCH(89,Engine!$C$2:$C$622,0)),"",INDEX('Compliance Database'!$J$2:$J$622,MATCH(89,Engine!$C$2:$C$622,0))) | K102: =IF(ISNA(MATCH(89,Engine!$C$2:$C$622,0)),"",INDEX('Compliance Database'!$K$2:$K$622,MATCH(89,Engine!$C$2:$C$622,0))) | L102: =IF(ISNA(MATCH(89,Engine!$C$2:$C$622,0)),"",INDEX('Compliance Database'!$L$2:$L$622,MATCH(89,Engine!$C$2:$C$622,0))) | M102: =IF(ISNA(MATCH(89,Engine!$C$2:$C$622,0)),"",INDEX('Compliance Database'!$M$2:$M$622,MATCH(89,Engine!$C$2:$C$622,0))) | N102: =IF(ISNA(MATCH(89,Engine!$C$2:$C$622,0)),"",INDEX('Compliance Database'!$N$2:$N$622,MATCH(89,Engine!$C$2:$C$622,0))) | O102: =IF(ISNA(MATCH(89,Engine!$C$2:$C$622,0)),"",INDEX('Compliance Database'!$O$2:$O$622,MATCH(89,Engine!$C$2:$C$622,0)))
...

Sheet Data Transfer
A1: Cross-Border Data Transfer
A3: Pick the two countries involved in the transfer. Every relevant act/section from either country is listed below; add a keyword to narrow it.
A4: Country A (from) | B4: Australia
A5: Country B (to) | B5: GDPR
A6: Keyword (free text)
A8: Matching sections (of 621 total): | C8: ='Transfer Engine'!$D$1
A9: Country | B9: Act | C9: Section | D9: Heading | E9: Pages | F9: Category | G9: Financial Relevance | H9: Confidence | I9: Topics | J9: Data Types | K9: Authority | L9: Summary | M9: DTIA Summary | N9: Requirements | O9: Source Quote
A10: =IF(ISNA(MATCH(1,'Transfer Engine'!$C$2:$C$622,0)),"",INDEX('Compliance Database'!$A$2:$A$622,MATCH(1,'Transfer Engine'!$C$2:$C$622,0))) | B10: =IF(ISNA(MATCH(1,'Transfer Engine'!$C$2:$C$622,0)),"",INDEX('Compliance Database'!$B$2:$B$622,MATCH(1,'Transfer Engine'!$C$2:$C$622,0))) | C10: =IF(ISNA(MATCH(1,'Transfer Engine'!$C$2:$C$622,0)),"",INDEX('Compliance Database'!$C$2:$C$622,MATCH(1,'Transfer Engine'!$C$2:$C$622,0))) | D10: =IF(ISNA(MATCH(1,'Transfer Engine'!$C$2:$C$622,0)),"",INDEX('Compliance Database'!$D$2:$D$622,MATCH(1,'Transfer Engine'!$C$2:$C$622,0))) | E10: =IF(ISNA(MATCH(1,'Transfer Engine'!$C$2:$C$622,0)),"",INDEX('Compliance Database'!$E$2:$E$622,MATCH(1,'Transfer Engine'!$C$2:$C$622,0))) | F10: =IF(ISNA(MATCH(1,'Transfer Engine'!$C$2:$C$622,0)),"",INDEX('Compliance Database'!$F$2:$F$622,MATCH(1,'Transfer Engine'!$C$2:$C$622,0))) | G10: =IF(ISNA(MATCH(1,'Transfer Engine'!$C$2:$C$622,0)),"",INDEX('Compliance Database'!$G$2:$G$622,MATCH(1,'Transfer Engine'!$C$2:$C$622,0))) | H10: =IF(ISNA(MATCH(1,'Transfer Engine'!$C$2:$C$622,0)),"",INDEX('Compliance Database'!$H$2:$H$622,MATCH(1,'Transfer Engine'!$C$2:$C$622,0))) | I10: =IF(ISNA(MATCH(1,'Transfer Engine'!$C$2:$C$622,0)),"",INDEX('Compliance Database'!$I$2:$I$622,MATCH(1,'Transfer Engine'!$C$2:$C$622,0))) | J10: =IF(ISNA(MATCH(1,'Transfer Engine'!$C$2:$C$622,0)),"",INDEX('Compliance Database'!$J$2:$J$622,MATCH(1,'Transfer Engine'!$C$2:$C$622,0))) | K10: =IF(ISNA(MATCH(1,'Transfer Engine'!$C$2:$C$622,0)),"",INDEX('Compliance Database'!$K$2:$K$622,MATCH(1,'Transfer Engine'!$C$2:$C$622,0))) | L10: =IF(ISNA(MATCH(1,'Transfer Engine'!$C$2:$C$622,0)),"",INDEX('Compliance Database'!$L$2:$L$622,MATCH(1,'Transfer Engine'!$C$2:$C$622,0))) | M10: =IF(ISNA(MATCH(1,'Transfer Engine'!$C$2:$C$622,0)),"",INDEX('Compliance Database'!$M$2:$M$622,MATCH(1,'Transfer Engine'!$C$2:$C$622,0))) | N10: =IF(ISNA(MATCH(1,'Transfer Engine'!$C$2:$C$622,0)),"",INDEX('Compliance Database'!$N$2:$N$622,MATCH(1,'Transfer Engine'!$C$2:$C$622,0))) | O10: =IF(ISNA(MATCH(1,'Transfer Engine'!$C$2:$C$622,0)),"",INDEX('Compliance Database'!$O$2:$O$622,MATCH(1,'Transfer Engine'!$C$2:$C$622,0)))
A11: =IF(ISNA(MATCH(2,'Transfer Engine'!$C$2:$C$622,0)),"",INDEX('Compliance Database'!$A$2:$A$622,MATCH(2,'Transfer Engine'!$C$2:$C$622,0))) | B11: =IF(ISNA(MATCH(2,'Transfer Engine'!$C$2:$C$622,0)),"",INDEX('Compliance Database'!$B$2:$B$622,MATCH(2,'Transfer Engine'!$C$2:$C$622,0))) | C11: =IF(ISNA(MATCH(2,'Transfer Engine'!$C$2:$C$622,0)),"",INDEX('Compliance Database'!$C$2:$C$622,MATCH(2,'Transfer Engine'!$C$2:$C$622,0))) | D11: =IF(ISNA(MATCH(2,'Transfer Engine'!$C$2:$C$622,0)),"",INDEX('Compliance Database'!$D$2:$D$622,MATCH(2,'Transfer Engine'!$C$2:$C$622,0))) | E11: =IF(ISNA(MATCH(2,'Transfer Engine'!$C$2:$C$622,0)),"",INDEX('Compliance Database'!$E$2:$E$622,MATCH(2,'Transfer Engine'!$C$2:$C$622,0))) | F11: =IF(ISNA(MATCH(2,'Transfer Engine'!$C$2:$C$622,0)),"",INDEX('Compliance Database'!$F$2:$F$622,MATCH(2,'Transfer Engine'!$C$2:$C$622,0))) | G11: =IF(ISNA(MATCH(2,'Transfer Engine'!$C$2:$C$622,0)),"",INDEX('Compliance Database'!$G$2:$G$622,MATCH(2,'Transfer Engine'!$C$2:$C$622,0))) | H11: =IF(ISNA(MATCH(2,'Transfer Engine'!$C$2:$C$622,0)),"",INDEX('Compliance Database'!$H$2:$H$622,MATCH(2,'Transfer Engine'!$C$2:$C$622,0))) | I11: =IF(ISNA(MATCH(2,'Transfer Engine'!$C$2:$C$622,0)),"",INDEX('Compliance Database'!$I$2:$I$622,MATCH(2,'Transfer Engine'!$C$2:$C$622,0))) | J11: =IF(ISNA(MATCH(2,'Transfer Engine'!$C$2:$C$622,0)),"",INDEX('Compliance Database'!$J$2:$J$622,MATCH(2,'Transfer Engine'!$C$2:$C$622,0))) | K11: =IF(ISNA(MATCH(2,'Transfer Engine'!$C$2:$C$622,0)),"",INDEX('Compliance Database'!$K$2:$K$622,MATCH(2,'Transfer Engine'!$C$2:$C$622,0))) | L11: =IF(ISNA(MATCH(2,'Transfer Engine'!$C$2:$C$622,0)),"",INDEX('Compliance Database'!$L$2:$L$622,MATCH(2,'Transfer Engine'!$C$2:$C$622,0))) | M11: =IF(ISNA(MATCH(2,'Transfer Engine'!$C$2:$C$622,0)),"",INDEX('Compliance Database'!$M$2:$M$622,MATCH(2,'Transfer Engine'!$C$2:$C$622,0))) | N11: =IF(ISNA(MATCH(2,'Transfer Engine'!$C$2:$C$622,0)),"",INDEX('Compliance Database'!$N$2:$N$622,MATCH(2,'Transfer Engine'!$C$2:$C$622,0))) | O11: =IF(ISNA(MATCH(2,'Transfer Engine'!$C$2:$C$622,0)),"",INDEX('Compliance Database'!$O$2:$O$622,MATCH(2,'Transfer Engine'!$C$2:$C$622,0)))
A12: =IF(ISNA(MATCH(3,'Transfer Engine'!$C$2:$C$622,0)),"",INDEX('Compliance Database'!$A$2:$A$622,MATCH(3,'Transfer Engine'!$C$2:$C$622,0))) | B12: =IF(ISNA(MATCH(3,'Transfer Engine'!$C$2:$C$622,0)),"",INDEX('Compliance Database'!$B$2:$B$622,MATCH(3,'Transfer Engine'!$C$2:$C$622,0))) | C12: =IF(ISNA(MATCH(3,'Transfer Engine'!$C$2:$C$622,0)),"",INDEX('Compliance Database'!$C$2:$C$622,MATCH(3,'Transfer Engine'!$C$2:$C$622,0))) | D12: =IF(ISNA(MATCH(3,'Transfer Engine'!$C$2:$C$622,0)),"",INDEX('Compliance Database'!$D$2:$D$622,MATCH(3,'Transfer Engine'!$C$2:$C$622,0))) | E12: =IF(ISNA(MATCH(3,'Transfer Engine'!$C$2:$C$622,0)),"",INDEX('Compliance Database'!$E$2:$E$622,MATCH(3,'Transfer Engine'!$C$2:$C$622,0))) | F12: =IF(ISNA(MATCH(3,'Transfer Engine'!$C$2:$C$622,0)),"",INDEX('Compliance Database'!$F$2:$F$622,MATCH(3,'Transfer Engine'!$C$2:$C$622,0))) | G12: =IF(ISNA(MATCH(3,'Transfer Engine'!$C$2:$C$622,0)),"",INDEX('Compliance Database'!$G$2:$G$622,MATCH(3,'Transfer Engine'!$C$2:$C$622,0))) | H12: =IF(ISNA(MATCH(3,'Transfer Engine'!$C$2:$C$622,0)),"",INDEX('Compliance Database'!$H$2:$H$622,MATCH(3,'Transfer Engine'!$C$2:$C$622,0))) | I12: =IF(ISNA(MATCH(3,'Transfer Engine'!$C$2:$C$622,0)),"",INDEX('Compliance Database'!$I$2:$I$622,MATCH(3,'Transfer Engine'!$C$2:$C$622,0))) | J12: =IF(ISNA(MATCH(3,'Transfer Engine'!$C$2:$C$622,0)),"",INDEX('Compliance Database'!$J$2:$J$622,MATCH(3,'Transfer Engine'!$C$2:$C$622,0))) | K12: =IF(ISNA(MATCH(3,'Transfer Engine'!$C$2:$C$622,0)),"",INDEX('Compliance Database'!$K$2:$K$622,MATCH(3,'Transfer Engine'!$C$2:$C$622,0))) | L12: =IF(ISNA(MATCH(3,'Transfer Engine'!$C$2:$C$622,0)),"",INDEX('Compliance Database'!$L$2:$L$622,MATCH(3,'Transfer Engine'!$C$2:$C$622,0))) | M12: =IF(ISNA(MATCH(3,'Transfer Engine'!$C$2:$C$622,0)),"",INDEX('Compliance Database'!$M$2:$M$622,MATCH(3,'Transfer Engine'!$C$2:$C$622,0))) | N12: =IF(ISNA(MATCH(3,'Transfer Engine'!$C$2:$C$622,0)),"",INDEX('Compliance Database'!$N$2:$N$622,MATCH(3,'Transfer Engine'!$C$2:$C$622,0))) | O12: =IF(ISNA(MATCH(3,'Transfer Engine'!$C$2:$C$622,0)),"",INDEX('Compliance Database'!$O$2:$O$622,MATCH(3,'Transfer Engine'!$C$2:$C$622,0)))
A13: =IF(ISNA(MATCH(4,'Transfer Engine'!$C$2:$C$622,0)),"",INDEX('Compliance Database'!$A$2:$A$622,MATCH(4,'Transfer Engine'!$C$2:$C$622,0))) | B13: =IF(ISNA(MATCH(4,'Transfer Engine'!$C$2:$C$622,0)),"",INDEX('Compliance Database'!$B$2:$B$622,MATCH(4,'Transfer Engine'!$C$2:$C$622,0))) | C13: =IF(ISNA(MATCH(4,'Transfer Engine'!$C$2:$C$622,0)),"",INDEX('Compliance Database'!$C$2:$C$622,MATCH(4,'Transfer Engine'!$C$2:$C$622,0))) | D13: =IF(ISNA(MATCH(4,'Transfer Engine'!$C$2:$C$622,0)),"",INDEX('Compliance Database'!$D$2:$D$622,MATCH(4,'Transfer Engine'!$C$2:$C$622,0))) | E13: =IF(ISNA(MATCH(4,'Transfer Engine'!$C$2:$C$622,0)),"",INDEX('Compliance Database'!$E$2:$E$622,MATCH(4,'Transfer Engine'!$C$2:$C$622,0))) | F13: =IF(ISNA(MATCH(4,'Transfer Engine'!$C$2:$C$622,0)),"",INDEX('Compliance Database'!$F$2:$F$622,MATCH(4,'Transfer Engine'!$C$2:$C$622,0))) | G13: =IF(ISNA(MATCH(4,'Transfer Engine'!$C$2:$C$622,0)),"",INDEX('Compliance Database'!$G$2:$G$622,MATCH(4,'Transfer Engine'!$C$2:$C$622,0))) | H13: =IF(ISNA(MATCH(4,'Transfer Engine'!$C$2:$C$622,0)),"",INDEX('Compliance Database'!$H$2:$H$622,MATCH(4,'Transfer Engine'!$C$2:$C$622,0))) | I13: =IF(ISNA(MATCH(4,'Transfer Engine'!$C$2:$C$622,0)),"",INDEX('Compliance Database'!$I$2:$I$622,MATCH(4,'Transfer Engine'!$C$2:$C$622,0))) | J13: =IF(ISNA(MATCH(4,'Transfer Engine'!$C$2:$C$622,0)),"",INDEX('Compliance Database'!$J$2:$J$622,MATCH(4,'Transfer Engine'!$C$2:$C$622,0))) | K13: =IF(ISNA(MATCH(4,'Transfer Engine'!$C$2:$C$622,0)),"",INDEX('Compliance Database'!$K$2:$K$622,MATCH(4,'Transfer Engine'!$C$2:$C$622,0))) | L13: =IF(ISNA(MATCH(4,'Transfer Engine'!$C$2:$C$622,0)),"",INDEX('Compliance Database'!$L$2:$L$622,MATCH(4,'Transfer Engine'!$C$2:$C$622,0))) | M13: =IF(ISNA(MATCH(4,'Transfer Engine'!$C$2:$C$622,0)),"",INDEX('Compliance Database'!$M$2:$M$622,MATCH(4,'Transfer Engine'!$C$2:$C$622,0))) | N13: =IF(ISNA(MATCH(4,'Transfer Engine'!$C$2:$C$622,0)),"",INDEX('Compliance Database'!$N$2:$N$622,MATCH(4,'Transfer Engine'!$C$2:$C$622,0))) | O13: =IF(ISNA(MATCH(4,'Transfer Engine'!$C$2:$C$622,0)),"",INDEX('Compliance Database'!$O$2:$O$622,MATCH(4,'Transfer Engine'!$C$2:$C$622,0)))
A14: =IF(ISNA(MATCH(5,'Transfer Engine'!$C$2:$C$622,0)),"",INDEX('Compliance Database'!$A$2:$A$622,MATCH(5,'Transfer Engine'!$C$2:$C$622,0))) | B14: =IF(ISNA(MATCH(5,'Transfer Engine'!$C$2:$C$622,0)),"",INDEX('Compliance Database'!$B$2:$B$622,MATCH(5,'Transfer Engine'!$C$2:$C$622,0))) | C14: =IF(ISNA(MATCH(5,'Transfer Engine'!$C$2:$C$622,0)),"",INDEX('Compliance Database'!$C$2:$C$622,MATCH(5,'Transfer Engine'!$C$2:$C$622,0))) | D14: =IF(ISNA(MATCH(5,'Transfer Engine'!$C$2:$C$622,0)),"",INDEX('Compliance Database'!$D$2:$D$622,MATCH(5,'Transfer Engine'!$C$2:$C$622,0))) | E14: =IF(ISNA(MATCH(5,'Transfer Engine'!$C$2:$C$622,0)),"",INDEX('Compliance Database'!$E$2:$E$622,MATCH(5,'Transfer Engine'!$C$2:$C$622,0))) | F14: =IF(ISNA(MATCH(5,'Transfer Engine'!$C$2:$C$622,0)),"",INDEX('Compliance Database'!$F$2:$F$622,MATCH(5,'Transfer Engine'!$C$2:$C$622,0))) | G14: =IF(ISNA(MATCH(5,'Transfer Engine'!$C$2:$C$622,0)),"",INDEX('Compliance Database'!$G$2:$G$622,MATCH(5,'Transfer Engine'!$C$2:$C$622,0))) | H14: =IF(ISNA(MATCH(5,'Transfer Engine'!$C$2:$C$622,0)),"",INDEX('Compliance Database'!$H$2:$H$622,MATCH(5,'Transfer Engine'!$C$2:$C$622,0))) | I14: =IF(ISNA(MATCH(5,'Transfer Engine'!$C$2:$C$622,0)),"",INDEX('Compliance Database'!$I$2:$I$622,MATCH(5,'Transfer Engine'!$C$2:$C$622,0))) | J14: =IF(ISNA(MATCH(5,'Transfer Engine'!$C$2:$C$622,0)),"",INDEX('Compliance Database'!$J$2:$J$622,MATCH(5,'Transfer Engine'!$C$2:$C$622,0))) | K14: =IF(ISNA(MATCH(5,'Transfer Engine'!$C$2:$C$622,0)),"",INDEX('Compliance Database'!$K$2:$K$622,MATCH(5,'Transfer Engine'!$C$2:$C$622,0))) | L14: =IF(ISNA(MATCH(5,'Transfer Engine'!$C$2:$C$622,0)),"",INDEX('Compliance Database'!$L$2:$L$622,MATCH(5,'Transfer Engine'!$C$2:$C$622,0))) | M14: =IF(ISNA(MATCH(5,'Transfer Engine'!$C$2:$C$622,0)),"",INDEX('Compliance Database'!$M$2:$M$622,MATCH(5,'Transfer Engine'!$C$2:$C$622,0))) | N14: =IF(ISNA(MATCH(5,'Transfer Engine'!$C$2:$C$622,0)),"",INDEX('Compliance Database'!$N$2:$N$622,MATCH(5,'Transfer Engine'!$C$2:$C$622,0))) | O14: =IF(ISNA(MATCH(5,'Transfer Engine'!$C$2:$C$622,0)),"",INDEX('Compliance Database'!$O$2:$O$622,MATCH(5,'Transfer Engine'!$C$2:$C$622,0)))
A15: =IF(ISNA(MATCH(6,'Transfer Engine'!$C$2:$C$622,0)),"",INDEX('Compliance Database'!$A$2:$A$622,MATCH(6,'Transfer Engine'!$C$2:$C$622,0))) | B15: =IF(ISNA(MATCH(6,'Transfer Engine'!$C$2:$C$622,0)),"",INDEX('Compliance Database'!$B$2:$B$622,MATCH(6,'Transfer Engine'!$C$2:$C$622,0))) | C15: =IF(ISNA(MATCH(6,'Transfer Engine'!$C$2:$C$622,0)),"",INDEX('Compliance Database'!$C$2:$C$622,MATCH(6,'Transfer Engine'!$C$2:$C$622,0))) | D15: =IF(ISNA(MATCH(6,'Transfer Engine'!$C$2:$C$622,0)),"",INDEX('Compliance Database'!$D$2:$D$622,MATCH(6,'Transfer Engine'!$C$2:$C$622,0))) | E15: =IF(ISNA(MATCH(6,'Transfer Engine'!$C$2:$C$622,0)),"",INDEX('Compliance Database'!$E$2:$E$622,MATCH(6,'Transfer Engine'!$C$2:$C$622,0))) | F15: =IF(ISNA(MATCH(6,'Transfer Engine'!$C$2:$C$622,0)),"",INDEX('Compliance Database'!$F$2:$F$622,MATCH(6,'Transfer Engine'!$C$2:$C$622,0))) | G15: =IF(ISNA(MATCH(6,'Transfer Engine'!$C$2:$C$622,0)),"",INDEX('Compliance Database'!$G$2:$G$622,MATCH(6,'Transfer Engine'!$C$2:$C$622,0))) | H15: =IF(ISNA(MATCH(6,'Transfer Engine'!$C$2:$C$622,0)),"",INDEX('Compliance Database'!$H$2:$H$622,MATCH(6,'Transfer Engine'!$C$2:$C$622,0))) | I15: =IF(ISNA(MATCH(6,'Transfer Engine'!$C$2:$C$622,0)),"",INDEX('Compliance Database'!$I$2:$I$622,MATCH(6,'Transfer Engine'!$C$2:$C$622,0))) | J15: =IF(ISNA(MATCH(6,'Transfer Engine'!$C$2:$C$622,0)),"",INDEX('Compliance Database'!$J$2:$J$622,MATCH(6,'Transfer Engine'!$C$2:$C$622,0))) | K15: =IF(ISNA(MATCH(6,'Transfer Engine'!$C$2:$C$622,0)),"",INDEX('Compliance Database'!$K$2:$K$622,MATCH(6,'Transfer Engine'!$C$2:$C$622,0))) | L15: =IF(ISNA(MATCH(6,'Transfer Engine'!$C$2:$C$622,0)),"",INDEX('Compliance Database'!$L$2:$L$622,MATCH(6,'Transfer Engine'!$C$2:$C$622,0))) | M15: =IF(ISNA(MATCH(6,'Transfer Engine'!$C$2:$C$622,0)),"",INDEX('Compliance Database'!$M$2:$M$622,MATCH(6,'Transfer Engine'!$C$2:$C$622,0))) | N15: =IF(ISNA(MATCH(6,'Transfer Engine'!$C$2:$C$622,0)),"",INDEX('Compliance Database'!$N$2:$N$622,MATCH(6,'Transfer Engine'!$C$2:$C$622,0))) | O15: =IF(ISNA(MATCH(6,'Transfer Engine'!$C$2:$C$622,0)),"",INDEX('Compliance Database'!$O$2:$O$622,MATCH(6,'Transfer Engine'!$C$2:$C$622,0)))
A16: =IF(ISNA(MATCH(7,'Transfer Engine'!$C$2:$C$622,0)),"",INDEX('Compliance Database'!$A$2:$A$622,MATCH(7,'Transfer Engine'!$C$2:$C$622,0))) | B16: =IF(ISNA(MATCH(7,'Transfer Engine'!$C$2:$C$622,0)),"",INDEX('Compliance Database'!$B$2:$B$622,MATCH(7,'Transfer Engine'!$C$2:$C$622,0))) | C16: =IF(ISNA(MATCH(7,'Transfer Engine'!$C$2:$C$622,0)),"",INDEX('Compliance Database'!$C$2:$C$622,MATCH(7,'Transfer Engine'!$C$2:$C$622,0))) | D16: =IF(ISNA(MATCH(7,'Transfer Engine'!$C$2:$C$622,0)),"",INDEX('Compliance Database'!$D$2:$D$622,MATCH(7,'Transfer Engine'!$C$2:$C$622,0))) | E16: =IF(ISNA(MATCH(7,'Transfer Engine'!$C$2:$C$622,0)),"",INDEX('Compliance Database'!$E$2:$E$622,MATCH(7,'Transfer Engine'!$C$2:$C$622,0))) | F16: =IF(ISNA(MATCH(7,'Transfer Engine'!$C$2:$C$622,0)),"",INDEX('Compliance Database'!$F$2:$F$622,MATCH(7,'Transfer Engine'!$C$2:$C$622,0))) | G16: =IF(ISNA(MATCH(7,'Transfer Engine'!$C$2:$C$622,0)),"",INDEX('Compliance Database'!$G$2:$G$622,MATCH(7,'Transfer Engine'!$C$2:$C$622,0))) | H16: =IF(ISNA(MATCH(7,'Transfer Engine'!$C$2:$C$622,0)),"",INDEX('Compliance Database'!$H$2:$H$622,MATCH(7,'Transfer Engine'!$C$2:$C$622,0))) | I16: =IF(ISNA(MATCH(7,'Transfer Engine'!$C$2:$C$622,0)),"",INDEX('Compliance Database'!$I$2:$I$622,MATCH(7,'Transfer Engine'!$C$2:$C$622,0))) | J16: =IF(ISNA(MATCH(7,'Transfer Engine'!$C$2:$C$622,0)),"",INDEX('Compliance Database'!$J$2:$J$622,MATCH(7,'Transfer Engine'!$C$2:$C$622,0))) | K16: =IF(ISNA(MATCH(7,'Transfer Engine'!$C$2:$C$622,0)),"",INDEX('Compliance Database'!$K$2:$K$622,MATCH(7,'Transfer Engine'!$C$2:$C$622,0))) | L16: =IF(ISNA(MATCH(7,'Transfer Engine'!$C$2:$C$622,0)),"",INDEX('Compliance Database'!$L$2:$L$622,MATCH(7,'Transfer Engine'!$C$2:$C$622,0))) | M16: =IF(ISNA(MATCH(7,'Transfer Engine'!$C$2:$C$622,0)),"",INDEX('Compliance Database'!$M$2:$M$622,MATCH(7,'Transfer Engine'!$C$2:$C$622,0))) | N16: =IF(ISNA(MATCH(7,'Transfer Engine'!$C$2:$C$622,0)),"",INDEX('Compliance Database'!$N$2:$N$622,MATCH(7,'Transfer Engine'!$C$2:$C$622,0))) | O16: =IF(ISNA(MATCH(7,'Transfer Engine'!$C$2:$C$622,0)),"",INDEX('Compliance Database'!$O$2:$O$622,MATCH(7,'Transfer Engine'!$C$2:$C$622,0)))
A17: =IF(ISNA(MATCH(8,'Transfer Engine'!$C$2:$C$622,0)),"",INDEX('Compliance Database'!$A$2:$A$622,MATCH(8,'Transfer Engine'!$C$2:$C$622,0))) | B17: =IF(ISNA(MATCH(8,'Transfer Engine'!$C$2:$C$622,0)),"",INDEX('Compliance Database'!$B$2:$B$622,MATCH(8,'Transfer Engine'!$C$2:$C$622,0))) | C17: =IF(ISNA(MATCH(8,'Transfer Engine'!$C$2:$C$622,0)),"",INDEX('Compliance Database'!$C$2:$C$622,MATCH(8,'Transfer Engine'!$C$2:$C$622,0))) | D17: =IF(ISNA(MATCH(8,'Transfer Engine'!$C$2:$C$622,0)),"",INDEX('Compliance Database'!$D$2:$D$622,MATCH(8,'Transfer Engine'!$C$2:$C$622,0))) | E17: =IF(ISNA(MATCH(8,'Transfer Engine'!$C$2:$C$622,0)),"",INDEX('Compliance Database'!$E$2:$E$622,MATCH(8,'Transfer Engine'!$C$2:$C$622,0))) | F17: =IF(ISNA(MATCH(8,'Transfer Engine'!$C$2:$C$622,0)),"",INDEX('Compliance Database'!$F$2:$F$622,MATCH(8,'Transfer Engine'!$C$2:$C$622,0))) | G17: =IF(ISNA(MATCH(8,'Transfer Engine'!$C$2:$C$622,0)),"",INDEX('Compliance Database'!$G$2:$G$622,MATCH(8,'Transfer Engine'!$C$2:$C$622,0))) | H17: =IF(ISNA(MATCH(8,'Transfer Engine'!$C$2:$C$622,0)),"",INDEX('Compliance Database'!$H$2:$H$622,MATCH(8,'Transfer Engine'!$C$2:$C$622,0))) | I17: =IF(ISNA(MATCH(8,'Transfer Engine'!$C$2:$C$622,0)),"",INDEX('Compliance Database'!$I$2:$I$622,MATCH(8,'Transfer Engine'!$C$2:$C$622,0))) | J17: =IF(ISNA(MATCH(8,'Transfer Engine'!$C$2:$C$622,0)),"",INDEX('Compliance Database'!$J$2:$J$622,MATCH(8,'Transfer Engine'!$C$2:$C$622,0))) | K17: =IF(ISNA(MATCH(8,'Transfer Engine'!$C$2:$C$622,0)),"",INDEX('Compliance Database'!$K$2:$K$622,MATCH(8,'Transfer Engine'!$C$2:$C$622,0))) | L17: =IF(ISNA(MATCH(8,'Transfer Engine'!$C$2:$C$622,0)),"",INDEX('Compliance Database'!$L$2:$L$622,MATCH(8,'Transfer Engine'!$C$2:$C$622,0))) | M17: =IF(ISNA(MATCH(8,'Transfer Engine'!$C$2:$C$622,0)),"",INDEX('Compliance Database'!$M$2:$M$622,MATCH(8,'Transfer Engine'!$C$2:$C$622,0))) | N17: =IF(ISNA(MATCH(8,'Transfer Engine'!$C$2:$C$622,0)),"",INDEX('Compliance Database'!$N$2:$N$622,MATCH(8,'Transfer Engine'!$C$2:$C$622,0))) | O17: =IF(ISNA(MATCH(8,'Transfer Engine'!$C$2:$C$622,0)),"",INDEX('Compliance Database'!$O$2:$O$622,MATCH(8,'Transfer Engine'!$C$2:$C$622,0)))
A18: =IF(ISNA(MATCH(9,'Transfer Engine'!$C$2:$C$622,0)),"",INDEX('Compliance Database'!$A$2:$A$622,MATCH(9,'Transfer Engine'!$C$2:$C$622,0))) | B18: =IF(ISNA(MATCH(9,'Transfer Engine'!$C$2:$C$622,0)),"",INDEX('Compliance Database'!$B$2:$B$622,MATCH(9,'Transfer Engine'!$C$2:$C$622,0))) | C18: =IF(ISNA(MATCH(9,'Transfer Engine'!$C$2:$C$622,0)),"",INDEX('Compliance Database'!$C$2:$C$622,MATCH(9,'Transfer Engine'!$C$2:$C$622,0))) | D18: =IF(ISNA(MATCH(9,'Transfer Engine'!$C$2:$C$622,0)),"",INDEX('Compliance Database'!$D$2:$D$622,MATCH(9,'Transfer Engine'!$C$2:$C$622,0))) | E18: =IF(ISNA(MATCH(9,'Transfer Engine'!$C$2:$C$622,0)),"",INDEX('Compliance Database'!$E$2:$E$622,MATCH(9,'Transfer Engine'!$C$2:$C$622,0))) | F18: =IF(ISNA(MATCH(9,'Transfer Engine'!$C$2:$C$622,0)),"",INDEX('Compliance Database'!$F$2:$F$622,MATCH(9,'Transfer Engine'!$C$2:$C$622,0))) | G18: =IF(ISNA(MATCH(9,'Transfer Engine'!$C$2:$C$622,0)),"",INDEX('Compliance Database'!$G$2:$G$622,MATCH(9,'Transfer Engine'!$C$2:$C$622,0))) | H18: =IF(ISNA(MATCH(9,'Transfer Engine'!$C$2:$C$622,0)),"",INDEX('Compliance Database'!$H$2:$H$622,MATCH(9,'Transfer Engine'!$C$2:$C$622,0))) | I18: =IF(ISNA(MATCH(9,'Transfer Engine'!$C$2:$C$622,0)),"",INDEX('Compliance Database'!$I$2:$I$622,MATCH(9,'Transfer Engine'!$C$2:$C$622,0))) | J18: =IF(ISNA(MATCH(9,'Transfer Engine'!$C$2:$C$622,0)),"",INDEX('Compliance Database'!$J$2:$J$622,MATCH(9,'Transfer Engine'!$C$2:$C$622,0))) | K18: =IF(ISNA(MATCH(9,'Transfer Engine'!$C$2:$C$622,0)),"",INDEX('Compliance Database'!$K$2:$K$622,MATCH(9,'Transfer Engine'!$C$2:$C$622,0))) | L18: =IF(ISNA(MATCH(9,'Transfer Engine'!$C$2:$C$622,0)),"",INDEX('Compliance Database'!$L$2:$L$622,MATCH(9,'Transfer Engine'!$C$2:$C$622,0))) | M18: =IF(ISNA(MATCH(9,'Transfer Engine'!$C$2:$C$622,0)),"",INDEX('Compliance Database'!$M$2:$M$622,MATCH(9,'Transfer Engine'!$C$2:$C$622,0))) | N18: =IF(ISNA(MATCH(9,'Transfer Engine'!$C$2:$C$622,0)),"",INDEX('Compliance Database'!$N$2:$N$622,MATCH(9,'Transfer Engine'!$C$2:$C$622,0))) | O18: =IF(ISNA(MATCH(9,'Transfer Engine'!$C$2:$C$622,0)),"",INDEX('Compliance Database'!$O$2:$O$622,MATCH(9,'Transfer Engine'!$C$2:$C$622,0)))
A19: =IF(ISNA(MATCH(10,'Transfer Engine'!$C$2:$C$622,0)),"",INDEX('Compliance Database'!$A$2:$A$622,MATCH(10,'Transfer Engine'!$C$2:$C$622,0))) | B19: =IF(ISNA(MATCH(10,'Transfer Engine'!$C$2:$C$622,0)),"",INDEX('Compliance Database'!$B$2:$B$622,MATCH(10,'Transfer Engine'!$C$2:$C$622,0))) | C19: =IF(ISNA(MATCH(10,'Transfer Engine'!$C$2:$C$622,0)),"",INDEX('Compliance Database'!$C$2:$C$622,MATCH(10,'Transfer Engine'!$C$2:$C$622,0))) | D19: =IF(ISNA(MATCH(10,'Transfer Engine'!$C$2:$C$622,0)),"",INDEX('Compliance Database'!$D$2:$D$622,MATCH(10,'Transfer Engine'!$C$2:$C$622,0))) | E19: =IF(ISNA(MATCH(10,'Transfer Engine'!$C$2:$C$622,0)),"",INDEX('Compliance Database'!$E$2:$E$622,MATCH(10,'Transfer Engine'!$C$2:$C$622,0))) | F19: =IF(ISNA(MATCH(10,'Transfer Engine'!$C$2:$C$622,0)),"",INDEX('Compliance Database'!$F$2:$F$622,MATCH(10,'Transfer Engine'!$C$2:$C$622,0))) | G19: =IF(ISNA(MATCH(10,'Transfer Engine'!$C$2:$C$622,0)),"",INDEX('Compliance Database'!$G$2:$G$622,MATCH(10,'Transfer Engine'!$C$2:$C$622,0))) | H19: =IF(ISNA(MATCH(10,'Transfer Engine'!$C$2:$C$622,0)),"",INDEX('Compliance Database'!$H$2:$H$622,MATCH(10,'Transfer Engine'!$C$2:$C$622,0))) | I19: =IF(ISNA(MATCH(10,'Transfer Engine'!$C$2:$C$622,0)),"",INDEX('Compliance Database'!$I$2:$I$622,MATCH(10,'Transfer Engine'!$C$2:$C$622,0))) | J19: =IF(ISNA(MATCH(10,'Transfer Engine'!$C$2:$C$622,0)),"",INDEX('Compliance Database'!$J$2:$J$622,MATCH(10,'Transfer Engine'!$C$2:$C$622,0))) | K19: =IF(ISNA(MATCH(10,'Transfer Engine'!$C$2:$C$622,0)),"",INDEX('Compliance Database'!$K$2:$K$622,MATCH(10,'Transfer Engine'!$C$2:$C$622,0))) | L19: =IF(ISNA(MATCH(10,'Transfer Engine'!$C$2:$C$622,0)),"",INDEX('Compliance Database'!$L$2:$L$622,MATCH(10,'Transfer Engine'!$C$2:$C$622,0))) | M19: =IF(ISNA(MATCH(10,'Transfer Engine'!$C$2:$C$622,0)),"",INDEX('Compliance Database'!$M$2:$M$622,MATCH(10,'Transfer Engine'!$C$2:$C$622,0))) | N19: =IF(ISNA(MATCH(10,'Transfer Engine'!$C$2:$C$622,0)),"",INDEX('Compliance Database'!$N$2:$N$622,MATCH(10,'Transfer Engine'!$C$2:$C$622,0))) | O19: =IF(ISNA(MATCH(10,'Transfer Engine'!$C$2:$C$622,0)),"",INDEX('Compliance Database'!$O$2:$O$622,MATCH(10,'Transfer Engine'!$C$2:$C$622,0)))
A20: =IF(ISNA(MATCH(11,'Transfer Engine'!$C$2:$C$622,0)),"",INDEX('Compliance Database'!$A$2:$A$622,MATCH(11,'Transfer Engine'!$C$2:$C$622,0))) | B20: =IF(ISNA(MATCH(11,'Transfer Engine'!$C$2:$C$622,0)),"",INDEX('Compliance Database'!$B$2:$B$622,MATCH(11,'Transfer Engine'!$C$2:$C$622,0))) | C20: =IF(ISNA(MATCH(11,'Transfer Engine'!$C$2:$C$622,0)),"",INDEX('Compliance Database'!$C$2:$C$622,MATCH(11,'Transfer Engine'!$C$2:$C$622,0))) | D20: =IF(ISNA(MATCH(11,'Transfer Engine'!$C$2:$C$622,0)),"",INDEX('Compliance Database'!$D$2:$D$622,MATCH(11,'Transfer Engine'!$C$2:$C$622,0))) | E20: =IF(ISNA(MATCH(11,'Transfer Engine'!$C$2:$C$622,0)),"",INDEX('Compliance Database'!$E$2:$E$622,MATCH(11,'Transfer Engine'!$C$2:$C$622,0))) | F20: =IF(ISNA(MATCH(11,'Transfer Engine'!$C$2:$C$622,0)),"",INDEX('Compliance Database'!$F$2:$F$622,MATCH(11,'Transfer Engine'!$C$2:$C$622,0))) | G20: =IF(ISNA(MATCH(11,'Transfer Engine'!$C$2:$C$622,0)),"",INDEX('Compliance Database'!$G$2:$G$622,MATCH(11,'Transfer Engine'!$C$2:$C$622,0))) | H20: =IF(ISNA(MATCH(11,'Transfer Engine'!$C$2:$C$622,0)),"",INDEX('Compliance Database'!$H$2:$H$622,MATCH(11,'Transfer Engine'!$C$2:$C$622,0))) | I20: =IF(ISNA(MATCH(11,'Transfer Engine'!$C$2:$C$622,0)),"",INDEX('Compliance Database'!$I$2:$I$622,MATCH(11,'Transfer Engine'!$C$2:$C$622,0))) | J20: =IF(ISNA(MATCH(11,'Transfer Engine'!$C$2:$C$622,0)),"",INDEX('Compliance Database'!$J$2:$J$622,MATCH(11,'Transfer Engine'!$C$2:$C$622,0))) | K20: =IF(ISNA(MATCH(11,'Transfer Engine'!$C$2:$C$622,0)),"",INDEX('Compliance Database'!$K$2:$K$622,MATCH(11,'Transfer Engine'!$C$2:$C$622,0))) | L20: =IF(ISNA(MATCH(11,'Transfer Engine'!$C$2:$C$622,0)),"",INDEX('Compliance Database'!$L$2:$L$622,MATCH(11,'Transfer Engine'!$C$2:$C$622,0))) | M20: =IF(ISNA(MATCH(11,'Transfer Engine'!$C$2:$C$622,0)),"",INDEX('Compliance Database'!$M$2:$M$622,MATCH(11,'Transfer Engine'!$C$2:$C$622,0))) | N20: =IF(ISNA(MATCH(11,'Transfer Engine'!$C$2:$C$622,0)),"",INDEX('Compliance Database'!$N$2:$N$622,MATCH(11,'Transfer Engine'!$C$2:$C$622,0))) | O20: =IF(ISNA(MATCH(11,'Transfer Engine'!$C$2:$C$622,0)),"",INDEX('Compliance Database'!$O$2:$O$622,MATCH(11,'Transfer Engine'!$C$2:$C$622,0)))
A21: =IF(ISNA(MATCH(12,'Transfer Engine'!$C$2:$C$622,0)),"",INDEX('Compliance Database'!$A$2:$A$622,MATCH(12,'Transfer Engine'!$C$2:$C$622,0))) | B21: =IF(ISNA(MATCH(12,'Transfer Engine'!$C$2:$C$622,0)),"",INDEX('Compliance Database'!$B$2:$B$622,MATCH(12,'Transfer Engine'!$C$2:$C$622,0))) | C21: =IF(ISNA(MATCH(12,'Transfer Engine'!$C$2:$C$622,0)),"",INDEX('Compliance Database'!$C$2:$C$622,MATCH(12,'Transfer Engine'!$C$2:$C$622,0))) | D21: =IF(ISNA(MATCH(12,'Transfer Engine'!$C$2:$C$622,0)),"",INDEX('Compliance Database'!$D$2:$D$622,MATCH(12,'Transfer Engine'!$C$2:$C$622,0))) | E21: =IF(ISNA(MATCH(12,'Transfer Engine'!$C$2:$C$622,0)),"",INDEX('Compliance Database'!$E$2:$E$622,MATCH(12,'Transfer Engine'!$C$2:$C$622,0))) | F21: =IF(ISNA(MATCH(12,'Transfer Engine'!$C$2:$C$622,0)),"",INDEX('Compliance Database'!$F$2:$F$622,MATCH(12,'Transfer Engine'!$C$2:$C$622,0))) | G21: =IF(ISNA(MATCH(12,'Transfer Engine'!$C$2:$C$622,0)),"",INDEX('Compliance Database'!$G$2:$G$622,MATCH(12,'Transfer Engine'!$C$2:$C$622,0))) | H21: =IF(ISNA(MATCH(12,'Transfer Engine'!$C$2:$C$622,0)),"",INDEX('Compliance Database'!$H$2:$H$622,MATCH(12,'Transfer Engine'!$C$2:$C$622,0))) | I21: =IF(ISNA(MATCH(12,'Transfer Engine'!$C$2:$C$622,0)),"",INDEX('Compliance Database'!$I$2:$I$622,MATCH(12,'Transfer Engine'!$C$2:$C$622,0))) | J21: =IF(ISNA(MATCH(12,'Transfer Engine'!$C$2:$C$622,0)),"",INDEX('Compliance Database'!$J$2:$J$622,MATCH(12,'Transfer Engine'!$C$2:$C$622,0))) | K21: =IF(ISNA(MATCH(12,'Transfer Engine'!$C$2:$C$622,0)),"",INDEX('Compliance Database'!$K$2:$K$622,MATCH(12,'Transfer Engine'!$C$2:$C$622,0))) | L21: =IF(ISNA(MATCH(12,'Transfer Engine'!$C$2:$C$622,0)),"",INDEX('Compliance Database'!$L$2:$L$622,MATCH(12,'Transfer Engine'!$C$2:$C$622,0))) | M21: =IF(ISNA(MATCH(12,'Transfer Engine'!$C$2:$C$622,0)),"",INDEX('Compliance Database'!$M$2:$M$622,MATCH(12,'Transfer Engine'!$C$2:$C$622,0))) | N21: =IF(ISNA(MATCH(12,'Transfer Engine'!$C$2:$C$622,0)),"",INDEX('Compliance Database'!$N$2:$N$622,MATCH(12,'Transfer Engine'!$C$2:$C$622,0))) | O21: =IF(ISNA(MATCH(12,'Transfer Engine'!$C$2:$C$622,0)),"",INDEX('Compliance Database'!$O$2:$O$622,MATCH(12,'Transfer Engine'!$C$2:$C$622,0)))
A22: =IF(ISNA(MATCH(13,'Transfer Engine'!$C$2:$C$622,0)),"",INDEX('Compliance Database'!$A$2:$A$622,MATCH(13,'Transfer Engine'!$C$2:$C$622,0))) | B22: =IF(ISNA(MATCH(13,'Transfer Engine'!$C$2:$C$622,0)),"",INDEX('Compliance Database'!$B$2:$B$622,MATCH(13,'Transfer Engine'!$C$2:$C$622,0))) | C22: =IF(ISNA(MATCH(13,'Transfer Engine'!$C$2:$C$622,0)),"",INDEX('Compliance Database'!$C$2:$C$622,MATCH(13,'Transfer Engine'!$C$2:$C$622,0))) | D22: =IF(ISNA(MATCH(13,'Transfer Engine'!$C$2:$C$622,0)),"",INDEX('Compliance Database'!$D$2:$D$622,MATCH(13,'Transfer Engine'!$C$2:$C$622,0))) | E22: =IF(ISNA(MATCH(13,'Transfer Engine'!$C$2:$C$622,0)),"",INDEX('Compliance Database'!$E$2:$E$622,MATCH(13,'Transfer Engine'!$C$2:$C$622,0))) | F22: =IF(ISNA(MATCH(13,'Transfer Engine'!$C$2:$C$622,0)),"",INDEX('Compliance Database'!$F$2:$F$622,MATCH(13,'Transfer Engine'!$C$2:$C$622,0))) | G22: =IF(ISNA(MATCH(13,'Transfer Engine'!$C$2:$C$622,0)),"",INDEX('Compliance Database'!$G$2:$G$622,MATCH(13,'Transfer Engine'!$C$2:$C$622,0))) | H22: =IF(ISNA(MATCH(13,'Transfer Engine'!$C$2:$C$622,0)),"",INDEX('Compliance Database'!$H$2:$H$622,MATCH(13,'Transfer Engine'!$C$2:$C$622,0))) | I22: =IF(ISNA(MATCH(13,'Transfer Engine'!$C$2:$C$622,0)),"",INDEX('Compliance Database'!$I$2:$I$622,MATCH(13,'Transfer Engine'!$C$2:$C$622,0))) | J22: =IF(ISNA(MATCH(13,'Transfer Engine'!$C$2:$C$622,0)),"",INDEX('Compliance Database'!$J$2:$J$622,MATCH(13,'Transfer Engine'!$C$2:$C$622,0))) | K22: =IF(ISNA(MATCH(13,'Transfer Engine'!$C$2:$C$622,0)),"",INDEX('Compliance Database'!$K$2:$K$622,MATCH(13,'Transfer Engine'!$C$2:$C$622,0))) | L22: =IF(ISNA(MATCH(13,'Transfer Engine'!$C$2:$C$622,0)),"",INDEX('Compliance Database'!$L$2:$L$622,MATCH(13,'Transfer Engine'!$C$2:$C$622,0))) | M22: =IF(ISNA(MATCH(13,'Transfer Engine'!$C$2:$C$622,0)),"",INDEX('Compliance Database'!$M$2:$M$622,MATCH(13,'Transfer Engine'!$C$2:$C$622,0))) | N22: =IF(ISNA(MATCH(13,'Transfer Engine'!$C$2:$C$622,0)),"",INDEX('Compliance Database'!$N$2:$N$622,MATCH(13,'Transfer Engine'!$C$2:$C$622,0))) | O22: =IF(ISNA(MATCH(13,'Transfer Engine'!$C$2:$C$622,0)),"",INDEX('Compliance Database'!$O$2:$O$622,MATCH(13,'Transfer Engine'!$C$2:$C$622,0)))
A23: =IF(ISNA(MATCH(14,'Transfer Engine'!$C$2:$C$622,0)),"",INDEX('Compliance Database'!$A$2:$A$622,MATCH(14,'Transfer Engine'!$C$2:$C$622,0))) | B23: =IF(ISNA(MATCH(14,'Transfer Engine'!$C$2:$C$622,0)),"",INDEX('Compliance Database'!$B$2:$B$622,MATCH(14,'Transfer Engine'!$C$2:$C$622,0))) | C23: =IF(ISNA(MATCH(14,'Transfer Engine'!$C$2:$C$622,0)),"",INDEX('Compliance Database'!$C$2:$C$622,MATCH(14,'Transfer Engine'!$C$2:$C$622,0))) | D23: =IF(ISNA(MATCH(14,'Transfer Engine'!$C$2:$C$622,0)),"",INDEX('Compliance Database'!$D$2:$D$622,MATCH(14,'Transfer Engine'!$C$2:$C$622,0))) | E23: =IF(ISNA(MATCH(14,'Transfer Engine'!$C$2:$C$622,0)),"",INDEX('Compliance Database'!$E$2:$E$622,MATCH(14,'Transfer Engine'!$C$2:$C$622,0))) | F23: =IF(ISNA(MATCH(14,'Transfer Engine'!$C$2:$C$622,0)),"",INDEX('Compliance Database'!$F$2:$F$622,MATCH(14,'Transfer Engine'!$C$2:$C$622,0))) | G23: =IF(ISNA(MATCH(14,'Transfer Engine'!$C$2:$C$622,0)),"",INDEX('Compliance Database'!$G$2:$G$622,MATCH(14,'Transfer Engine'!$C$2:$C$622,0))) | H23: =IF(ISNA(MATCH(14,'Transfer Engine'!$C$2:$C$622,0)),"",INDEX('Compliance Database'!$H$2:$H$622,MATCH(14,'Transfer Engine'!$C$2:$C$622,0))) | I23: =IF(ISNA(MATCH(14,'Transfer Engine'!$C$2:$C$622,0)),"",INDEX('Compliance Database'!$I$2:$I$622,MATCH(14,'Transfer Engine'!$C$2:$C$622,0))) | J23: =IF(ISNA(MATCH(14,'Transfer Engine'!$C$2:$C$622,0)),"",INDEX('Compliance Database'!$J$2:$J$622,MATCH(14,'Transfer Engine'!$C$2:$C$622,0))) | K23: =IF(ISNA(MATCH(14,'Transfer Engine'!$C$2:$C$622,0)),"",INDEX('Compliance Database'!$K$2:$K$622,MATCH(14,'Transfer Engine'!$C$2:$C$622,0))) | L23: =IF(ISNA(MATCH(14,'Transfer Engine'!$C$2:$C$622,0)),"",INDEX('Compliance Database'!$L$2:$L$622,MATCH(14,'Transfer Engine'!$C$2:$C$622,0))) | M23: =IF(ISNA(MATCH(14,'Transfer Engine'!$C$2:$C$622,0)),"",INDEX('Compliance Database'!$M$2:$M$622,MATCH(14,'Transfer Engine'!$C$2:$C$622,0))) | N23: =IF(ISNA(MATCH(14,'Transfer Engine'!$C$2:$C$622,0)),"",INDEX('Compliance Database'!$N$2:$N$622,MATCH(14,'Transfer Engine'!$C$2:$C$622,0))) | O23: =IF(ISNA(MATCH(14,'Transfer Engine'!$C$2:$C$622,0)),"",INDEX('Compliance Database'!$O$2:$O$622,MATCH(14,'Transfer Engine'!$C$2:$C$622,0)))
A24: =IF(ISNA(MATCH(15,'Transfer Engine'!$C$2:$C$622,0)),"",INDEX('Compliance Database'!$A$2:$A$622,MATCH(15,'Transfer Engine'!$C$2:$C$622,0))) | B24: =IF(ISNA(MATCH(15,'Transfer Engine'!$C$2:$C$622,0)),"",INDEX('Compliance Database'!$B$2:$B$622,MATCH(15,'Transfer Engine'!$C$2:$C$622,0))) | C24: =IF(ISNA(MATCH(15,'Transfer Engine'!$C$2:$C$622,0)),"",INDEX('Compliance Database'!$C$2:$C$622,MATCH(15,'Transfer Engine'!$C$2:$C$622,0))) | D24: =IF(ISNA(MATCH(15,'Transfer Engine'!$C$2:$C$622,0)),"",INDEX('Compliance Database'!$D$2:$D$622,MATCH(15,'Transfer Engine'!$C$2:$C$622,0))) | E24: =IF(ISNA(MATCH(15,'Transfer Engine'!$C$2:$C$622,0)),"",INDEX('Compliance Database'!$E$2:$E$622,MATCH(15,'Transfer Engine'!$C$2:$C$622,0))) | F24: =IF(ISNA(MATCH(15,'Transfer Engine'!$C$2:$C$622,0)),"",INDEX('Compliance Database'!$F$2:$F$622,MATCH(15,'Transfer Engine'!$C$2:$C$622,0))) | G24: =IF(ISNA(MATCH(15,'Transfer Engine'!$C$2:$C$622,0)),"",INDEX('Compliance Database'!$G$2:$G$622,MATCH(15,'Transfer Engine'!$C$2:$C$622,0))) | H24: =IF(ISNA(MATCH(15,'Transfer Engine'!$C$2:$C$622,0)),"",INDEX('Compliance Database'!$H$2:$H$622,MATCH(15,'Transfer Engine'!$C$2:$C$622,0))) | I24: =IF(ISNA(MATCH(15,'Transfer Engine'!$C$2:$C$622,0)),"",INDEX('Compliance Database'!$I$2:$I$622,MATCH(15,'Transfer Engine'!$C$2:$C$622,0))) | J24: =IF(ISNA(MATCH(15,'Transfer Engine'!$C$2:$C$622,0)),"",INDEX('Compliance Database'!$J$2:$J$622,MATCH(15,'Transfer Engine'!$C$2:$C$622,0))) | K24: =IF(ISNA(MATCH(15,'Transfer Engine'!$C$2:$C$622,0)),"",INDEX('Compliance Database'!$K$2:$K$622,MATCH(15,'Transfer Engine'!$C$2:$C$622,0))) | L24: =IF(ISNA(MATCH(15,'Transfer Engine'!$C$2:$C$622,0)),"",INDEX('Compliance Database'!$L$2:$L$622,MATCH(15,'Transfer Engine'!$C$2:$C$622,0))) | M24: =IF(ISNA(MATCH(15,'Transfer Engine'!$C$2:$C$622,0)),"",INDEX('Compliance Database'!$M$2:$M$622,MATCH(15,'Transfer Engine'!$C$2:$C$622,0))) | N24: =IF(ISNA(MATCH(15,'Transfer Engine'!$C$2:$C$622,0)),"",INDEX('Compliance Database'!$N$2:$N$622,MATCH(15,'Transfer Engine'!$C$2:$C$622,0))) | O24: =IF(ISNA(MATCH(15,'Transfer Engine'!$C$2:$C$622,0)),"",INDEX('Compliance Database'!$O$2:$O$622,MATCH(15,'Transfer Engine'!$C$2:$C$622,0)))
